Workbook

Sheet jan22
C2: RELATÓRIO MENSAL DE ACOMPANHAMENTO DO CUSTO DO GÁS
C3: 44562
C5: Petrobras | D5: =SUMIF($C$18:$G$40,$C$5:$C$7,$G$18:$G$40)/SUMIF($C$18:$G$40,$C$5:$C$7,$E$18:$E$40) -> 2.0108289
C6: Shell | D6: =SUMIF($C$18:$G$40,$C$5:$C$7,$G$18:$G$40)/SUMIF($C$18:$G$40,$C$5:$C$7,$E$18:$E$40) -> 2.055651
C7: NFE | D7: =SUM(G33:G34)/SUM(E33:E34) -> 3.1718472
M8: Poderação QDC | N8: Poderação QDR
C9: Custo Médio Ponderado real | D9: =+G45/E45 -> 2.0452406 | L9: =+C5 -> Petrobras | M9: =790000/1580000 -> 0.5 | N9: =+SUM(E18:E31)/E45 -> 0.46550278
L10: =+C6 -> Shell | M10: 0.47468354 | N10: =+E32/E45 -> 0.5251311
C11: Custo Médio Ponderado tarifa | D11: 2.025 | L11: =+C7 -> NFE | M11: 0.025316456 | N11: =+SUM(E33:E34)/E45 -> 0.0093661186
L12: Total | M12: =SUM(M9:M11) -> 1 | N12: =SUM(N9:N11) -> 1
L16: CONFORME XML DA NOTA
B17: Mês | C17: Supridor | D17: Nota Fiscal | E17: Vol m³ | F17: Compra R$ c/tributos | G17: Compra R$ s/tributos | H17: Custo | I17: ICMS | J17: PIS | K17: COFINS | L17: ICMS | M17: PIS | N17: COFINS
B18: 44562 | C18: Petrobras | D18: 10497-6 | E18: 30483 | F18: 77719.07 | G18: =F18-SUM(L18:N18) -> 61203.768 | H18: =+IF(G18=0,0,G18/E18) -> 2.0078 | I18: 0.12 | J18: 0.0165 | K18: 0.076 | L18: =+I18*F18 -> 9326.2884 | M18: =+F18*J18 -> 1282.3647 | N18: =K18*F18 -> 5906.6493
B19: 44562 | C19: Petrobras | D19: 4820-24 | E19: 3484310 | F19: 8883552.5 | G19: =F19-SUM(L19:N19) -> 6995797.6 | H19: =+IF(G19=0,0,G19/E19) -> 2.0078 | I19: 0.12 | J19: 0.0165 | K19: 0.076 | L19: =+I19*F19 -> 1066026.3 | M19: =+F19*J19 -> 146578.62 | N19: =K19*F19 -> 675149.99
B20: 44562 | C20: Petrobras | D20: 10499-6 | E20: 3507754 | F20: 8943325 | G20: =F20-SUM(L20:N20) -> 7042868.5 | H20: =+IF(G20=0,0,G20/E20) -> 2.0078 | I20: 0.12 | J20: 0.0165 | K20: 0.076 | L20: =+I20*F20 -> 1073199 | M20: =+F20*J20 -> 147564.86 | N20: =K20*F20 -> 679692.7
B21: 44562 | C21: Petrobras | D21: 3401-12 | E21: 3129545 | F21: 7979048.2 | G21: =F21-SUM(L21:N21) -> 6283500.4 | H21: =+IF(G21=0,0,G21/E21) -> 2.0078 | I21: 0.12 | J21: 0.0165 | K21: 0.076 | L21: =+I21*F21 -> 957485.78 | M21: =+F21*J21 -> 131654.3 | N21: =K21*F21 -> 606407.66
B22: 44562 | C22: Petrobras | D22: 4758-4 | E22: 9448559 | F22: 24089926 | G22: =F22-SUM(L22:N22) -> 18970817 | H22: =+IF(G22=0,0,G22/E22) -> 2.0078 | I22: 0.12 | J22: 0.0165 | K22: 0.076 | L22: =+I22*F22 -> 2890791.1 | M22: =+F22*J22 -> 397483.78 | N22: =K22*F22 -> 1830834.4
B23: 44562 | C23: Petrobras | D23: 430266-2 | E23: 3889558 | F23: 9324721.9 | G23: =F23-SUM(L23:N23) -> 7809454.5 | H23: =+IF(G23=0,0,G23/E23) -> 2.0078 | I23: 0.07 | J23: 0.0165 | K23: 0.076 | L23: =+I23*F23 -> 652730.53 | M23: =+F23*J23 -> 153857.91 | N23: =K23*F23 -> 708678.86
B24: 44562 | C24: Petrobras | D24: 3193-28 | E24: 232008 | F24: 591524.65 | G24: =F24-SUM(L24:N24) -> 465825.66 | H24: =+IF(G24=0,0,G24/E24) -> 2.0078 | I24: 0.12 | J24: 0.0165 | K24: 0.076 | L24: =+I24*F24 -> 70982.958 | M24: =+F24*J24 -> 9760.1567 | N24: =K24*F24 -> 44955.873
B25: 44562 | C25: Petrobras | D25: 3992-4 | E25: 41095 | F25: 104775.29 | G25: =F25-SUM(L25:N25) -> 82510.541 | H25: =+IF(G25=0,0,G25/E25) -> 2.0078 | I25: 0.12 | J25: 0.0165 | K25: 0.076 | L25: =+I25*F25 -> 12573.035 | M25: =+F25*J25 -> 1728.7923 | N25: =K25*F25 -> 7962.922
B26: 44562 | C26: Petrobras | D26: 10498-6 | E26: 786 | F26: 2833.99 | G26: =F26-SUM(L26:N26) -> 2231.7671 | H26: =+IF(G26=0,0,G26/E26) -> 2.8393984 | I26: 0.12 | J26: 0.0165 | K26: 0.076 | L26: =+I26*F26 -> 340.0788 | M26: =+F26*J26 -> 46.760835 | N26: =K26*F26 -> 215.38324
B27: 44562 | C27: Petrobras | D27: 4821-24 | E27: 15676 | F27: 56521.18 | G27: =F27-SUM(L27:N27) -> 44510.429 | H27: =+IF(G27=0,0,G27/E27) -> 2.8393997 | I27: 0.12 | J27: 0.0165 | K27: 0.076 | L27: =+I27*F27 -> 6782.5416 | M27: =+F27*J27 -> 932.59947 | N27: =K27*F27 -> 4295.6097
B28: 44562 | C28: Petrobras | D28: 3402-12 | E28: 4810 | F28: 17342.87 | G28: =F28-SUM(L28:N28) -> 13657.51 | H28: =+IF(G28=0,0,G28/E28) -> 2.8393992 | I28: 0.12 | J28: 0.0165 | K28: 0.076 | L28: =+I28*F28 -> 2081.1444 | M28: =+F28*J28 -> 286.15736 | N28: =K28*F28 -> 1318.0581
B29: 44562 | C29: Petrobras | D29: 4759-4 | E29: 12211 | F29: 44027.82 | G29: =F29-SUM(L29:N29) -> 34671.908 | H29: =+IF(G29=0,0,G29/E29) -> 2.8393996 | I29: 0.12 | J29: 0.0165 | K29: 0.076 | L29: =+I29*F29 -> 5283.3384 | M29: =+F29*J29 -> 726.45903 | N29: =K29*F29 -> 3346.1143
... B31: 44562 | C31: Petrobras | D31: 10500-6 | E31: 19004 | F31: 68520.58 | G31: =F31-SUM(L31:N31) -> 53959.957 | H31: =+IF(G31=0,0,G31/E31) -> 2.8394 | I31: 0.12 | J31: 0.0165 | K31: 0.076 | L31: =+I31*F31 -> 8222.4696 | M31: =+F31*J31 -> 1130.5896 | N31: =K31*F31 -> 5207.5641
B32: 44562 | C32: Shell | D32: 14-1 | E32: 26905255 | F32: 65532528 | G32: =F32-SUM(L32:N32) -> 55307816 | H32: =+IF(G32=0,0,G32/E32) -> 2.055651 | I32: 0.07 | J32: 0.0165 | K32: 0.076 | L32: =+I32*F32 -> 4587277 | M32: =+(F32-L32)*J32 -> 1005596.6 | N32: =+(F32-L32)*K32 -> 4631839.1
B33: 44562 | C33: New Fortress (Petrolina) | D33: 9-1 | E33: 453796 | F33: 1937391.3 | G33: =F33-SUM(L33:N33) -> 1441709.7 | H33: =+IF(G33=0,0,G33/E33) -> 3.1769996 | I33: 0.18 | J33: 0.0165 | K33: 0.076 | L33: =+I33*F33 -> 348730.43 | M33: =+(F33-L33)*J33 -> 26212.904 | N33: =+(F33-L33)*K33 -> 120738.22
B34: 44562 | C34: New Fortress (Garanhuns) | D34: 3-1 | E34: 26080 | F34: 108020.75 | G34: =F34-SUM(L34:N34) -> 80383.641 | H34: =+IF(G34=0,0,G34/E34) -> 3.0821948 | I34: 0.18 | J34: 0.0165 | K34: 0.076 | L34: =+I34*F34 -> 19443.735 | M34: =+(F34-L34)*J34 -> 1461.5207 | N34: =+(F34-L34)*K34 -> 6731.8531
E45: =SUM(E18:E34) -> 51235311 | G45: =SUM(G18:G34) -> 1.0478854e+08
B48: Observações Relevantes:

Sheet fev22
C2: RELATÓRIO MENSAL DE ACOMPANHAMENTO DO CUSTO DO GÁS
C3: 44593
C5: Petrobras | D5: =SUMIF($C$18:$G$40,$C$5:$C$7,$G$18:$G$40)/SUMIF($C$18:$G$40,$C$5:$C$7,$E$18:$E$40) -> 2.3132459
C6: Shell | D6: =SUMIF($C$18:$G$40,$C$5:$C$7,$G$18:$G$40)/SUMIF($C$18:$G$40,$C$5:$C$7,$E$18:$E$40) -> 1.7200042
C7: NFE | D7: =SUM(G33:G34)/SUM(E33:E34) -> 3.4477245
M8: Poderação QDC | N8: Poderação QDR
C9: Custo Médio Ponderado real | D9: =+G45/E45 -> 2.0428354 | L9: =+C5 -> Petrobras | M9: =790000/1580000 -> 0.5 | N9: =+SUM(E18:E31)/E45 -> 0.50481329
L10: =+C6 -> Shell | M10: 0.47468354 | N10: =+E32/E45 -> 0.48166893
C11: Custo Médio Ponderado tarifa | D11: 2.025 | L11: =+C7 -> NFE | M11: 0.025316456 | N11: =+SUM(E33:E34)/E45 -> 0.01351778
L12: Total | M12: =SUM(M9:M11) -> 1 | N12: =SUM(N9:N11) -> 1
L16: CONFORME XML DA NOTA
B17: Mês | C17: Supridor | D17: Nota Fiscal | E17: Vol m³ | F17: Compra R$ c/tributos | G17: Compra R$ s/tributos | H17: Custo | I17: ICMS | J17: PIS | K17: COFINS | L17: ICMS | M17: PIS | N17: COFINS
B18: 44593 | C18: Petrobras | D18: 4879-24 | E18: 768484 | F18: 2217625.3 | G18: =F18-SUM(L18:N18) -> 1746379.9 | H18: =+IF(G18=0,0,G18/E18) -> 2.2725 | I18: 0.12 | J18: 0.0165 | K18: 0.076 | L18: =+I18*F18 -> 266115.03 | M18: =+F18*J18 -> 36590.817 | N18: =K18*F18 -> 168539.52
B19: 44593 | C19: Petrobras | D19: 3432-12 | E19: 245003 | F19: 707008.66 | G19: =F19-SUM(L19:N19) -> 556769.32 | H19: =+IF(G19=0,0,G19/E19) -> 2.2725 | I19: 0.12 | J19: 0.0165 | K19: 0.076 | L19: =+I19*F19 -> 84841.039 | M19: =+F19*J19 -> 11665.643 | N19: =K19*F19 -> 53732.658
B20: 44593 | C20: Petrobras | D20: 10595-6 | E20: 1145411 | F20: 3305328.9 | G20: =F20-SUM(L20:N20) -> 2602946.5 | H20: =+IF(G20=0,0,G20/E20) -> 2.2725 | I20: 0.12 | J20: 0.0165 | K20: 0.076 | L20: =+I20*F20 -> 396639.47 | M20: =+F20*J20 -> 54537.927 | N20: =K20*F20 -> 251205
B21: 44593 | C21: Petrobras | D21: 4813-4 | E21: 10273133 | F21: 29645327 | G21: =F21-SUM(L21:N21) -> 23345695 | H21: =+IF(G21=0,0,G21/E21) -> 2.2725 | I21: 0.12 | J21: 0.0165 | K21: 0.076 | L21: =+I21*F21 -> 3557439.2 | M21: =+F21*J21 -> 489147.89 | N21: =K21*F21 -> 2253044.8
B22: 44593 | C22: Petrobras | D22: 3245-28 | E22: 23935 | F22: 69069.57 | G22: =F22-SUM(L22:N22) -> 54392.286 | H22: =+IF(G22=0,0,G22/E22) -> 2.2725 | I22: 0.12 | J22: 0.0165 | K22: 0.076 | L22: =+I22*F22 -> 8288.3484 | M22: =+F22*J22 -> 1139.6479 | N22: =K22*F22 -> 5249.2873
B23: 44593 | C23: Petrobras | D23: 430396-2 | E23: 10337821 | F23: 28050983 | G23: =F23-SUM(L23:N23) -> 23492698 | H23: =+IF(G23=0,0,G23/E23) -> 2.2725 | I23: 0.07 | J23: 0.0165 | K23: 0.076 | L23: =+I23*F23 -> 1963568.8 | M23: =+F23*J23 -> 462841.22 | N23: =K23*F23 -> 2131874.7
B24: 44593 | C24: Petrobras | D24: 10593-6 | E24: 218638 | F24: 630926.81 | G24: =F24-SUM(L24:N24) -> 496854.86 | H24: =+IF(G24=0,0,G24/E24) -> 2.2725 | I24: 0.12 | J24: 0.0165 | K24: 0.076 | L24: =+I24*F24 -> 75711.217 | M24: =+F24*J24 -> 10410.292 | N24: =K24*F24 -> 47950.438
B25: 44593 | C25: Petrobras | D25: 430397-2 | E25: 530835 | F25: 2051336.6 | G25: =F25-SUM(L25:N25) -> 1717994.4 | H25: =+IF(G25=0,0,G25/E25) -> 3.2364 | I25: 0.07 | J25: 0.0165 | K25: 0.076 | L25: =+I25*F25 -> 143593.56 | M25: =+F25*J25 -> 33847.054 | N25: =K25*F25 -> 155901.58
B26: 44593 | C26: Petrobras | D26: 4880-24 | E26: 33870 | F26: 139196.03 | G26: =F26-SUM(L26:N26) -> 109616.87 | H26: =+IF(G26=0,0,G26/E26) -> 3.2364002 | I26: 0.12 | J26: 0.0165 | K26: 0.076 | L26: =+I26*F26 -> 16703.524 | M26: =+F26*J26 -> 2296.7345 | N26: =K26*F26 -> 10578.898
B27: 44593 | C27: Petrobras | D27: 4814-4 | E27: 379365 | F27: 1559081.8 | G27: =F27-SUM(L27:N27) -> 1227776.9 | H27: =+IF(G27=0,0,G27/E27) -> 3.2364 | I27: 0.12 | J27: 0.0165 | K27: 0.076 | L27: =+I27*F27 -> 187089.81 | M27: =+F27*J27 -> 25724.849 | N27: =K27*F27 -> 118490.21
B28: 44593 | C28: Petrobras | D28: 10596-6 | E28: 52112 | F28: 214165.43 | G28: =F28-SUM(L28:N28) -> 168655.28 | H28: =+IF(G28=0,0,G28/E28) -> 3.2364 | I28: 0.12 | J28: 0.0165 | K28: 0.076 | L28: =+I28*F28 -> 25699.852 | M28: =+F28*J28 -> 3533.7296 | N28: =K28*F28 -> 16276.573
B29: 44593 | C29: Petrobras | D29: 3246-2 | E29: 874 | F29: 3591.89 | G29: =F29-SUM(L29:N29) -> 2828.6134 | H29: =+IF(G29=0,0,G29/E29) -> 3.2363997 | I29: 0.12 | J29: 0.0165 | K29: 0.076 | L29: =+I29*F29 -> 431.0268 | M29: =+F29*J29 -> 59.266185 | N29: =K29*F29 -> 272.98364
... B31: 44593 | C31: Petrobras | D31: 4815-4 | E31: 6555 | F31: 34962.5 | G31: =F31-SUM(L31:N31) -> 27532.969 | H31: =+IF(G31=0,0,G31/E31) -> 4.2003003 | I31: 0.12 | J31: 0.0165 | K31: 0.076 | L31: =+I31*F31 -> 4195.5 | M31: =+F31*J31 -> 576.88125 | N31: =K31*F31 -> 2657.15
B32: 44593 | C32: Shell | D32: 30-1 | E32: 22919983 | F32: 46710467 | G32: =F32-SUM(L32:N32) -> 39422466 | H32: =+IF(G32=0,0,G32/E32) -> 1.7200042 | I32: 0.07 | J32: 0.0165 | K32: 0.076 | L32: =+I32*F32 -> 3269732.7 | M32: =+(F32-L32)*J32 -> 716772.12 | N32: =+(F32-L32)*K32 -> 3301495.8
B33: 44593 | C33: New Fortress (Petrolina) | D33: 10-1 | E33: 581205 | F33: 2699929.7 | G33: =F33-SUM(L33:N33) -> 2009152.7 | H33: =+IF(G33=0,0,G33/E33) -> 3.4568744 | I33: 0.18 | J33: 0.0165 | K33: 0.076 | L33: =+I33*F33 -> 485987.35 | M33: =+(F33-L33)*J33 -> 36530.049 | N33: =+(F33-L33)*K33 -> 168259.62
B34: 44593 | C34: New Fortress (Garanhuns) | D34: 9-1 | E34: 62032 | F34: 280254.37 | G34: =F34-SUM(L34:N34) -> 208551.29 | H34: =+IF(G34=0,0,G34/E34) -> 3.3619953 | I34: 0.18 | J34: 0.0165 | K34: 0.076 | L34: =+I34*F34 -> 50445.787 | M34: =+(F34-L34)*J34 -> 3791.8416 | N34: =+(F34-L34)*K34 -> 17465.452
E45: =SUM(E18:E34) -> 47584516 | G45: =SUM(G18:G34) -> 97207335
B48: Observações Relevantes:

Sheet mar22
C2: RELATÓRIO MENSAL DE ACOMPANHAMENTO DO CUSTO DO GÁS
C3: 44621
C5: Petrobras | D5: =SUMIF($C$18:$G$40,$C$5:$C$7,$G$18:$G$40)/SUMIF($C$18:$G$40,$C$5:$C$7,$E$18:$E$40) -> 2.3201778
C6: Shell | D6: =SUMIF($C$18:$G$40,$C$5:$C$7,$G$18:$G$40)/SUMIF($C$18:$G$40,$C$5:$C$7,$E$18:$E$40) -> 1.7200042
C7: NFE | D7: =SUM(G39:G40)/SUM(E39:E40) -> 3.4481454
M8: Poderação QDC | N8: Poderação QDR
C9: Custo Médio Ponderado real | D9: =+G45/E45 -> 2.0482984 | L9: =+C5 -> Petrobras | M9: =790000/1580000 -> 0.5 | N9: =+SUM(E18:E37)/E45 -> 0.50557782
L10: =+C6 -> Shell | M10: 0.47468354 | N10: =+E38/E45 -> 0.4800369
C11: Custo Médio Ponderado tarifa | D11: 2.025 | L11: =+C7 -> NFE | M11: 0.025316456 | N11: =+SUM(E39:E40)/E45 -> 0.014385275
C12: Volume de vendas | D12: ='[1]Compra 03 2022'!$C$25 -> 54546983 | L12: Total | M12: =SUM(M9:M11) -> 1 | N12: =SUM(N9:N11) -> 1
L16: CONFORME XML DA NOTA
B17: Mês | C17: Supridor | D17: Nota Fiscal | E17: Vol m³ | F17: Compra R$ c/tributos | G17: Compra R$ s/tributos | H17: Custo | I17: ICMS | J17: PIS | K17: COFINS | L17: ICMS | M17: PIS | N17: COFINS
B18: 44621 | C18: Petrobras | D18: 4874-4 | E18: 9254960 | F18: 26707170 | G18: =F18-SUM(L18:N18) -> 21031897 | H18: =+IF(G18=0,0,G18/E18) -> 2.2725 | I18: 0.12 | J18: 0.0165 | K18: 0.076 | L18: =+I18*F18 -> 3204860.4 | M18: =+F18*J18 -> 440668.31 | N18: =K18*F18 -> 2029744.9
B19: 44621 | C19: Petrobras | D19: 10723-6 | E19: 6114653 | F19: 17645142 | G19: =F19-SUM(L19:N19) -> 13895549 | H19: =+IF(G19=0,0,G19/E19) -> 2.2725 | I19: 0.12 | J19: 0.0165 | K19: 0.076 | L19: =+I19*F19 -> 2117417 | M19: =+F19*J19 -> 291144.83 | N19: =K19*F19 -> 1341030.8
B20: 44621 | C20: Petrobras | D20: 3457-12 | E20: 6603143 | F20: 19054784 | G20: =F20-SUM(L20:N20) -> 15005642 | H20: =+IF(G20=0,0,G20/E20) -> 2.2725 | I20: 0.12 | J20: 0.0165 | K20: 0.076 | L20: =+I20*F20 -> 2286574.1 | M20: =+F20*J20 -> 314403.94 | N20: =K20*F20 -> 1448163.6
B21: 44621 | C21: Petrobras | D21: 4-9 | E21: 2013407 | F21: 5463244.7 | G21: =F21-SUM(L21:N21) -> 4575467.4 | H21: =+IF(G21=0,0,G21/E21) -> 2.2725 | I21: 0.07 | J21: 0.0165 | K21: 0.076 | L21: =+I21*F21 -> 382427.13 | M21: =+F21*J21 -> 90143.537 | N21: =K21*F21 -> 415206.59
B22: 44621 | C22: Petrobras | D22: 4011-4 | E22: 842191 | F22: 2430322.6 | G22: =F22-SUM(L22:N22) -> 1913879 | H22: =+IF(G22=0,0,G22/E22) -> 2.2725 | I22: 0.12 | J22: 0.0165 | K22: 0.076 | L22: =+I22*F22 -> 291638.71 | M22: =+F22*J22 -> 40100.323 | N22: =K22*F22 -> 184704.52
B23: 44621 | C23: Petrobras | D23: 10720-6 | E23: 413670 | F23: 1193733.4 | G23: =F23-SUM(L23:N23) -> 940065.08 | H23: =+IF(G23=0,0,G23/E23) -> 2.2725 | I23: 0.12 | J23: 0.0165 | K23: 0.076 | L23: =+I23*F23 -> 143248.01 | M23: =+F23*J23 -> 19696.602 | N23: =K23*F23 -> 90723.741
B24: 44621 | C24: Petrobras | D24: 4936-24 | E24: 290491 | F24: 838274.03 | G24: =F24-SUM(L24:N24) -> 660140.8 | H24: =+IF(G24=0,0,G24/E24) -> 2.2725 | I24: 0.12 | J24: 0.0165 | K24: 0.076 | L24: =+I24*F24 -> 100592.88 | M24: =+F24*J24 -> 13831.521 | N24: =K24*F24 -> 63708.826
B25: 44621 | C25: Petrobras | D25: 4875-4 | E25: 493489 | F25: 2028098.8 | G25: =F25-SUM(L25:N25) -> 1597127.8 | H25: =+IF(G25=0,0,G25/E25) -> 3.2364 | I25: 0.12 | J25: 0.0165 | K25: 0.076 | L25: =+I25*F25 -> 243371.85 | M25: =+F25*J25 -> 33463.63 | N25: =K25*F25 -> 154135.51
B26: 44621 | C26: Petrobras | D26: 3456-12 | E26: 318441 | F26: 1308701.5 | G26: =F26-SUM(L26:N26) -> 1030602.4 | H26: =+IF(G26=0,0,G26/E26) -> 3.2364 | I26: 0.12 | J26: 0.0165 | K26: 0.076 | L26: =+I26*F26 -> 157044.18 | M26: =+F26*J26 -> 21593.575 | N26: =K26*F26 -> 99461.316
B27: 44621 | C27: Petrobras | D27: 10725-6 | E27: 210891.97 | F27: 866705.74 | G27: =F27-SUM(L27:N27) -> 682530.77 | H27: =+IF(G27=0,0,G27/E27) -> 3.2364 | I27: 0.12 | J27: 0.0165 | K27: 0.076 | L27: =+I27*F27 -> 104004.69 | M27: =+F27*J27 -> 14300.645 | N27: =K27*F27 -> 65869.636
B28: 44621 | C28: Petrobras | D28: 10726-6 | E28: 116219.03 | F28: 477627.01 | G28: =F28-SUM(L28:N28) -> 376131.27 | H28: =+IF(G28=0,0,G28/E28) -> 3.2364 | I28: 0.12 | J28: 0.0165 | K28: 0.076 | L28: =+I28*F28 -> 57315.241 | M28: =+F28*J28 -> 7880.8457 | N28: =K28*F28 -> 36299.653
B29: 44621 | C29: Petrobras | D29: 5-9 | E29: 86428 | F29: 333988.75 | G29: =F29-SUM(L29:N29) -> 279715.58 | H29: =+IF(G29=0,0,G29/E29) -> 3.2364 | I29: 0.07 | J29: 0.0165 | K29: 0.076 | L29: =+I29*F29 -> 23379.213 | M29: =+F29*J29 -> 5510.8144 | N29: =K29*F29 -> 25383.145
... B37: 44621 | C37: Petrobras | D37: 10722-6 | E37: 38 | F37: 202.68 | G37: =F37-SUM(L37:N37) -> 159.6105 | H37: =+IF(G37=0,0,G37/E37) -> 4.2002763 | I37: 0.12 | J37: 0.0165 | K37: 0.076 | L37: =+I37*F37 -> 24.3216 | M37: =+F37*J37 -> 3.34422 | N37: =K37*F37 -> 15.40368
B38: 44621 | C38: Shell | D38: 39-1 | E38: 25482782 | F38: 51933400 | G38: =F38-SUM(L38:N38) -> 43830491 | H38: =+IF(G38=0,0,G38/E38) -> 1.7200042 | I38: 0.07 | J38: 0.0165 | K38: 0.076 | L38: =+I38*F38 -> 3635338 | M38: =+(F38-L38)*J38 -> 796918.02 | N38: =+(F38-L38)*K38 -> 3670652.7
B39: 44621 | C39: New Fortress (Petrolina) | D39: 11-1 | E39: 693387 | F39: 3221060 | G39: =F39-SUM(L39:N39) -> 2396951.8 | H39: =+IF(G39=0,0,G39/E39) -> 3.4568744 | I39: 0.18 | J39: 0.0165 | K39: 0.076 | L39: =+I39*F39 -> 579790.79 | M39: =+(F39-L39)*J39 -> 43580.941 | N39: =+(F39-L39)*K39 -> 200736.46
B40: 44621 | C40: New Fortress (Garanhuns) | D40: 10-1 | E40: 70256 | F40: 317409.58 | G40: =F40-SUM(L40:N40) -> 236200.34 | H40: =+IF(G40=0,0,G40/E40) -> 3.3619953 | I40: 0.18 | J40: 0.0165 | K40: 0.076 | L40: =+I40*F40 -> 57133.724 | M40: =+(F40-L40)*J40 -> 4294.5516 | N40: =+(F40-L40)*K40 -> 19780.965
E45: =SUM(E18:E40) -> 53085048 | G45: =SUM(G18:G40) -> 1.0873402e+08
B48: Observações Relevantes:

Sheet abr22
C2: RELATÓRIO MENSAL DE ACOMPANHAMENTO DO CUSTO DO GÁS
C3: 44652
C5: Petrobras | D5: =SUMIF($C$18:$G$40,$C$5:$C$7,$G$18:$G$40)/SUMIF($C$18:$G$40,$C$5:$C$7,$E$18:$E$40) -> 2.3200881
C6: Shell | D6: =SUMIF($C$18:$G$40,$C$5:$C$7,$G$18:$G$40)/SUMIF($C$18:$G$40,$C$5:$C$7,$E$18:$E$40) -> 1.720021
C7: NFE | D7: =SUM(G35:G36)/SUM(E35:E36) -> 3.4421499
M8: Poderação QDC | N8: Poderação QDR
C9: Custo Médio Ponderado real | D9: =+G45/E45 -> 2.0403835 | L9: =+C5 -> Petrobras | M9: =790000/1580000 -> 0.5 | N9: =+SUM(E18:E33)/E45 -> 0.50813882
L10: =+C6 -> Shell | M10: 0.47468354 | N10: =+E34/E45 -> 0.48289261
C11: Custo Médio Ponderado tarifa | D11: 2.025 | L11: =+C7 -> NFE | M11: 0.025316456 | N11: =+SUM(E35:E36)/E45 -> 0.0089685688
L12: Total | M12: =SUM(M9:M11) -> 1 | N12: =SUM(N9:N11) -> 1
L16: CONFORME XML DA NOTA
B17: Mês | C17: Supridor | D17: Nota Fiscal | E17: Vol m³ | F17: Compra R$ c/tributos | G17: Compra R$ s/tributos | H17: Custo | I17: ICMS | J17: PIS | K17: COFINS | L17: ICMS | M17: PIS | N17: COFINS
B18: 44652 | C18: Petrobras | D18: 4946-24 | E18: 2640756 | F18: 7620467.3 | G18: =F18-SUM(L18:N18) -> 6001118 | H18: =+IF(G18=0,0,G18/E18) -> 2.2725 | I18: 0.12 | J18: 0.0165 | K18: 0.076 | L18: =+I18*F18 -> 914456.08 | M18: =+F18*J18 -> 125737.71 | N18: =K18*F18 -> 579155.52
B19: 44652 | C19: Petrobras | D19: 10774-6 | E19: 165324 | F19: 477077.83 | G19: =F19-SUM(L19:N19) -> 375698.79 | H19: =+IF(G19=0,0,G19/E19) -> 2.2725 | I19: 0.12 | J19: 0.0165 | K19: 0.076 | L19: =+I19*F19 -> 57249.34 | M19: =+F19*J19 -> 7871.7842 | N19: =K19*F19 -> 36257.915
B20: 44652 | C20: Petrobras | D20: 10776-6 | E20: 4839057 | F20: 13964136 | G20: =F20-SUM(L20:N20) -> 10996757 | H20: =+IF(G20=0,0,G20/E20) -> 2.2725 | I20: 0.12 | J20: 0.0165 | K20: 0.076 | L20: =+I20*F20 -> 1675696.3 | M20: =+F20*J20 -> 230408.24 | N20: =K20*F20 -> 1061274.3
B21: 44652 | C21: Petrobras | D21: 3288-28 | E21: 142068 | F21: 409967.66 | G21: =F21-SUM(L21:N21) -> 322849.53 | H21: =+IF(G21=0,0,G21/E21) -> 2.2725 | I21: 0.12 | J21: 0.0165 | K21: 0.076 | L21: =+I21*F21 -> 49196.119 | M21: =+F21*J21 -> 6764.4664 | N21: =K21*F21 -> 31157.542
B22: 44652 | C22: Petrobras | D22: 4914-4 | E22: 4593055 | F22: 13254244 | G22: =F22-SUM(L22:N22) -> 10437717 | H22: =+IF(G22=0,0,G22/E22) -> 2.2725 | I22: 0.12 | J22: 0.0165 | K22: 0.076 | L22: =+I22*F22 -> 1590509.3 | M22: =+F22*J22 -> 218695.03 | N22: =K22*F22 -> 1007322.6
B23: 44652 | C23: Petrobras | D23: 61-9 | E23: 12439043 | F23: 33752508 | G23: =F23-SUM(L23:N23) -> 28267725 | H23: =+IF(G23=0,0,G23/E23) -> 2.2725 | I23: 0.07 | J23: 0.0165 | K23: 0.076 | L23: =+I23*F23 -> 2362675.5 | M23: =+F23*J23 -> 556916.38 | N23: =K23*F23 -> 2565190.6
B24: 44652 | C24: Petrobras | D24: 10775-6 | E24: 588 | F24: 2416.51 | G24: =F24-SUM(L24:N24) -> 1903.0016 | H24: =+IF(G24=0,0,G24/E24) -> 3.2363973 | I24: 0.12 | J24: 0.0165 | K24: 0.076 | L24: =+I24*F24 -> 289.9812 | M24: =+F24*J24 -> 39.872415 | N24: =K24*F24 -> 183.65476
B25: 44652 | C25: Petrobras | D25: 3289-28 | E25: 10908 | F25: 44828.76 | G25: =F25-SUM(L25:N25) -> 35302.649 | H25: =+IF(G25=0,0,G25/E25) -> 3.2363998 | I25: 0.12 | J25: 0.0165 | K25: 0.076 | L25: =+I25*F25 -> 5379.4512 | M25: =+F25*J25 -> 739.67454 | N25: =K25*F25 -> 3406.9858
B26: 44652 | C26: Petrobras | D26: 4947-24 | E26: 116437 | F26: 478522.81 | G26: =F26-SUM(L26:N26) -> 376836.71 | H26: =+IF(G26=0,0,G26/E26) -> 3.2364001 | I26: 0.12 | J26: 0.0165 | K26: 0.076 | L26: =+I26*F26 -> 57422.737 | M26: =+F26*J26 -> 7895.6264 | N26: =K26*F26 -> 36367.734
B27: 44652 | C27: Petrobras | D27: 62-9 | E27: 657365 | F27: 2540293.8 | G27: =F27-SUM(L27:N27) -> 2127496.1 | H27: =+IF(G27=0,0,G27/E27) -> 3.2364 | I27: 0.07 | J27: 0.0165 | K27: 0.076 | L27: =+I27*F27 -> 177820.57 | M27: =+F27*J27 -> 41914.848 | N27: =K27*F27 -> 193062.33
B28: 44652 | C28: Petrobras | D28: 10777-6 | E28: 200808 | F28: 825263.5 | G28: =F28-SUM(L28:N28) -> 649895.01 | H28: =+IF(G28=0,0,G28/E28) -> 3.2364 | I28: 0.12 | J28: 0.0165 | K28: 0.076 | L28: =+I28*F28 -> 99031.62 | M28: =+F28*J28 -> 13616.848 | N28: =K28*F28 -> 62720.026
B29: 44652 | C29: Petrobras | D29: 4915-4 | E29: 204847 | F29: 841862.64 | G29: =F29-SUM(L29:N29) -> 662966.83 | H29: =+IF(G29=0,0,G29/E29) -> 3.2364 | I29: 0.12 | J29: 0.0165 | K29: 0.076 | L29: =+I29*F29 -> 101023.52 | M29: =+F29*J29 -> 13890.734 | N29: =K29*F29 -> 63981.561
... B33: 44652 | C33: Petrobras | D33: 4948-24 | E33: 18055 | F33: 96300.22 | G33: =F33-SUM(L33:N33) -> 75836.423 | H33: =+IF(G33=0,0,G33/E33) -> 4.2003004 | I33: 0.12 | J33: 0.0165 | K33: 0.076 | L33: =+I33*F33 -> 11556.026 | M33: =+F33*J33 -> 1588.9536 | N33: =K33*F33 -> 7318.8167
B34: 44652 | C34: Shell | D34: 54-1 | E34: 24763368 | F34: 50467744 | G34: =F34-SUM(L34:N34) -> 42593514 | H34: =+IF(G34=0,0,G34/E34) -> 1.720021 | I34: 0.07 | J34: 0.0165 | K34: 0.076 | L34: =+I34*F34 -> 3532742.1 | M34: =+(F34-L34)*J34 -> 774427.53 | N34: =+(F34-L34)*K34 -> 3567060.1
B35: 44652 | C35: New Fortress (Petrolina) | D35: 13-1 | E35: 388544 | F35: 1804942.3 | G35: =F35-SUM(L35:N35) -> 1343147.8 | H35: =+IF(G35=0,0,G35/E35) -> 3.4568744 | I35: 0.18 | J35: 0.0165 | K35: 0.076 | L35: =+I35*F35 -> 324889.61 | M35: =+(F35-L35)*J35 -> 24420.869 | N35: =+(F35-L35)*K35 -> 112484
B36: 44652 | C36: New Fortress (Garanhuns) | D36: 11-1 | E36: 71376 | F36: 322469.63 | G36: =F36-SUM(L36:N36) -> 239965.78 | H36: =+IF(G36=0,0,G36/E36) -> 3.3619953 | I36: 0.18 | J36: 0.0165 | K36: 0.076 | L36: =+I36*F36 -> 58044.533 | M36: =+(F36-L36)*J36 -> 4363.0141 | N36: =+(F36-L36)*K36 -> 20096.307
E45: =SUM(E18:E40) -> 51281315 | G45: =SUM(G18:G40) -> 1.0463355e+08
B48: Observações Relevantes:

Sheet mai22
C2: RELATÓRIO MENSAL DE ACOMPANHAMENTO DO CUSTO DO GÁS
C3: 44682
C5: Petrobras | D5: =SUMIF($C$18:$G$40,$C$5:$C$7,$G$18:$G$40)/SUMIF($C$18:$G$40,$C$5:$C$7,$E$18:$E$40) -> 2.7753623
C6: Shell | D6: =SUMIF($C$18:$G$40,$C$5:$C$7,$G$18:$G$40)/SUMIF($C$18:$G$40,$C$5:$C$7,$E$18:$E$40) -> 1.9547305
C7: NFE | D7: =SUM(G29:G30)/SUM(E29:E30) -> 3.8550713
M8: Poderação QDC | N8: Poderação QDR
C9: Custo Médio Ponderado real | D9: =+G45/E45 -> 2.3944805 | L9: =+C5 -> Petrobras | M9: =790000/1580000 -> 0.5 | N9: =+SUM(E18:E27)/E45 -> 0.50457814
L10: =+C6 -> Shell | M10: 0.47468354 | N10: =+E28/E45 -> 0.48190998
C11: Custo Médio Ponderado tarifa | D11: 2.3639 | L11: =+C7 -> NFE | M11: 0.025316456 | N11: =+SUM(E29:E30)/E45 -> 0.013511873
L12: Total | M12: =SUM(M9:M11) -> 1 | N12: z
L16: CONFORME XML DA NOTA
B17: Mês | C17: Supridor | D17: Nota Fiscal | E17: Vol m³ | F17: Compra R$ c/tributos | G17: Compra R$ s/tributos | H17: Custo | I17: ICMS | J17: PIS | K17: COFINS | L17: ICMS | M17: PIS | N17: COFINS
B18: 44682 | C18: Petrobras | D18: 4973-4 | E18: 12806648 | F18: 43445744 | G18: =F18-SUM(L18:N18) -> 34695814 | H18: =+IF(G18=0,0,G18/E18) -> 2.7092034 | I18: 0.12 | J18: 0.0165 | K18: 0.076 | L18: =+I18*F18 -> 5213489.2 | M18: =+(F18-L18)*J18 -> 630832.2 | N18: 2905607.9
B19: 44682 | C19: Petrobras | D19: 3489-12 | E19: 8529281 | F19: 28935046 | G19: =F19-SUM(L19:N19) -> 23107557 | H19: =+IF(G19=0,0,G19/E19) -> 2.7092034 | I19: 0.12 | J19: 0.0165 | K19: 0.076 | L19: =+I19*F19 -> 3472205.6 | M19: =+(F19-L19)*J19 -> 420136.87 | N19: 1935147
B20: 44682 | C20: Petrobras | D20: 10869-6 | E20: 2998823 | F20: 10173317 | G20: =F20-SUM(L20:N20) -> 8124421.4 | H20: =+IF(G20=0,0,G20/E20) -> 2.7092034 | I20: 0.12 | J20: 0.0165 | K20: 0.076 | L20: =+I20*F20 -> 1220798.1 | M20: =+(F20-L20)*J20 -> 147716.57 | N20: 680381.29
B21: 44682 | C21: Petrobras | D21: 5000-24 | E21: 941367 | F21: 3193528 | G21: =F21-SUM(L21:N21) -> 2550354.7 | H21: =+IF(G21=0,0,G21/E21) -> 2.7092034 | I21: 0.12 | J21: 0.0165 | K21: 0.076 | L21: =+I21*F21 -> 383223.36 | M21: =+(F21-L21)*J21 -> 46370.027 | N21: 213579.96
B22: 44682 | C22: Petrobras | D22: 4974-4 | E22: 766491 | F22: 3710561.2 | G22: =F22-SUM(L22:N22) -> 2963257.9 | H22: =+IF(G22=0,0,G22/E22) -> 3.8660048 | I22: 0.12 | J22: 0.0165 | K22: 0.076 | L22: =+I22*F22 -> 445267.35 | M22: =+(F22-L22)*J22 -> 53877.349 | N22: 248158.63
B23: 44682 | C23: Petrobras | D23: 3490-12 | E23: 488627 | F23: 2365429.5 | G23: =F23-SUM(L23:N23) -> 1889034.3 | H23: =+IF(G23=0,0,G23/E23) -> 3.8660048 | I23: 0.12 | J23: 0.0165 | K23: 0.076 | L23: =+I23*F23 -> 283851.54 | M23: =+(F23-L23)*J23 -> 34346.036 | N23: 158197.56
B24: 44682 | C24: Petrobras | D24: 10870-6 | E24: 87040 | F24: 421358.18 | G24: =F24-SUM(L24:N24) -> 336497.07 | H24: =+IF(G24=0,0,G24/E24) -> 3.8660049 | I24: 0.12 | J24: 0.0165 | K24: 0.076 | L24: =+I24*F24 -> 50562.982 | M24: =+(F24-L24)*J24 -> 6118.1208 | N24: 28180.01
B25: 44682 | C25: Petrobras | D25: 5001-24 | E25: 26303 | F25: 127332.08 | G25: =F25-SUM(L25:N25) -> 101687.53 | H25: =+IF(G25=0,0,G25/E25) -> 3.866005 | I25: 0.12 | J25: 0.0165 | K25: 0.076 | L25: =+I25*F25 -> 15279.85 | M25: =+(F25-L25)*J25 -> 1848.8618 | N25: 8515.84
B26: 44682 | C26: Petrobras | D26: 3491-12 | E26: 52734 | F26: 331664.24 | G26: =F26-SUM(L26:N26) -> 264867.4 | H26: =+IF(G26=0,0,G26/E26) -> 5.0227063 | I26: 0.12 | J26: 0.0165 | K26: 0.076 | L26: =+I26*F26 -> 39799.709 | M26: =+(F26-L26)*J26 -> 4815.7648 | N26: 22181.37
B27: 44682 | C27: Petrobras | D27: 4975-4 | E27: 27244 | F27: 171347.91 | G27: =F27-SUM(L27:N27) -> 136838.61 | H27: =+IF(G27=0,0,G27/E27) -> 5.0227063 | I27: 0.12 | J27: 0.0165 | K27: 0.076 | L27: =+I27*F27 -> 20561.749 | M27: =+(F27-L27)*J27 -> 2487.9717 | N27: 11459.58
B28: 44682 | C28: Shell | D28: 74-1 | E28: 25523958 | F28: 59116039 | G28: =F28-SUM(L28:N28) -> 49892459 | H28: =+IF(G28=0,0,G28/E28) -> 1.9547305 | I28: 0.07 | J28: 0.0165 | K28: 0.076 | L28: =+I28*F28 -> 4138122.7 | M28: =+(F28-L28)*J28 -> 907135.62 | N28: =+(F28-L28)*K28 -> 4178321.6
B29: 44682 | C29: New Fortress (Petrolina) | D29: 16-1 | E29: 643817 | F29: 3343534.8 | G29: =F29-SUM(L29:N29) -> 2488091.4 | H29: =+IF(G29=0,0,G29/E29) -> 3.8645942 | I29: 0.18 | J29: 0.0165 | K29: 0.076 | L29: =+I29*F29 -> 601836.27 | M29: =+(F29-L29)*J29 -> 45238.026 | N29: =+(F29-L29)*K29 -> 208369.09
B30: 44682 | C30: New Fortress (Garanhuns) | D30: 13-1 | E30: 71828 | F30: 363866.28 | G30: =F30-SUM(L30:N30) -> 270771.09 | H30: =+IF(G30=0,0,G30/E30) -> 3.769715 | I30: 0.18 | J30: 0.0165 | K30: 0.076 | L30: =+I30*F30 -> 65495.93 | M30: =+(F30-L30)*J30 -> 4923.1108 | N30: =+(F30-L30)*K30 -> 22676.147
E45: =SUM(E18:E40) -> 52964161 | G45: =SUM(G18:G40) -> 1.2682165e+08
B48: Observações Relevantes:

Sheet jun22
C2: RELATÓRIO MENSAL DE ACOMPANHAMENTO DO CUSTO DO GÁS
C3: 44713
C5: Petrobras | D5: =SUMIF($C$18:$G$40,$C$5:$C$7,$G$18:$G$40)/SUMIF($C$18:$G$40,$C$5:$C$7,$E$18:$E$40) -> 2.7840492
C6: Shell | D6: =SUMIF($C$18:$G$40,$C$5:$C$7,$G$18:$G$40)/SUMIF($C$18:$G$40,$C$5:$C$7,$E$18:$E$40) -> 1.9547305
C7: NFE | D7: =SUM(G41:G42)/SUM(E41:E42) -> 3.7897486
M8: Poderação QDC | N8: Poderação QDR
C9: Custo Médio Ponderado real | D9: =+G45/E45 -> 2.3983039 | L9: =+C5 -> Petrobras | M9: =790000/1580000 -> 0.5 | N9: =+SUM(E18:E39)/E45 -> 0.50638886
L10: =+C6 -> Shell | M10: 0.47468354 | N10: =+E40/E45 -> 0.4807417
C11: Custo Médio Ponderado tarifa | D11: 2.3639 | L11: =+C7 -> NFE | M11: 0.025316456 | N11: =+SUM(E41:E42)/E45 -> 0.012869441
L12: Total | M12: =SUM(M9:M11) -> 1 | N12: =SUM(N9:N11) -> 1
L16: CONFORME XML DA NOTA
B17: Mês | C17: Supridor | D17: Nota Fiscal | E17: Vol m³ | F17: Compra R$ c/tributos | G17: Compra R$ s/tributos | H17: Custo | I17: ICMS | J17: PIS | K17: COFINS | L17: ICMS | M17: PIS | N17: COFINS
B18: 44713 | C18: Petrobras | D18: 3350-28 | E18: 20353 | F18: 69046.27 | G18: =F18-SUM(L18:N18) -> 55140.416 | H18: =+IF(G18=0,0,G18/E18) -> 2.7092033 | I18: 0.12 | J18: 0.0165 | K18: 0.076 | L18: =+I18*F18 -> 8285.5524 | M18: =+(F18-L18)*J18 -> 1002.5518 | N18: 4617.75
B19: 44713 | C19: Petrobras | D19: 5029-4 | E19: 6151282 | F19: 20867835 | G19: =F19-SUM(L19:N19) -> 16665074 | H19: =+IF(G19=0,0,G19/E19) -> 2.7092034 | I19: 0.12 | J19: 0.0165 | K19: 0.076 | L19: =+I19*F19 -> 2504140.2 | M19: =+(F19-L19)*J19 -> 303000.97 | N19: 1395619.9
B20: 44713 | C20: Petrobras | D20: 10928-6 | E20: 227433 | F20: 771552.07 | G20: =F20-SUM(L20:N20) -> 616162.26 | H20: =+IF(G20=0,0,G20/E20) -> 2.7092034 | I20: 0.12 | J20: 0.0165 | K20: 0.076 | L20: =+I20*F20 -> 92586.248 | M20: =+(F20-L20)*J20 -> 11202.936 | N20: 51600.63
B21: 44713 | C21: Petrobras | D21: 3519-12 | E21: 14345444 | F21: 48666012 | G21: =F21-SUM(L21:N21) -> 38864726 | H21: =+IF(G21=0,0,G21/E21) -> 2.7092034 | I21: 0.12 | J21: 0.0165 | K21: 0.076 | L21: =+I21*F21 -> 5839921.4 | M21: =+(F21-L21)*J21 -> 706630.49 | N21: 3254734.2
B22: 44713 | C22: Petrobras | D22: 5032-24 | E22: 109597 | F22: 371800.9 | G22: =F22-SUM(L22:N22) -> 296920.57 | H22: =+IF(G22=0,0,G22/E22) -> 2.7092034 | I22: 0.12 | J22: 0.0165 | K22: 0.076 | L22: =+I22*F22 -> 44616.108 | M22: =+(F22-L22)*J22 -> 5398.5491 | N22: 24865.67
B23: 44713 | C23: Petrobras | D23: 5033-24 | E23: 563591 | F23: 1911946.8 | G23: =F23-SUM(L23:N23) -> 1652249 | H23: =+IF(G23=0,0,G23/E23) -> 2.9316455 | I23: 0.12 | J23: 0.0165 | K23: 0.076 | L23: =+I23*F23 -> 229433.62 | M23: 5398.5491 | N23: 24865.67
B24: 44713 | C24: Petrobras | D24: 5030-24 | E24: 58944 | F24: 285346.23 | G24: =F24-SUM(L24:N24) -> 227877.79 | H24: =+IF(G24=0,0,G24/E24) -> 3.8660048 | I24: 0.12 | J24: 0.0165 | K24: 0.076 | L24: =+I24*F24 -> 34241.548 | M24: =+(F24-L24)*J24 -> 4143.2273 | N24: 19083.67
B25: 44713 | C25: Petrobras | D25: 3351-28 | E25: 1670 | F25: 8084.42 | G25: =F25-SUM(L25:N25) -> 6456.2238 | H25: =+IF(G25=0,0,G25/E25) -> 3.8660023 | I25: 0.12 | J25: 0.0165 | K25: 0.076 | L25: =+I25*F25 -> 970.1304 | M25: =+(F25-L25)*J25 -> 117.38578 | N25: 540.68
B26: 44713 | C26: Petrobras | D26: 5030-4 | E26: 283958 | F26: 1374632.6 | G26: =F26-SUM(L26:N26) -> 1097783 | H26: =+IF(G26=0,0,G26/E26) -> 3.8660048 | I26: 0.12 | J26: 0.0165 | K26: 0.076 | L26: =+I26*F26 -> 164955.92 | M26: =+(F26-L26)*J26 -> 19959.666 | N26: 91934.06
B27: 44713 | C27: Petrobras | D27: 10929-6 | E27: 11500 | F27: 55671.17 | G27: =F27-SUM(L27:N27) -> 44459.054 | H27: =+IF(G27=0,0,G27/E27) -> 3.8660047 | I27: 0.12 | J27: 0.0165 | K27: 0.076 | L27: =+I27*F27 -> 6680.5404 | M27: =+(F27-L27)*J27 -> 808.34539 | N27: 3723.23
B28: 44713 | C28: Petrobras | D28: 3520-12 | E28: 929102 | F28: 4497756.5 | G28: =F28-SUM(L28:N28) -> 3591912.8 | H28: =+IF(G28=0,0,G28/E28) -> 3.8660048 | I28: 0.12 | J28: 0.0165 | K28: 0.076 | L28: =+I28*F28 -> 539730.78 | M28: =+(F28-L28)*J28 -> 65307.424 | N28: 300805.46
B29: 44713 | C29: Petrobras | D29: 3352-28 | E29: 287 | F29: 1805.05 | G29: =F29-SUM(L29:N29) -> 1441.5147 | H29: =+IF(G29=0,0,G29/E29) -> 5.0226992 | I29: 0.12 | J29: 0.0165 | K29: 0.076 | L29: =+I29*F29 -> 216.606 | M29: =+(F29-L29)*J29 -> 26.209326 | N29: 120.72
B30: 44713 | C30: Petrobras | D30: 5031-24 | E30: 13231 | F30: 83214.8 | G30: =F30-SUM(L30:N30) -> 66455.425 | H30: =+IF(G30=0,0,G30/E30) -> 5.0227062 | I30: 0.12 | J30: 0.0165 | K30: 0.076 | L30: =+I30*F30 -> 9985.776 | M30: =+(F30-L30)*J30 -> 1208.2789 | N30: 5565.32
B31: 44713 | C31: Petrobras | D31: 5031-4 | E31: 2486 | F31: 15635.4 | G31: =F31-SUM(L31:N31) -> 12486.446 | H31: =+IF(G31=0,0,G31/E31) -> 5.0227055 | I31: 0.12 | J31: 0.0165 | K31: 0.076 | L31: =+I31*F31 -> 1876.248 | M31: =+(F31-L31)*J31 -> 227.02601 | N31: 1045.68
B32: 44713 | C32: Petrobras | D32: 3521-12 | E32: 48713 | F32: 306374.64 | G32: =F32-SUM(L32:N32) -> 244671.09 | H32: =+IF(G32=0,0,G32/E32) -> 5.0227063 | I32: 0.12 | J32: 0.0165 | K32: 0.076 | L32: =+I32*F32 -> 36764.957 | M32: =+(F32-L32)*J32 -> 4448.5598 | N32: 20490.03
B33: 44713 | C33: Petrobras | D33: 10927-6 | E33: 21232 | F33: 93276.03 | G33: =F33-SUM(L33:N33) -> 82082.906 | H33: =+IF(G33=0,0,G33/E33) -> 3.8659997 | I33: 0.12 | J33: 0 | K33: 0 | L33: =+I33*F33 -> 11193.124 | M33: =+(F33-L33)*J33 -> 0 | N33: 0
B34: 44713 | C34: Petrobras | D34: 3517-12 | E34: 104303 | F34: 458222.05 | G34: =F34-SUM(L34:N34) -> 403235.4 | H34: =+IF(G34=0,0,G34/E34) -> 3.8660001 | I34: 0.12 | J34: 0 | K34: 0 | L34: =+I34*F34 -> 54986.646 | M34: =+(F34-L34)*J34 -> 0 | N34: 0
B35: 44713 | C35: Petrobras | D35: 5028-4 | E35: 30694 | F35: 134844.32 | G35: =F35-SUM(L35:N35) -> 118663 | H35: =+IF(G35=0,0,G35/E35) -> 3.8659999 | I35: 0.12 | J35: 0 | K35: 0 | L35: =+I35*F35 -> 16181.318 | M35: =+(F35-L35)*J35 -> 0 | N35: 0
... B39: 44713 | C39: Petrobras | D39: 10926-6 | E39: 414365 | F39: 1275679.2 | G39: =F39-SUM(L39:N39) -> 1122597.7 | H39: =+IF(G39=0,0,G39/E39) -> 2.7092 | I39: 0.12 | J39: 0 | K39: 0 | L39: =+I39*F39 -> 153081.5 | M39: =+(F39-L39)*J39 -> 0 | N39: 0
B40: 44713 | C40: Shell | D40: 80-1 | E40: 24961813 | F40: 57814055 | G40: =F40-SUM(L40:N40) -> 48793617 | H40: =+IF(G40=0,0,G40/E40) -> 1.9547305 | I40: 0.07 | J40: 0.0165 | K40: 0.076 | L40: =+I40*F40 -> 4046983.9 | M40: =+(F40-L40)*J40 -> 887156.68 | N40: =+(F40-L40)*K40 -> 4086297.4
B41: 44713 | C41: New Fortress (Petrolina) | D41: 17-1 | E41: 608037 | F41: 3103641.7 | G41: =F41-SUM(L41:N41) -> 2309575 | H41: =+IF(G41=0,0,G41/E41) -> 3.7984119 | I41: 0.18 | J41: 0.0165 | K41: 0.076 | L41: =+I41*F41 -> 558655.51 | M41: =+(F41-L41)*J41 -> 41992.273 | N41: =+(F41-L41)*K41 -> 193418.95
B42: 44713 | C42: New Fortress (Garanhuns) | D42: 16-1 | E42: 60190 | F42: 299452.14 | G42: =F42-SUM(L42:N42) -> 222837.32 | H42: =+IF(G42=0,0,G42/E42) -> 3.7022316 | I42: 0.18 | J42: 0.0165 | K42: 0.076 | L42: =+I42*F42 -> 53901.385 | M42: =+(F42-L42)*J42-0.01 -> 4051.5775 | N42: =+(F42-L42)*K42 -> 18661.857
E45: =SUM(E18:E44) -> 51923544 | G45: =SUM(G18:G44) -> 1.2452844e+08
B48: Observações Relevantes: Publicação da Lei Complementar 194/2022, no DOU de 23.06.2022, Edição Extra, prevendo, até 31.12.2022, redução a zero da alíquota de PIS/COFINS incidente sobre a receita ou o faturamento na venda de gás natural veicular classificado nos códigos 2711.11.00 ou 2711.21.00 da NCM. "Art. 9º-B Até 31 de dezembro de 2022, ficam reduzidas a 0 (zero) as alíquotas das contribuições de que tratam o caput e o § 1º do art. 9º desta Lei Complementar incidentes sobre a receita ou o faturamento na venda ou sobre a importação de gás natural veicular classificado nos códigos 2711.11.00 ou 2711.21.00 da NCM." Dessa forma, a Copergás informou a Petrobras todo o volume de GNV e GNC veicular comercializado a partir do dia 23/06/2022, o qual foi sensibilizado nas notas do supridor e, consequentemente, foram emitidas com alíquotas zero de PIS/Cofins

Sheet jul22
C2: RELATÓRIO MENSAL DE ACOMPANHAMENTO DO CUSTO DO GÁS
C3: 44743
C5: Petrobras | D5: =SUMIF($C$18:$G$40,$C$5:$C$7,$G$18:$G$40)/SUMIF($C$18:$G$40,$C$5:$C$7,$E$18:$E$40) -> 2.7445427
C6: Shell | D6: =SUMIF($C$18:$G$40,$C$5:$C$7,$G$18:$G$40)/SUMIF($C$18:$G$40,$C$5:$C$7,$E$18:$E$40) -> 1.9547306
C7: NFE | D7: =SUM(G41:G42)/SUM(E41:E42) -> 3.749814
M8: Poderação QDC | N8: Poderação QDR
C9: Custo Médio Ponderado real | D9: =+G45/E45 -> 2.3740817 | L9: =+C5 -> Petrobras | M9: =790000/1580000 -> 0.5 | N9: =+SUM(E18:E37)/E45 -> 0.4997238
L10: =+C6 -> Shell | M10: 0.47468354 | N10: =+SUM(E38:E40)/E45 -> 0.48653689
C11: Custo Médio Ponderado tarifa | D11: 2.3639 | L11: =+C7 -> NFE | M11: 0.025316456 | N11: =+SUM(E41:E42)/E45 -> 0.013739309
L12: Total | M12: =SUM(M9:M11) -> 1 | N12: =SUM(N9:N11) -> 1
L16: CONFORME XML DA NOTA
B17: Mês | C17: Supridor | D17: Nota Fiscal | E17: Vol m³ | F17: Compra R$ c/tributos | G17: Compra R$ s/tributos | H17: Custo | I17: ICMS | J17: PIS | K17: COFINS | L17: ICMS | M17: PIS | N17: COFINS
B18: 44743 | C18: Petrobras | D18: 3597 | E18: 3815 | F18: 18468.31 | G18: =F18-SUM(L18:N18) -> 14748.813 | H18: =+IF(G18=0,0,G18/E18) -> 3.866006 | I18: 0.12 | J18: 0.0165 | K18: 0.076 | L18: =+I18*F18 -> 2216.1972 | M18: =(F18-L18)*J18 -> 268.15986 | N18: 1235.14
B19: 44743 | C19: Petrobras | D19: 3598 | E19: 484767 | F19: 1492421.3 | G19: =F19-SUM(L19:N19) -> 1313330.8 | H19: =+IF(G19=0,0,G19/E19) -> 2.7092 | I19: 0.12 | J19: 0 | K19: 0 | L19: =+I19*F19 -> 179090.56 | M19: =(F19-L19)*J19 -> 0 | N19: =(F19-L19)*K19 -> 0
B20: 44743 | C20: Petrobras | D20: 3599 | E20: 14204 | F20: 62400.75 | G20: =F20-SUM(L20:N20) -> 54912.66 | H20: =+IF(G20=0,0,G20/E20) -> 3.8659997 | I20: 0.12 | J20: 0 | K20: 0 | L20: =+I20*F20 -> 7488.09 | M20: =(F20-L20)*J20 -> 0 | N20: =(F20-L20)*K20 -> 0
B21: 44743 | C21: Petrobras | D21: 3600 | E21: 135427 | F21: 459427.54 | G21: =F21-SUM(L21:N21) -> 366899.3 | H21: =+IF(G21=0,0,G21/E21) -> 2.7092035 | I21: 0.12 | J21: 0.0165 | K21: 0.076 | L21: =+I21*F21 -> 55131.305 | M21: =(F21-L21)*J21 -> 6670.8879 | N21: 30726.05
B22: 44743 | C22: Petrobras | D22: 4049 | E22: 151815 | F22: 515022.79 | G22: =F22-SUM(L22:N22) -> 411297.71 | H22: =+IF(G22=0,0,G22/E22) -> 2.7092034 | I22: 0.12 | J22: 0.0165 | K22: 0.076 | L22: =+I22*F22 -> 61802.735 | M22: =(F22-L22)*J22 -> 7478.1309 | N22: 34444.21
B23: 44743 | C23: Petrobras | D23: 4050 | E23: 942 | F23: 4560.19 | G23: =F23-SUM(L23:N23) -> 3641.7732 | H23: =+IF(G23=0,0,G23/E23) -> 3.8660013 | I23: 0.12 | J23: 0.0165 | K23: 0.076 | L23: =+I23*F23 -> 547.2228 | M23: =(F23-L23)*J23 -> 66.213959 | N23: 304.98
B24: 44743 | C24: Petrobras | D24: 4051 | E24: 59933 | F24: 184511.91 | G24: =F24-SUM(L24:N24) -> 162370.48 | H24: =+IF(G24=0,0,G24/E24) -> 2.7092 | I24: 0.12 | J24: 0 | K24: 0 | L24: =+I24*F24 -> 22141.429 | M24: =(F24-L24)*J24 -> 0 | N24: =(F24-L24)*K24 -> 0
B25: 44743 | C25: Petrobras | D25: 4052 | E25: 372 | F25: 1634.26 | G25: =F25-SUM(L25:N25) -> 1438.1488 | H25: =+IF(G25=0,0,G25/E25) -> 3.8659914 | I25: 0.12 | J25: 0 | K25: 0 | L25: =+I25*F25 -> 196.1112 | M25: =(F25-L25)*J25 -> 0 | N25: =(F25-L25)*K25 -> 0
B26: 44743 | C26: Petrobras | D26: 11015 | E26: 2217455 | F26: 7522575.9 | G26: =F26-SUM(L26:N26) -> 6007536.6 | H26: =+IF(G26=0,0,G26/E26) -> 2.7092034 | I26: 0.12 | J26: 0.0165 | K26: 0.076 | L26: =+I26*F26 -> 902709.1 | M26: =(F26-L26)*J26 -> 109227.8 | N26: 503102.35
B27: 44743 | C27: Petrobras | D27: 11016 | E27: 69162 | F27: 334811.28 | G27: =F27-SUM(L27:N27) -> 267380.63 | H27: =+IF(G27=0,0,G27/E27) -> 3.8660048 | I27: 0.12 | J27: 0.0165 | K27: 0.076 | L27: =+I27*F27 -> 40177.354 | M27: =(F27-L27)*J27 -> 4861.4598 | N27: 22391.84
B28: 44743 | C28: Petrobras | D28: 11017 | E28: 3543910 | F28: 10910410 | G28: =F28-SUM(L28:N28) -> 9601161 | H28: =+IF(G28=0,0,G28/E28) -> 2.7092 | I28: 0.12 | J28: 0 | K28: 0 | L28: =+I28*F28 -> 1309249.2 | M28: =(F28-L28)*J28 -> 0 | N28: =(F28-L28)*K28 -> 0
B29: 44743 | C29: Petrobras | D29: 11018 | E29: 103352 | F29: 454044.13 | G29: =F29-SUM(L29:N29) -> 399558.83 | H29: =+IF(G29=0,0,G29/E29) -> 3.866 | I29: 0.12 | J29: 0 | K29: 0 | L29: =+I29*F29 -> 54485.296 | M29: =(F29-L29)*J29 -> 0 | N29: =(F29-L29)*K29 -> 0
B30: 44743 | C30: Petrobras | D30: 5106 | E30: 8325077 | F30: 28242297 | G30: =F30-SUM(L30:N30) -> 22554327 | H30: =+IF(G30=0,0,G30/E30) -> 2.7092034 | I30: 0.12 | J30: 0.0165 | K30: 0.076 | L30: =+I30*F30 -> 3389075.7 | M30: =(F30-L30)*J30 -> 410078.16 | N30: 1888816.6
B31: 44743 | C31: Petrobras | D31: 5107 | E31: 299225 | F31: 1448539.8 | G31: =F31-SUM(L31:N31) -> 1156805.3 | H31: =+IF(G31=0,0,G31/E31) -> 3.8660049 | I31: 0.12 | J31: 0.0165 | K31: 0.076 | L31: =+I31*F31 -> 173824.77 | M31: =(F31-L31)*J31 -> 21032.797 | N31: 96876.89
B32: 44743 | C32: Petrobras | D32: 5108 | E32: 9474983 | F32: 29170027 | G32: =F32-SUM(L32:N32) -> 25669624 | H32: =+IF(G32=0,0,G32/E32) -> 2.7092 | I32: 0.12 | J32: 0 | K32: 0 | L32: =+I32*F32 -> 3500403.3 | M32: =(F32-L32)*J32 -> 0 | N32: =(F32-L32)*K32 -> 0
B33: 44743 | C33: Petrobras | D33: 5109 | E33: 288334 | F33: 1266703.7 | G33: =F33-SUM(L33:N33) -> 1114699.2 | H33: =+IF(G33=0,0,G33/E33) -> 3.866 | I33: 0.12 | J33: 0 | K33: 0 | L33: =+I33*F33 -> 152004.44 | M33: =(F33-L33)*J33 -> 0 | N33: =(F33-L33)*K33 -> 0
B34: 44743 | C34: Petrobras | D34: 3376 | E34: 6892 | F34: 23380.68 | G34: =F34-SUM(L34:N34) -> 18671.831 | H34: =+IF(G34=0,0,G34/E34) -> 2.7092036 | I34: 0.12 | J34: 0.0165 | K34: 0.076 | L34: =+I34*F34 -> 2805.6816 | M34: =(F34-L34)*J34 -> 339.48747 | N34: 1563.68
B35: 44743 | C35: Petrobras | D35: 3377 | E35: 108537 | F35: 334145.94 | G35: =F35-SUM(L35:N35) -> 294048.43 | H35: =+IF(G35=0,0,G35/E35) -> 2.7091999 | I35: 0.12 | J35: 0 | K35: 0 | L35: =+I35*F35 -> 40097.513 | M35: =(F35-L35)*J35 -> 0 | N35: =(F35-L35)*K35 -> 0
B36: 44743 | C36: Petrobras | D36: 5068 | E36: 163676 | F36: 555260.48 | G36: =F36-SUM(L36:N36) -> 443431.57 | H36: =+IF(G36=0,0,G36/E36) -> 2.7092034 | I36: 0.12 | J36: 0.0165 | K36: 0.076 | L36: =+I36*F36 -> 66631.258 | M36: =(F36-L36)*J36 -> 8062.3822 | N36: 37135.27
B37: 44743 | C37: Petrobras | D37: 5069 | E37: 59942 | F37: 184539.63 | G37: =F37-SUM(L37:N37) -> 162394.87 | H37: =+IF(G37=0,0,G37/E37) -> 2.7092001 | I37: 0.12 | J37: 0 | K37: 0 | L37: =+I37*F37 -> 22144.756 | M37: =(F37-L37)*J37 -> 0 | N37: =(F37-L37)*K37 -> 0
B38: 44743 | C38: Shell | D38: 257517 | E38: -7270 | F38: -16838.05 | G38: =F38-SUM(L38:N38) -> -14210.893 | H38: =+IF(G38=0,0,G38/E38) -> 1.9547308 | I38: 0.07 | J38: 0.0165 | K38: 0.076 | L38: =+I38*F38 -> -1178.6635 | M38: =(F38-L38)*J38 -> -258.37988 | N38: =(F38-L38)*K38 -> -1190.1134
B39: 44743 | C39: Shell | D39: 257516 | E39: -11 | F39: -22.42 | G39: =F39-SUM(L39:N39) -> -18.92192 | H39: =+IF(G39=0,0,G39/E39) -> 1.7201745 | I39: 0.07 | J39: 0.0165 | K39: 0.076 | L39: =+I39*F39 -> -1.5694 | M39: =(F39-L39)*J39 -> -0.3440349 | N39: =(F39-L39)*K39 -> -1.5846456
B40: 44743 | C40: Shell | D40: 99 | E40: 24845885 | F40: 57545554 | G40: =F40-SUM(L40:N40) -> 48567009 | H40: =+IF(G40=0,0,G40/E40) -> 1.9547305 | I40: 0.07 | J40: 0.0165 | K40: 0.076 | L40: =+I40*F40 -> 4028188.8 | M40: =(F40-L40)*J40 -> 883036.53 | N40: =(F40-L40)*K40 -> 4067319.8
B41: 44743 | C41: New Fortress (Petrolina) | D41: 18-1 | E41: =291501+336567 -> 628068 | F41: 3174339.1 | G41: =F41-SUM(L41:N41) -> 2362184.4 | H41: =+IF(G41=0,0,G41/E41) -> 3.7610329 | I41: 0.18 | J41: 0.0165 | K41: 0.076 | L41: =+I41*F41 -> 571381.04 | M41: =20482.42+22466.39 -> 42948.81 | N41: =94343.27+103481.55 -> 197824.82
B42: 44743 | C42: New Fortress (Garanhuns) | D42: 19-1 | E42: =28223+45126 -> 73349 | F42: 360140.95 | G42: =F42-SUM(L42:N42) -> 267998.89 | H42: =+IF(G42=0,0,G42/E42) -> 3.6537497 | I42: 0.18 | J42: 0.0165 | K42: 0.076 | L42: =+I42*F42 -> 64825.371 | M42: =(F42-L42)*J42 -> 4872.7071 | N42: =(F42-L42)*K42 -> 22443.984
E45: =SUM(E18:E44) -> 51051841 | G45: =SUM(G18:G44) -> 1.2120124e+08
B48: Observações Relevantes: Publicação da Lei Complementar 194/2022, no DOU de 23.06.2022, Edição Extra, prevendo, até 31.12.2022, redução a zero da alíquota de PIS/COFINS incidente sobre a receita ou o faturamento na venda de gás natural veicular classificado nos códigos 2711.11.00 ou 2711.21.00 da NCM. "Art. 9º-B Até 31 de dezembro de 2022, ficam reduzidas a 0 (zero) as alíquotas das contribuições de que tratam o caput e o § 1º do art. 9º desta Lei Complementar incidentes sobre a receita ou o faturamento na venda ou sobre a importação de gás natural veicular classificado nos códigos 2711.11.00 ou 2711.21.00 da NCM." Dessa forma, a Copergás informou a Petrobras todo o volume de GNV e GNC veicular comercializado durante o mês de julho/22, o qual foi sensibilizado nas notas do supridor e, consequentemente, foram emitidas com alíquotas zero de PIS/Cofins Além disso, houve a necessidade de emissão por parte da Copergás da emissão de 2 notas de devolução para regularização das notas fiscais emitidas pela Shell em abril e maio/22.

Sheet ago22
C2: RELATÓRIO MENSAL DE ACOMPANHAMENTO DO CUSTO DO GÁS
C3: 44774
C5: Petrobras | D5: =SUMIF($C$18:$G$39,$C$5:$C$7,$G$18:$G$39)/SUMIF($C$18:$G$39,$C$5:$C$7,$E$18:$E$39) -> 2.8424561
C6: Shell | D6: =SUMIF($C$18:$G$39,$C$5:$C$7,$G$18:$G$39)/SUMIF($C$18:$G$39,$C$5:$C$7,$E$18:$E$39) -> 2.2936709
C7: NFE | D7: =SUM(G40:G41)/SUM(E40:E41) -> 3.9387137
M8: Poderação QDC | N8: Poderação QDR
C9: Custo Médio Ponderado real | D9: =+G44/E44 -> 2.5950619 | L9: =+C5 -> Petrobras | M9: =790000/1580000 -> 0.5 | N9: =+SUM(E18:E36)/E44 -> 0.49740843
L10: =+C6 -> Shell | M10: 0.47468354 | N10: =+SUM(E37:E39)/E44 -> 0.48531502
C11: Custo Médio Ponderado tarifa | D11: 2.5881 | L11: =+C7 -> NFE | M11: 0.025316456 | N11: =+SUM(E40:E41)/E44 -> 0.017276549
L12: Total | M12: =SUM(M9:M11) -> 1 | N12: =SUM(N9:N11) -> 1
L16: CONFORME XML DA NOTA
B17: Mês | C17: Supridor | D17: Nota Fiscal | E17: Vol m³ | F17: Compra R$ c/tributos | G17: Compra R$ s/tributos | H17: Custo | I17: ICMS | J17: PIS | K17: COFINS | L17: ICMS | M17: PIS | N17: COFINS
B18: 44774 | C18: Petrobras | D18: 430938-2 | E18: 49820 | F18: 166718.95 | G18: =F18-SUM(L18:N18) -> 140706.79 | H18: =+IF(G18=0,0,G18/E18) -> 2.8243034 | I18: 0.07 | J18: 0.0165 | K18: 0.076 | L18: =+I18*F18 -> 11670.327 | M18: 2558.3 | N18: 11783.53
B19: =B18 -> 44774 | C19: Petrobras | D19: 11063-6 | E19: 1765563 | F19: 6244026.5 | G19: =F19-SUM(L19:N19) -> 4986485.8 | H19: =+IF(G19=0,0,G19/E19) -> 2.8243035 | I19: 0.12 | J19: 0.0165 | K19: 0.076 | L19: =+I19*F19 -> 749283.18 | M19: 90663.27 | N19: 417594.25
B20: =B19 -> 44774 | C20: Petrobras | D20: 3612-12 | E20: 782661 | F20: 2767930.7 | G20: =F20-SUM(L20:N20) -> 2210472.2 | H20: =+IF(G20=0,0,G20/E20) -> 2.8243035 | I20: 0.12 | J20: 0.0165 | K20: 0.076 | L20: =+I20*F20 -> 332151.68 | M20: 40190.35 | N20: 185116.44
B21: =B20 -> 44774 | C21: Petrobras | D21: 5174-4 | E21: 7429162 | F21: 26273707 | G21: =F21-SUM(L21:N21) -> 20982209 | H21: =+IF(G21=0,0,G21/E21) -> 2.8243035 | I21: 0.12 | J21: 0.0165 | K21: 0.076 | L21: =+I21*F21 -> 3152844.8 | M21: 381494.22 | N21: 1757159.2
B22: =B21 -> 44774 | C22: Petrobras | D22: 3609-12 | E22: 33788 | F22: 170869.3 | G22: =F22-SUM(L22:N22) -> 136456.39 | H22: =+IF(G22=0,0,G22/E22) -> 4.0386052 | I22: 0.12 | J22: 0.0165 | K22: 0.076 | L22: =+I22*F22 -> 20504.316 | M22: 2481.02 | N22: 11427.57
B23: =B22 -> 44774 | C23: Petrobras | D23: 11064-6 | E23: 51566 | F23: 260774.42 | G23: =F23-SUM(L23:N23) -> 208254.72 | H23: =+IF(G23=0,0,G23/E23) -> 4.0386053 | I23: 0.12 | J23: 0.0165 | K23: 0.076 | L23: =+I23*F23 -> 31292.93 | M23: 3786.44 | N23: 17440.33
B24: =B23 -> 44774 | C24: Petrobras | D24: 5175-4 | E24: 88538 | F24: 447745.52 | G24: =F24-SUM(L24:N24) -> 357570.03 | H24: =+IF(G24=0,0,G24/E24) -> 4.0386052 | I24: 0.12 | J24: 0.0165 | K24: 0.076 | L24: =+I24*F24 -> 53729.462 | M24: 6501.26 | N24: 29944.77
B25: =B24 -> 44774 | C25: Petrobras | D25: 430939-2 | E25: 78616 | F25: 238747.49 | G25: =F25-SUM(L25:N25) -> 222035.17 | H25: =+IF(G25=0,0,G25/E25) -> 2.8243 | I25: 0.07 | J25: 0 | K25: 0 | L25: =+I25*F25 -> 16712.324 | M25: 0 | N25: 0
B26: =B25 -> 44774 | C26: Petrobras | D26: 11065-6 | E26: 2168885 | F26: 6960888.5 | G26: =F26-SUM(L26:N26) -> 6125581.9 | H26: =+IF(G26=0,0,G26/E26) -> 2.8243 | I26: 0.12 | J26: 0 | K26: 0 | L26: =+I26*F26 -> 835306.62 | M26: 0 | N26: 0
B27: =B26 -> 44774 | C27: Petrobras | D27: 5176-4 | E27: 11016082 | F27: 35355364 | G27: =F27-SUM(L27:N27) -> 31112720 | H27: =+IF(G27=0,0,G27/E27) -> 2.8243 | I27: 0.12 | J27: 0 | K27: 0 | L27: =+I27*F27 -> 4242643.7 | M27: 0 | N27: 0
B28: =B27 -> 44774 | C28: Petrobras | D28: 3610-12 | E28: 876339 | F28: 2812550.3 | G28: =F28-SUM(L28:N28) -> 2475044.2 | H28: =+IF(G28=0,0,G28/E28) -> 2.8243 | I28: 0.12 | J28: 0 | K28: 0 | L28: =+I28*F28 -> 337506.03 | M28: 0 | N28: 0
B29: =B28 -> 44774 | C29: Petrobras | D29: 11066-6 | E29: 59053 | F29: 271013.01 | G29: =F29-SUM(L29:N29) -> 238491.45 | H29: =+IF(G29=0,0,G29/E29) -> 4.0386001 | I29: 0.12 | J29: 0 | K29: 0 | L29: =+I29*F29 -> 32521.561 | M29: 0 | N29: 0
B30: =B29 -> 44774 | C30: Petrobras | D30: 5177-4 | E30: 96350 | F30: 442180.81 | G30: =F30-SUM(L30:N30) -> 389119.11 | H30: =+IF(G30=0,0,G30/E30) -> 4.0386 | I30: 0.12 | J30: 0 | K30: 0 | L30: =+I30*F30 -> 53061.697 | M30: 0 | N30: 0
B31: =B30 -> 44774 | C31: Petrobras | D31: 3611-12 | E31: 37505 | F31: 172122.38 | G31: =F31-SUM(L31:N31) -> 151467.69 | H31: =+IF(G31=0,0,G31/E31) -> 4.0386 | I31: 0.12 | J31: 0 | K31: 0 | L31: =+I31*F31 -> 20654.686 | M31: 0 | N31: 0
B32: =B31 -> 44774 | C32: Petrobras | G32: =F32-SUM(L32:N32) -> 0 | H32: =+IF(G32=0,0,G32/E32) -> 0 | L32: =+I32*F32 -> 0 | M32: =(F32-L32)*J32 -> 0 | N32: =(F32-L32)*K32 -> 0
B33: =B32 -> 44774 | C33: Petrobras | G33: =F33-SUM(L33:N33) -> 0 | H33: =+IF(G33=0,0,G33/E33) -> 0 | L33: =+I33*F33 -> 0 | M33: =(F33-L33)*J33 -> 0 | N33: =(F33-L33)*K33 -> 0
B34: =B33 -> 44774 | C34: Petrobras | G34: =F34-SUM(L34:N34) -> 0 | H34: =+IF(G34=0,0,G34/E34) -> 0 | L34: =+I34*F34 -> 0 | M34: =(F34-L34)*J34 -> 0 | N34: =(F34-L34)*K34 -> 0
B35: =B34 -> 44774 | C35: Petrobras | G35: =F35-SUM(L35:N35) -> 0 | H35: =+IF(G35=0,0,G35/E35) -> 0 | L35: =+I35*F35 -> 0 | M35: =(F35-L35)*J35 -> 0 | N35: =(F35-L35)*K35 -> 0
B36: =B35 -> 44774 | C36: Petrobras | G36: =F36-SUM(L36:N36) -> 0 | H36: =+IF(G36=0,0,G36/E36) -> 0 | L36: =+I36*F36 -> 0 | M36: =(F36-L36)*J36 -> 0 | N36: =(F36-L36)*K36 -> 0
B37: =B36 -> 44774 | C37: Shell | G37: =F37-SUM(L37:N37) -> 0 | H37: =+IF(G37=0,0,G37/E37) -> 0 | J37: 0.0165 | K37: 0.076
B38: =B37 -> 44774 | C38: Shell | G38: =F38-SUM(L38:N38) -> 0 | H38: =+IF(G38=0,0,G38/E38) -> 0 | J38: 0.0165 | K38: 0.076
B39: =B38 -> 44774 | C39: Shell | D39: 221-1 | E39: 23937439 | F39: 65054778 | G39: =F39-SUM(L39:N39) -> 54904606 | H39: =+IF(G39=0,0,G39/E39) -> 2.2936709 | I39: 0.07 | J39: 0.0165 | K39: 0.076 | L39: =+I39*F39 -> 4553834.5 | M39: 998265.57 | N39: 4598071.7
B40: =B39 -> 44774 | C40: New Fortress (Petrolina) | D40: 21-1 | E40: =625673+153041 -> 778714 | F40: 4130352.9 | G40: =F40-SUM(L40:N40) -> 3073602.1 | H40: =+IF(G40=0,0,G40/E40) -> 3.9470231 | I40: 0.18 | J40: 0.0165 | K40: 0.076 | L40: =+I40*F40 -> 743463.52 | M40: 55883.67 | N40: 257403.59
B41: =B40 -> 44774 | C41: New Fortress (Garanhuns) | D41: 21-1 | E41: =58033+15393 -> 73426 | F41: 379941.32 | G41: =F41-SUM(L41:N41) -> 282733.34 | H41: =+IF(G41=0,0,G41/E41) -> 3.8505889 | I41: 0.18 | J41: 0.0165 | K41: 0.076 | L41: 68389.43 | M41: 5140.61 | N41: 23677.94
E44: =SUM(E18:E43) -> 49323507 | G44: =SUM(G18:G43) -> 1.2799756e+08
B47: Observações Relevantes: Publicação da Lei Complementar 194/2022, no DOU de 23.06.2022, Edição Extra, prevendo, até 31.12.2022, redução a zero da alíquota de PIS/COFINS incidente sobre a receita ou o faturamento na venda de gás natural veicular classificado nos códigos 2711.11.00 ou 2711.21.00 da NCM. "Art. 9º-B Até 31 de dezembro de 2022, ficam reduzidas a 0 (zero) as alíquotas das contribuições de que tratam o caput e o § 1º do art. 9º desta Lei Complementar incidentes sobre a receita ou o faturamento na venda ou sobre a importação de gás natural veicular classificado nos códigos 2711.11.00 ou 2711.21.00 da NCM." Dessa forma, a Copergás informou a Petrobras todo o volume de GNV e GNC veicular comercializado durante o mês de julho/22, o qual foi sensibilizado nas notas do supridor e, consequentemente, foram emitidas com alíquotas zero de PIS/Cofins NewFortress - GARANHUNS: Desconto de 5% do Preço do Gás, sobre o volume de 15.393 m³, pelo não cumprimento da estocagem mínima prevista em contrato (cláusula 6.2.4.). NewFortress - PETROLINA: Desconto de 5% do Preço do Gás, sobre o volume de 153.041m³, pelo não cumprimento da estocagem mínima prevista em contrato (cláusula 6.2.4.).

Sheet set22
C2: RELATÓRIO MENSAL DE ACOMPANHAMENTO DO CUSTO DO GÁS
C3: 44805
C5: Petrobras | D5: =SUMIF($C$18:$G$41,$C$5:$C$7,$G$18:$G$41)/SUMIF($C$18:$G$41,$C$5:$C$7,$E$18:$E$41) -> 2.8371809
C6: Shell | D6: =SUMIF($C$18:$G$41,$C$5:$C$7,$G$18:$G$41)/SUMIF($C$18:$G$41,$C$5:$C$7,$E$18:$E$41) -> 2.2936709
C7: NFE | D7: =SUM(G42:G43)/SUM(E42:E43) -> 3.9776824
M8: Poderação QDC | N8: Poderação QDR
C9: Custo Médio Ponderado real | D9: =+G46/E46 -> 2.5732966 | L9: =+C5 -> Petrobras | M9: =790000/1580000 -> 0.5 | N9: =+SUM(E18:E36)/E46 -> 0.46571209
L10: =+C6 -> Shell | M10: 0.47468354 | N10: =+SUM(E39:E41)/E46 -> 0.51841141
C11: Custo Médio Ponderado tarifa | D11: 2.5881 | L11: =+C7 -> NFE | M11: 0.025316456 | N11: =+SUM(E42:E43)/E46 -> 0.015675117
L12: Total | M12: =SUM(M9:M11) -> 1 | N12: =SUM(N9:N11) -> 0.99979861
L16: CONFORME XML DA NOTA
B17: Mês | C17: Supridor | D17: Nota Fiscal | E17: Vol m³ | F17: Compra R$ c/tributos | G17: Compra R$ s/tributos | H17: Custo | I17: ICMS | J17: PIS | K17: COFINS | L17: ICMS | M17: PIS | N17: COFINS
B18: 44805 | C18: Petrobras | D18: 11181-6 | E18: 931775 | F18: 3295281.9 | G18: =F18-SUM(L18:N18) -> 2631615.4 | H18: =+IF(G18=0,0,G18/E18) -> 2.8243035 | I18: 0.12 | J18: 0.0165 | K18: 0.076 | L18: =+I18*F18 -> 395433.83 | M18: 47847.49 | N18: 220385.16
B19: =B18 -> 44805 | C19: Petrobras | D19: 431038-2 | E19: 154512 | F19: 517062.99 | G19: =F19-SUM(L19:N19) -> 436388.75 | H19: =+IF(G19=0,0,G19/E19) -> 2.8243033 | I19: 0.07 | J19: 0.0165 | K19: 0.076 | L19: =+I19*F19 -> 36194.409 | M19: 7934.33 | N19: 36545.5
B20: =B19 -> 44805 | C20: Petrobras | D20: 3427-28 | E20: 57232 | F20: 202404.63 | G20: =F20-SUM(L20:N20) -> 161640.53 | H20: =+IF(G20=0,0,G20/E20) -> 2.8243034 | I20: 0.12 | J20: 0.0165 | K20: 0.076 | L20: =+I20*F20 -> 24288.556 | M20: 2938.92 | N20: 13536.62
B21: =B20 -> 44805 | C21: Petrobras | D21: 5161-24 | E21: 620441 | F21: 2194229.3 | G21: =F21-SUM(L21:N21) -> 1752313.7 | H21: =+IF(G21=0,0,G21/E21) -> 2.8243035 | I21: 0.12 | J21: 0.0165 | K21: 0.076 | L21: =+I21*F21 -> 263307.52 | M21: 31860.21 | N21: 146747.86
B22: =B21 -> 44805 | C22: Petrobras | D22: 5255-4 | E22: 9069958 | F22: 32076487 | G22: =F22-SUM(L22:N22) -> 25616314 | H22: =+IF(G22=0,0,G22/E22) -> 2.8243035 | I22: 0.12 | J22: 0.0165 | K22: 0.076 | L22: =+I22*F22 -> 3849178.4 | M22: 465750.59 | N22: 2145243.4
A23: PGU1 | B23: =B22 -> 44805 | C23: Petrobras | D23: 5256-4 | E23: 58832 | F23: 297519.31 | G23: =F23-SUM(L23:N23) -> 237599.22 | H23: =+IF(G23=0,0,G23/E23) -> 4.0386052 | I23: 0.12 | J23: 0.0165 | K23: 0.076 | L23: =+I23*F23 -> 35702.317 | M23: 4319.98 | N23: 19897.79
A24: PGU1 | B24: =B23 -> 44805 | C24: Petrobras | D24: 5162-24 | E24: 23610 | F24: 119398.13 | G24: =F24-SUM(L24:N24) -> 95351.464 | H24: =+IF(G24=0,0,G24/E24) -> 4.038605 | I24: 0.12 | J24: 0.0165 | K24: 0.076 | L24: =+I24*F24 -> 14327.776 | M24: 1733.66 | N24: 7985.23
A25: GNV | B25: =B24 -> 44805 | C25: Petrobras | D25: 5257-4 | E25: 11048991 | F25: 35460983 | G25: =F25-SUM(L25:N25) -> 31205665 | H25: =+IF(G25=0,0,G25/E25) -> 2.8243 | I25: 0.12 | J25: 0 | K25: 0 | L25: =+I25*F25 -> 4255318 | M25: 0 | N25: 0
A26: GNV | B26: =B25 -> 44805 | C26: Petrobras | D26: 5163-24 | E26: 829476 | F26: 2662146.7 | G26: =F26-SUM(L26:N26) -> 2342689.1 | H26: =+IF(G26=0,0,G26/E26) -> 2.8243 | I26: 0.12 | J26: 0 | K26: 0 | L26: =+I26*F26 -> 319457.6 | M26: 0 | N26: 0
A27: GNV | B27: =B26 -> 44805 | C27: Petrobras | D27: 431037-2 | E27: 236824.77 | F27: 719208.82 | G27: =F27-SUM(L27:N27) -> 668864.2 | H27: =+IF(G27=0,0,G27/E27) -> 2.8243 | I27: 0.07 | J27: 0 | K27: 0 | L27: =+I27*F27 -> 50344.617 | M27: 0 | N27: 0
A28: GNV | B28: =B27 -> 44805 | C28: Petrobras | D28: 431036-2 | E28: 53023.229 | F28: 161025.28 | G28: =F28-SUM(L28:N28) -> 149753.51 | H28: =+IF(G28=0,0,G28/E28) -> 2.8243001 | I28: 0.07 | J28: 0 | K28: 0 | L28: =+I28*F28 -> 11271.77 | M28: 0 | N28: 0
A29: GNV | B29: =B28 -> 44805 | C29: Petrobras | D29: 11183-6 | E29: 1026055 | F29: 3293053.6 | G29: =F29-SUM(L29:N29) -> 2897887.1 | H29: =+IF(G29=0,0,G29/E29) -> 2.8243 | I29: 0.12 | J29: 0 | K29: 0 | L29: =+I29*F29 -> 395166.43 | M29: 0 | N29: 0
A30: PGU1 GNV | B30: =B29 -> 44805 | C30: Petrobras | D30: 431035-2 | E30: 10196 | F30: 44276.96 | G30: =F30-SUM(L30:N30) -> 41177.573 | H30: =+IF(G30=0,0,G30/E30) -> 4.0386007 | I30: 0.07 | J30: 0 | K30: 0 | L30: =+I30*F30 -> 3099.3872 | M30: 0 | N30: 0
A31: PGU1 GNV | B31: =B30 -> 44805 | C31: Petrobras | D31: 5258-4 | E31: 76482 | F31: 351000.24 | G31: =F31-SUM(L31:N31) -> 308880.21 | H31: =+IF(G31=0,0,G31/E31) -> 4.0386001 | I31: 0.12 | J31: 0 | K31: 0 | L31: =+I31*F31 -> 42120.029 | M31: 0 | N31: 0
A32: PGU1 GNV | B32: =B31 -> 44805 | C32: Petrobras | D32: 5164-24 | E32: 24647 | F32: 113112.92 | G32: =F32-SUM(L32:N32) -> 99539.37 | H32: =+IF(G32=0,0,G32/E32) -> 4.0385998 | I32: 0.12 | J32: 0 | K32: 0 | L32: =+I32*F32 -> 13573.55 | M32: 0 | N32: 0
A33: PGU1 GNV | B33: =B32 -> 44805 | C33: Petrobras | D33: 11184-6 | E33: 17182 | F33: 78853.67 | G33: =F33-SUM(L33:N33) -> 69391.23 | H33: =+IF(G33=0,0,G33/E33) -> 4.0386003 | I33: 0.12 | J33: 0 | K33: 0 | L33: =+I33*F33 -> 9462.4404 | M33: 0 | N33: 0
A34: PGU1 | B34: =B33 -> 44805 | C34: Petrobras | D34: 431034-2 | E34: 6901 | F34: 33022.76 | G34: =F34-SUM(L34:N34) -> 27870.417 | H34: =+IF(G34=0,0,G34/E34) -> 4.0386055 | I34: 0.07 | J34: 0.0165 | K34: 0.076 | L34: =+I34*F34 -> 2311.5932 | M34: 506.73 | N34: 2334.02
... A38: PGU1 | B38: =B37 -> 44805 | C38: Petrobras | D38: 3428-28 | E38: 2947 | F38: 14903.27 | G38: =F38-SUM(L38:N38) -> 11901.758 | H38: =+IF(G38=0,0,G38/E38) -> 4.0386012 | I38: 0.12 | J38: 0.0165 | K38: 0.076 | L38: =+I38*F38 -> 1788.3924 | M38: 216.4 | N38: 996.72
B39: =B36 -> 44805 | C39: Shell | G39: =F39-SUM(L39:N39) -> 0 | H39: =+IF(G39=0,0,G39/E39) -> 0 | J39: 0.0165 | K39: 0.076 | L39: =+I39*F39 -> 0
B40: =B39 -> 44805 | C40: Shell | D40: 224-1 | E40: 27183472 | F40: 73876522 | G40: =F40-SUM(L40:N40) -> 62349938 | H40: =+IF(G40=0,0,G40/E40) -> 2.2936709 | I40: 0.07 | J40: 0.0165 | K40: 0.076 | L40: =+I40*F40 -> 5171356.5 | M40: 1133635.2 | N40: 5221592.6
B41: =B40 -> 44805 | C41: Shell | G41: =F41-SUM(L41:N41) -> 0 | H41: =+IF(G41=0,0,G41/E41) -> 0 | J41: 0.0165 | K41: 0.076 | L41: =+I41*F41 -> 0
B42: =B41 -> 44805 | C42: New Fortress (Petrolina) | D42: 22-1 | E42: 748197 | F42: 4007866.9 | G42: =F42-SUM(L42:N42) -> 2982454.1 | H42: =+IF(G42=0,0,G42/E42) -> 3.9861883 | I42: 0.18 | J42: 0.0165 | K42: 0.076 | L42: =+I42*F42 -> 721416.04 | M42: 54226.44 | N42: 249770.26
B43: =B42 -> 44805 | C43: New Fortress (Garanhuns) | D43: 22-1 | E43: 73745 | F43: 385634.73 | G43: =F43-SUM(L43:N43) -> 286970.08 | H43: =+IF(G43=0,0,G43/E43) -> 3.8913835 | I43: 0.18 | J43: 0.0165 | K43: 0.076 | L43: =+I43*F43 -> 69414.251 | M43: 5217.64 | N43: 24032.76
E46: =SUM(E18:E45) -> 52436099 | G46: =SUM(G18:G45) -> 1.3493363e+08
B49: Observações Relevantes: Publicação da Lei Complementar 194/2022, no DOU de 23.06.2022, Edição Extra, prevendo, até 31.12.2022, redução a zero da alíquota de PIS/COFINS incidente sobre a receita ou o faturamento na venda de gás natural veicular classificado nos códigos 2711.11.00 ou 2711.21.00 da NCM. "Art. 9º-B Até 31 de dezembro de 2022, ficam reduzidas a 0 (zero) as alíquotas das contribuições de que tratam o caput e o § 1º do art. 9º desta Lei Complementar incidentes sobre a receita ou o faturamento na venda ou sobre a importação de gás natural veicular classificado nos códigos 2711.11.00 ou 2711.21.00 da NCM." Dessa forma, a Copergás informou a Petrobras todo o volume de GNV e GNC veicular comercializado durante o mês de julho/22, o qual foi sensibilizado nas notas do supridor e, consequentemente, foram emitidas com alíquotas zero de PIS/Cofins

Sheet Out22
C2: RELATÓRIO MENSAL DE ACOMPANHAMENTO DO CUSTO DO GÁS
C3: 44835
C5: Petrobras | D5: =SUMIF($C$18:$G$41,$C$5:$C$7,$G$18:$G$41)/SUMIF($C$18:$G$41,$C$5:$C$7,$E$18:$E$41) -> 2.8279084
C6: Shell | D6: =SUMIF($C$18:$G$41,$C$5:$C$7,$G$18:$G$41)/SUMIF($C$18:$G$41,$C$5:$C$7,$E$18:$E$41) -> 2.2936709
C7: NFE | D7: =SUM(G42:G43)/SUM(E42:E43) -> 3.9778993
M8: Poderação QDC | N8: Poderação QDR
C9: Custo Médio Ponderado real | D9: =+G46/E46 -> 2.5644388 | L9: =+C5 -> Petrobras | M9: =790000/1580000 -> 0.5 | N9: =+SUM(E18:E36)/E46 -> 0.45788139
L10: =+C6 -> Shell | M10: 0.47468354 | N10: =+SUM(E39:E41)/E46 -> 0.52651804
C11: Custo Médio Ponderado tarifa | D11: 2.5881 | L11: =+C7 -> NFE | M11: 0.025316456 | N11: =+SUM(E42:E43)/E46 -> 0.01549241
L12: Total | M12: =SUM(M9:M11) -> 1 | N12: =SUM(N9:N11) -> 0.99989184
L16: CONFORME XML DA NOTA
B17: Mês | C17: Supridor | D17: Nota Fiscal | E17: Vol m³ | F17: Compra R$ c/tributos | G17: Compra R$ s/tributos | H17: Custo | I17: ICMS | J17: PIS | K17: COFINS | L17: ICMS | M17: PIS | N17: COFINS
B18: =C3 -> 44835 | C18: Petrobras | D18: 5182-24 | E18: 1665749 | F18: 5891027.9 | G18: =F18-SUM(L18:N18) -> 4704580.8 | H18: =+IF(G18=0,0,G18/E18) -> 2.8243035 | I18: 0.12 | J18: 0.0165 | K18: 0.076 | L18: =+I18*F18 -> 706923.35 | M18: 85537.73 | N18: 393986.06
B19: =B18 -> 44835 | C19: Petrobras | D19: 11226-6 | E19: 2242408 | F19: 7930419.4 | G19: =F19-SUM(L19:N19) -> 6333240.8 | H19: =+IF(G19=0,0,G19/E19) -> 2.8243035 | I19: 0.12 | J19: 0.0165 | K19: 0.076 | L19: =+I19*F19 -> 951650.32 | M19: 115149.69 | N19: 530378.52
B20: =B19 -> 44835 | C20: Petrobras | D20: 3433-28 | E20: 46601 | F20: 164807.41 | G20: =F20-SUM(L20:N20) -> 131615.37 | H20: =+IF(G20=0,0,G20/E20) -> 2.8243036 | I20: 0.12 | J20: 0.0165 | K20: 0.076 | L20: =+I20*F20 -> 19776.889 | M20: 2393 | N20: 11022.15
B21: =B20 -> 44835 | C21: Petrobras | D21: 431127-2 | E21: 5103020 | F21: 17076880 | G21: =F21-SUM(L21:N21) -> 14412476 | H21: =+IF(G21=0,0,G21/E21) -> 2.8243033 | I21: 0.07 | J21: 0.0165 | K21: 0.076 | L21: =+I21*F21 -> 1195381.6 | M21: 262044.72 | N21: 1206976.8
B22: =B21 -> 44835 | C22: Petrobras | D22: 4068-4 | E22: 5946 | F22: 21028.41 | G22: =F22-SUM(L22:N22) -> 16793.311 | H22: =+IF(G22=0,0,G22/E22) -> 2.8243039 | I22: 0.12 | J22: 0.0165 | K22: 0.076 | L22: =+I22*F22 -> 2523.4092 | M22: 305.33 | N22: 1406.36
B23: =B22 -> 44835 | C23: Petrobras | D23: 5286-4 | E23: 2048670 | F23: 7245252.5 | G23: =F23-SUM(L23:N23) -> 5786065.9 | H23: =+IF(G23=0,0,G23/E23) -> 2.8243035 | I23: 0.12 | J23: 0.0165 | K23: 0.076 | L23: =+I23*F23 -> 869430.3 | M23: 105201.07 | N23: 484555.24
A24: PGU1 | B24: =B23 -> 44835 | C24: Petrobras | D24: 431128-2 | E24: 2927 | F24: 14006.32 | G24: =F24-SUM(L24:N24) -> 11820.998 | H24: =+IF(G24=0,0,G24/E24) -> 4.0386053 | I24: 0.07 | J24: 0.0165 | K24: 0.076 | L24: =+I24*F24 -> 980.4424 | M24: 214.93 | N24: 989.95
A25: GNV | B25: =B24 -> 44835 | C25: Petrobras | D25: 5184-24 | E25: 1647668 | F25: 5288078.1 | G25: =F25-SUM(L25:N25) -> 4653508.7 | H25: =+IF(G25=0,0,G25/E25) -> 2.8243 | I25: 0.12 | J25: 0 | K25: 0 | L25: =+I25*F25 -> 634569.37 | M25: 0 | N25: 0
A26: GNV | B26: =B25 -> 44835 | C26: Petrobras | D26: 4069-4 | E26: 12235 | F26: 39267.4 | G26: =F26-SUM(L26:N26) -> 34555.312 | H26: =+IF(G26=0,0,G26/E26) -> 2.8243001 | I26: 0.12 | J26: 0 | K26: 0 | L26: =+I26*F26 -> 4712.088 | M26: 0 | N26: 0
A27: GNV | B27: =B26 -> 44835 | C27: Petrobras | D27: 11228-6 | E27: 2602754 | F27: 8353361.5 | G27: =F27-SUM(L27:N27) -> 7350958.1 | H27: =+IF(G27=0,0,G27/E27) -> 2.8243 | I27: 0.12 | J27: 0 | K27: 0 | L27: =+I27*F27 -> 1002403.4 | M27: 0 | N27: 0
A28: GNV | B28: =B27 -> 44835 | C28: Petrobras | D28: 5288-4 | E28: 2598620 | F28: 8340093.7 | G28: =F28-SUM(L28:N28) -> 7339282.5 | H28: =+IF(G28=0,0,G28/E28) -> 2.8243 | I28: 0.12 | J28: 0 | K28: 0 | L28: =+I28*F28 -> 1000811.2 | M28: 0 | N28: 0
A29: GNV | B29: =B28 -> 44835 | C29: Petrobras | D29: 431129-2 | E29: 6706259 | F29: 20366115 | G29: =F29-SUM(L29:N29) -> 18940487 | H29: =+IF(G29=0,0,G29/E29) -> 2.8243 | I29: 0.07 | J29: 0 | K29: 0 | L29: =+I29*F29 -> 1425628.1 | M29: 0 | N29: 0
A30: PGU1 GNV | B30: =B29 -> 44835 | C30: Petrobras | D30: 5289-4 | E30: 7539 | F30: 34598.88 | G30: =F30-SUM(L30:N30) -> 30447.014 | H30: =+IF(G30=0,0,G30/E30) -> 4.0386012 | I30: 0.12 | J30: 0 | K30: 0 | L30: =+I30*F30 -> 4151.8656 | M30: 0 | N30: 0
A31: PGU1 GNV | B31: =B30 -> 44835 | C31: Petrobras | D31: 5185-24 | E31: 22648 | F31: 103938.88 | G31: =F31-SUM(L31:N31) -> 91466.214 | H31: =+IF(G31=0,0,G31/E31) -> 4.0386001 | I31: 0.12 | J31: 0 | K31: 0 | L31: =+I31*F31 -> 12472.666 | M31: 0 | N31: 0
A32: PGU1 GNV | B32: =B31 -> 44835 | C32: Petrobras | D32: 431130-2 | E32: 184 | F32: 799.03 | G32: =F32-SUM(L32:N32) -> 743.0979 | H32: =+IF(G32=0,0,G32/E32) -> 4.0385755 | I32: 0.07 | J32: 0 | K32: 0 | L32: =+I32*F32 -> 55.9321 | M32: 0 | N32: 0
A33: PGU1 GNV | B33: =B32 -> 44835 | C33: Petrobras | D33: 11229-6 | E33: 7118 | F33: 32666.76 | G33: =F33-SUM(L33:N33) -> 28746.749 | H33: =+IF(G33=0,0,G33/E33) -> 4.0385992 | I33: 0.12 | J33: 0 | K33: 0 | L33: =+I33*F33 -> 3920.0112 | M33: 0 | N33: 0
A34: PGU1 | B34: =B33 -> 44835 | C34: Petrobras | D34: 5183-24 | E34: 20188 | F34: 102092.74 | G34: =F34-SUM(L34:N34) -> 81531.361 | H34: =+IF(G34=0,0,G34/E34) -> 4.0386052 | I34: 0.12 | J34: 0.0165 | K34: 0.076 | L34: =+I34*F34 -> 12251.129 | M34: 1482.39 | N34: 6827.86
A35: GNV | B35: =B34 -> 44835 | C35: Petrobras | G35: =F35-SUM(L35:N35) -> 0 | H35: =+IF(G35=0,0,G35/E35) -> 0 | J35: 0 | K35: 0 | L35: =+I35*F35 -> 0 | M35: 0 | N35: 0
A36: PGU1 | B36: =B35 -> 44835 | C36: Petrobras | D36: 5287-4 | E36: 7076 | F36: 35784.03 | G36: =F36-SUM(L36:N36) -> 28577.166 | H36: =+IF(G36=0,0,G36/E36) -> 4.0386046 | I36: 0.12 | J36: 0.0165 | K36: 0.076 | L36: =+I36*F36 -> 4294.0836 | M36: 519.58 | N36: 2393.2
A37: GNV | B37: =B36 -> 44835 | C37: Petrobras | G37: =F37-SUM(L37:N37) -> 0 | H37: =+IF(G37=0,0,G37/E37) -> 0 | J37: 0 | K37: 0 | L37: =+I37*F37 -> 0 | M37: 0 | N37: 0
A38: PGU1 | B38: =B37 -> 44835 | C38: Petrobras | D38: 11227-6 | E38: 5846 | F38: 29563.81 | G38: =F38-SUM(L38:N38) -> 23609.683 | H38: =+IF(G38=0,0,G38/E38) -> 4.0386047 | I38: 0.12 | J38: 0.0165 | K38: 0.076 | L38: =+I38*F38 -> 3547.6572 | M38: 429.27 | N38: 1977.2
B39: =B36 -> 44835 | C39: Shell | D39: 290-1 | E39: 28457289 | F39: 77338374 | G39: =F39-SUM(L39:N39) -> 65271654 | H39: =+IF(G39=0,0,G39/E39) -> 2.2936709 | I39: 0.07 | J39: 0.0165 | K39: 0.076 | L39: =+I39*F39 -> 5413686.2 | M39: 1186757.4 | N39: 5466276.3
B40: =B39 -> 44835 | C40: Shell | G40: =F40-SUM(L40:N40) -> 0 | H40: =+IF(G40=0,0,G40/E40) -> 0 | I40: 0.07 | J40: 0.0165 | K40: 0.076 | L40: =+I40*F40 -> 0
B41: =B40 -> 44835 | C41: Shell | G41: =F41-SUM(L41:N41) -> 0 | H41: =+IF(G41=0,0,G41/E41) -> 0 | J41: 0.0165 | K41: 0.076 | L41: =+I41*F41 -> 0
B42: =B41 -> 44835 | C42: New Fortress (Petrolina) | D42: 23-1 | E42: 764125 | F42: 4093188.4 | G42: =F42-SUM(L42:N42) -> 3045946.1 | H42: =+IF(G42=0,0,G42/E42) -> 3.9861883 | I42: 0.18 | J42: 0.0165 | K42: 0.076 | L42: =+I42*F42 -> 736773.91 | M42: 55380.84 | N42: 255087.5
B43: =B42 -> 44835 | C43: New Fortress (Garanhuns) | D43: 25-1 | E43: 73210 | F43: 382837.05 | G43: =F43-SUM(L43:N43) -> 284888.19 | H43: =+IF(G43=0,0,G43/E43) -> 3.8913836 | I43: 0.18 | J43: 0.0165 | K43: 0.076 | L43: =+I43*F43 -> 68910.669 | M43: 5179.79 | N43: 23858.4
E46: =SUM(E18:E45) -> 54048080 | G46: =SUM(G18:G45) -> 1.38603e+08
B49: Observações Relevantes: Publicação da Lei Complementar 194/2022, no DOU de 23.06.2022, Edição Extra, prevendo, até 31.12.2022, redução a zero da alíquota de PIS/COFINS incidente sobre a receita ou o faturamento na venda de gás natural veicular classificado nos códigos 2711.11.00 ou 2711.21.00 da NCM. "Art. 9º-B Até 31 de dezembro de 2022, ficam reduzidas a 0 (zero) as alíquotas das contribuições de que tratam o caput e o § 1º do art. 9º desta Lei Complementar incidentes sobre a receita ou o faturamento na venda ou sobre a importação de gás natural veicular classificado nos códigos 2711.11.00 ou 2711.21.00 da NCM." Dessa forma, a Copergás informou a Petrobras todo o volume de GNV e GNC veicular comercializado durante o mês de julho/22, o qual foi sensibilizado nas notas do supridor e, consequentemente, foram emitidas com alíquotas zero de PIS/Cofins

Sheet Nov22
C2: RELATÓRIO MENSAL DE ACOMPANHAMENTO DO CUSTO DO GÁS
C3: 44866
C5: Petrobras | D5: =SUMIF($C$18:$G$41,$C$5:$C$7,$G$18:$G$41)/SUMIF($C$18:$G$41,$C$5:$C$7,$E$18:$E$41) -> 2.7589443
C6: Shell | D6: =SUMIF($C$18:$G$41,$C$5:$C$7,$G$18:$G$41)/SUMIF($C$18:$G$41,$C$5:$C$7,$E$18:$E$41) -> 2.2372089
C7: NFE | D7: =SUM(G42:G43)/SUM(E42:E43) -> 3.9479926
M8: Poderação QDC | N8: Poderação QDR
C9: Custo Médio Ponderado real | D9: =+G46/E46 -> 2.5262808 | L9: =+C5 -> Petrobras | M9: =790000/1580000 -> 0.5 | N9: =+SUM(E18:E36)/E46 -> 0.44982574
L10: =+C6 -> Shell | M10: 0.47468354 | N10: =+SUM(E39:E41)/E46 -> 0.48636201
C11: Custo Médio Ponderado tarifa | D11: 2.4673 | L11: =+C7 -> NFE | M11: 0.025316456 | N11: =+SUM(E42:E43)/E46 -> 0.017735837
L12: Total | M12: =SUM(M9:M11) -> 1 | N12: =SUM(N9:N11) -> 0.95392358
L16: CONFORME XML DA NOTA
B17: Mês | C17: Supridor | D17: Nota Fiscal | E17: Vol m³ | F17: Compra R$ c/tributos | G17: Compra R$ s/tributos | H17: Custo | I17: ICMS | J17: PIS | K17: COFINS | L17: ICMS | M17: PIS | N17: COFINS
B18: =C3 -> 44866 | C18: Petrobras | D18: 5305-4 | E18: 1042198 | F18: 3503617.5 | G18: =F18-SUM(L18:N18) -> 2797989 | H18: =+IF(G18=0,0,G18/E18) -> 2.6847 | I18: 0.12 | J18: 0.0165 | K18: 0.076 | L18: =+I18*F18 -> 420434.1 | M18: =J18*(F18-L18) -> 50872.527 | N18: =K18*(F18-L18) -> 234321.94
B19: =B18 -> 44866 | C19: Petrobras | D19: 431220-2 | E19: 5731508 | F19: 18232032 | G19: =F19-SUM(L19:N19) -> 15387380 | H19: =+IF(G19=0,0,G19/E19) -> 2.6847 | I19: 0.07 | J19: 0.0165 | K19: 0.076 | L19: =+I19*F19 -> 1276242.3 | M19: =J19*(F19-L19) -> 279770.54 | N19: =K19*(F19-L19) -> 1288640
B20: =B19 -> 44866 | C20: Petrobras | D20: 3442-28 | E20: 43523 | F20: 146313.8 | G20: =F20-SUM(L20:N20) -> 116846.2 | H20: =+IF(G20=0,0,G20/E20) -> 2.6847001 | I20: 0.12 | J20: 0.0165 | K20: 0.076 | L20: =+I20*F20 -> 17557.656 | M20: =J20*(F20-L20) -> 2124.4764 | N20: =K20*(F20-L20) -> 9785.4669
B21: =B20 -> 44866 | C21: Petrobras | D21: 3635-12 | E21: 1570195 | F21: 5278615.7 | G21: =F21-SUM(L21:N21) -> 4215502.5 | H21: =+IF(G21=0,0,G21/E21) -> 2.6847 | I21: 0.12 | J21: 0.0165 | K21: 0.076 | L21: =+I21*F21 -> 633433.89 | M21: =J21*(F21-L21) -> 76645.5 | N21: =K21*(F21-L21) -> 353033.82
B22: =B21 -> 44866 | C22: Petrobras | D22: 11253-6 | E22: 444800 | F22: 1495310 | G22: =F22-SUM(L22:N22) -> 1194154.6 | H22: =+IF(G22=0,0,G22/E22) -> 2.6847 | I22: 0.12 | J22: 0.0165 | K22: 0.076 | L22: =+I22*F22 -> 179437.2 | M22: =J22*(F22-L22) -> 21711.901 | N22: =K22*(F22-L22) -> 100006.33
B23: =B22 -> 44866 | C23: Petrobras | D23: 5204-24 | E23: 1941806 | F23: 6527882 | G23: =F23-SUM(L23:N23) -> 5213166.6 | H23: =+IF(G23=0,0,G23/E23) -> 2.6847 | I23: 0.12 | J23: 0.0165 | K23: 0.076 | L23: =+I23*F23 -> 783345.84 | M23: =J23*(F23-L23) -> 94784.847 | N23: =K23*(F23-L23) -> 436584.75
A24: PGU1 | B24: =B23 -> 44866 | C24: Petrobras | D24: 5205-24 | E24: 26883 | F24: 128901.05 | G24: =F24-SUM(L24:N24) -> 102940.38 | H24: =+IF(G24=0,0,G24/E24) -> 3.8291998 | I24: 0.12 | J24: 0.0165 | K24: 0.076 | L24: =+I24*F24 -> 15468.126 | M24: =J24*(F24-L24) -> 1871.6432 | N24: =K24*(F24-L24) -> 8620.9022
A25: GNV | B25: =B24 -> 44866 | C25: Petrobras | D25: 431222-2 | E25: 7248357 | F25: 20924370 | G25: =F25-SUM(L25:N25) -> 19459664 | H25: =+IF(G25=0,0,G25/E25) -> 2.6847 | I25: 0.07 | J25: 0 | K25: 0 | L25: =+I25*F25 -> 1464705.9 | M25: =J25*(F25-L25) -> 0 | N25: =K25*(F25-L25) -> 0
A26: GNV | B26: =B25 -> 44866 | C26: Petrobras | D26: 11254-6 | E26: 534781 | F26: 1631507.4 | G26: =F26-SUM(L26:N26) -> 1435726.5 | H26: =+IF(G26=0,0,G26/E26) -> 2.6847 | I26: 0.12 | J26: 0 | K26: 0 | L26: =+I26*F26 -> 195780.89 | M26: =J26*(F26-L26) -> 0 | N26: =K26*(F26-L26) -> 0
A27: GNV | B27: =B26 -> 44866 | C27: Petrobras | D27: 5306-4 | E27: 1343800 | F27: 4099658.9 | G27: =F27-SUM(L27:N27) -> 3607699.9 | H27: =+IF(G27=0,0,G27/E27) -> 2.6847 | I27: 0.12 | J27: 0 | K27: 0 | L27: =+I27*F27 -> 491959.07 | M27: =J27*(F27-L27) -> 0 | N27: =K27*(F27-L27) -> 0
A28: GNV | B28: =B27 -> 44866 | C28: Petrobras | D28: 3632-12 | E28: 1471236 | F28: 4488440.1 | G28: =F28-SUM(L28:N28) -> 3949827.3 | H28: =+IF(G28=0,0,G28/E28) -> 2.6847 | I28: 0.12 | J28: 0 | K28: 0 | L28: =+I28*F28 -> 538612.81 | M28: =J28*(F28-L28) -> 0 | N28: =K28*(F28-L28) -> 0
A29: GNV | B29: =B28 -> 44866 | C29: Petrobras | D29: 3443-28 | E29: 51300 | F29: 156505.81 | G29: =F29-SUM(L29:N29) -> 137725.11 | H29: =+IF(G29=0,0,G29/E29) -> 2.6847001 | I29: 0.12 | J29: 0 | K29: 0 | L29: =+I29*F29 -> 18780.697 | M29: =J29*(F29-L29) -> 0 | N29: =K29*(F29-L29) -> 0
A30: PGU1 GNV | B30: =B29 -> 44866 | C30: Petrobras | D30: 5207-24 | E30: 23273 | F30: 101269.28 | G30: =F30-SUM(L30:N30) -> 89116.966 | H30: =+IF(G30=0,0,G30/E30) -> 3.8291998 | I30: 0.12 | J30: 0 | K30: 0 | L30: =+I30*F30 -> 12152.314 | M30: =J30*(F30-L30) -> 0 | N30: =K30*(F30-L30) -> 0
A31: PGU1 GNV | B31: =B30 -> 44866 | C31: Petrobras | D31: 431223-2 | E31: 52153 | F31: 214735.77 | G31: =F31-SUM(L31:N31) -> 199704.27 | H31: =+IF(G31=0,0,G31/E31) -> 3.8292 | I31: 0.07 | J31: 0 | K31: 0 | L31: =+I31*F31 -> 15031.504 | M31: =J31*(F31-L31) -> 0 | N31: =K31*(F31-L31) -> 0
A32: PGU1 GNV | B32: =B31 -> 44866 | C32: Petrobras | D32: 3633-12 | E32: 21115 | F32: 91879.05 | G32: =F32-SUM(L32:N32) -> 80853.564 | H32: =+IF(G32=0,0,G32/E32) -> 3.8292003 | I32: 0.12 | J32: 0 | K32: 0 | L32: =+I32*F32 -> 11025.486 | M32: =J32*(F32-L32) -> 0 | N32: =K32*(F32-L32) -> 0
A33: PGU1 GNV | B33: =B32 -> 44866 | C33: Petrobras | G33: =F33-SUM(L33:N33) -> 0 | H33: =+IF(G33=0,0,G33/E33) -> 0 | J33: 0 | K33: 0 | L33: =+I33*F33 -> 0 | M33: =J33*(F33-L33) -> 0 | N33: =K33*(F33-L33) -> 0
A34: PGU1 | B34: =B33 -> 44866 | C34: Petrobras | D34: 3631-12 | E34: 57885 | F34: 277552.27 | G34: =F34-SUM(L34:N34) -> 221653.24 | H34: =+IF(G34=0,0,G34/E34) -> 3.8292 | I34: 0.12 | J34: 0.0165 | K34: 0.076 | L34: =+I34*F34 -> 33306.272 | M34: =J34*(F34-L34) -> 4030.059 | N34: =K34*(F34-L34) -> 18562.696
A35: PGU2 GNV | B35: =B34 -> 44866 | C35: Petrobras | D35: 3634-12 | E35: 182818 | F35: 1033274.9 | G35: =F35-SUM(L35:N35) -> 909281.89 | H35: =+IF(G35=0,0,G35/E35) -> 4.9737 | I35: 0.12 | J35: 0 | K35: 0 | L35: =+I35*F35 -> 123992.99 | M35: =J35*(F35-L35) -> 0 | N35: =K35*(F35-L35) -> 0
A36: PGU2 | B36: =B35 -> 44866 | C36: Petrobras | D36: 3636-12 | E36: 501191 | F36: 3121429.6 | G36: =F36-SUM(L36:N36) -> 2492773.7 | H36: =+IF(G36=0,0,G36/E36) -> 4.9737 | I36: 0.12 | J36: 0.0165 | K36: 0.076 | L36: =+I36*F36 -> 374571.55 | M36: =J36*(F36-L36) -> 45323.158 | N36: =K36*(F36-L36) -> 208761.21
A37: GNV | B37: =B36 -> 44866 | C37: Petrobras | D37: 5206-24 | E37: 2238417 | F37: 6828952.4 | G37: =F37-SUM(L37:N37) -> 6009478.1 | H37: =+IF(G37=0,0,G37/E37) -> 2.6847 | I37: 0.12 | J37: 0 | K37: 0 | L37: =+I37*F37 -> 819474.29 | M37: =J37*(F37-L37) -> 0 | N37: =K37*(F37-L37) -> 0
A38: PGU1 | B38: =B37 -> 44866 | C38: Petrobras | D38: 431221-2 | E38: 44665 | F38: 202649.63 | G38: =F38-SUM(L38:N38) -> 171031.22 | H38: =+IF(G38=0,0,G38/E38) -> 3.8292001 | I38: 0.07 | J38: 0.0165 | K38: 0.076 | L38: =+I38*F38 -> 14185.474 | M38: =J38*(F38-L38) -> 3109.6586 | N38: =K38*(F38-L38) -> 14323.276
B39: =B36 -> 44866 | C39: Shell | D39: 344-1 | E39: 24099191 | F39: 63882136 | G39: =F39-SUM(L39:N39) -> 53914925 | H39: =+IF(G39=0,0,G39/E39) -> 2.2372089 | I39: 0.07 | J39: 0.0165 | K39: 0.076 | L39: =+I39*F39 -> 4471749.5 | M39: =J39*(F39-L39) -> 980271.37 | N39: =K39*(F39-L39) -> 4515189.3
B40: =B39 -> 44866 | C40: Shell | G40: =F40-SUM(L40:N40) -> 0 | H40: =+IF(G40=0,0,G40/E40) -> 0 | J40: 0.0165 | K40: 0.076 | L40: =+I40*F40 -> 0 | M40: =J40*(F40-L40) -> 0 | N40: =K40*(F40-L40) -> 0
B41: =B40 -> 44866 | C41: Shell | G41: =F41-SUM(L41:N41) -> 0 | H41: =+IF(G41=0,0,G41/E41) -> 0 | J41: 0.0165 | K41: 0.076 | L41: =+I41*F41 -> 0 | M41: =J41*(F41-L41) -> 0 | N41: =K41*(F41-L41) -> 0
B42: =B41 -> 44866 | C42: New Fortress (Petrolina) | D42: 24-1 | E42: 811765 | F42: 4315261.6 | G42: =F42-SUM(L42:N42) -> 3211201.9 | H42: =+IF(G42=0,0,G42/E42) -> 3.955827 | I42: 0.18 | J42: 0.0165 | K42: 0.076 | L42: =+I42*F42 -> 776747.08 | M42: =J42*(F42-L42) -> 58385.489 | N42: =K42*(F42-L42) -> 268927.1
B43: =B42 -> 44866 | C43: New Fortress (Garanhuns) | D43: 26-1 | E43: 67044 | F43: 347147.13 | G43: =F43-SUM(L43:N43) -> 258329.54 | H43: =+IF(G43=0,0,G43/E43) -> 3.8531343 | I43: 0.18 | J43: 0.0165 | K43: 0.076 | L43: =+I43*F43 -> 62486.483 | M43: =J43*(F43-L43) -> 4696.9007 | N43: =K43*(F43-L43) -> 21634.209
E46: =SUM(E18:E45) -> 49549904 | G46: =SUM(G18:G45) -> 1.2517697e+08
B49: Observações Relevantes: Publicação da Lei Complementar 194/2022, no DOU de 23.06.2022, Edição Extra, prevendo, até 31.12.2022, redução a zero da alíquota de PIS/COFINS incidente sobre a receita ou o faturamento na venda de gás natural veicular classificado nos códigos 2711.11.00 ou 2711.21.00 da NCM. "Art. 9º-B Até 31 de dezembro de 2022, ficam reduzidas a 0 (zero) as alíquotas das contribuições de que tratam o caput e o § 1º do art. 9º desta Lei Complementar incidentes sobre a receita ou o faturamento na venda ou sobre a importação de gás natural veicular classificado nos códigos 2711.11.00 ou 2711.21.00 da NCM." Dessa forma, a Copergás informou a Petrobras todo o volume de GNV e GNC veicular comercializado durante o mês de julho/22, o qual foi sensibilizado nas notas do supridor e, consequentemente, foram emitidas com alíquotas zero de PIS/Cofins

Sheet Dez22
C2: RELATÓRIO MENSAL DE ACOMPANHAMENTO DO CUSTO DO GÁS
C3: 44896
C5: Petrobras | D5: =SUMIF($C$18:$G$41,$C$5:$C$7,$G$18:$G$41)/SUMIF($C$18:$G$41,$C$5:$C$7,$E$18:$E$41) -> 2.7364128
C6: Shell | D6: =SUMIF($C$18:$G$41,$C$5:$C$7,$G$18:$G$41)/SUMIF($C$18:$G$41,$C$5:$C$7,$E$18:$E$41) -> 2.2372089
C7: NFE | D7: =SUM(G42:G43)/SUM(E42:E43) -> 3.9480201
M8: Poderação QDC | N8: Poderação QDR
C9: Custo Médio Ponderado real | D9: =+G46/E46 -> 2.5188015 | L9: =+C5 -> Petrobras | M9: =790000/1580000 -> 0.5 | N9: =+SUM(E18:E36)/E46 -> 0.49742037
L10: =+C6 -> Shell | M10: 0.47468354 | N10: =+SUM(E39:E41)/E46 -> 0.48092622
C11: Custo Médio Ponderado tarifa | D11: 2.4673 | L11: =+C7 -> NFE | M11: 0.025316456 | N11: =+SUM(E42:E43)/E46 -> 0.018381742
L12: Total | M12: =SUM(M9:M11) -> 1 | N12: =SUM(N9:N11) -> 0.99672834
L16: CONFORME XML DA NOTA
B17: Mês | C17: Supridor | D17: Nota Fiscal | E17: Vol m³ | F17: Compra R$ c/tributos | G17: Compra R$ s/tributos | H17: Custo | I17: ICMS | J17: PIS | K17: COFINS | L17: ICMS | M17: PIS | N17: COFINS
B18: =C3 -> 44896 | C18: Petrobras | D18: 5238-24 | E18: 277882 | F18: 934172.06 | G18: =F18-SUM(L18:N18) -> 746029.81 | H18: =+IF(G18=0,0,G18/E18) -> 2.6847 | I18: 0.12 | J18: 0.0165 | K18: 0.076 | L18: =+I18*F18 -> 112100.65 | M18: =J18*(F18-L18) -> 13564.178 | N18: =K18*(F18-L18) -> 62477.427
B19: =B18 -> 44896 | C19: Petrobras | D19: 431307-2 | E19: 6886454 | F19: 21905937 | G19: =F19-SUM(L19:N19) -> 18488063 | H19: =+IF(G19=0,0,G19/E19) -> 2.6847 | I19: 0.07 | J19: 0.0165 | K19: 0.076 | L19: =+I19*F19 -> 1533415.6 | M19: =J19*(F19-L19) -> 336146.6 | N19: =K19*(F19-L19) -> 1548311.6
B20: =B19 -> 44896 | C20: Petrobras | D20: 3688-12 | E20: 2232102 | F20: 7503786.9 | G20: =F20-SUM(L20:N20) -> 5992524.2 | H20: =+IF(G20=0,0,G20/E20) -> 2.6847 | I20: 0.12 | J20: 0.0165 | K20: 0.076 | L20: =+I20*F20 -> 900454.43 | M20: =J20*(F20-L20) -> 108954.99 | N20: =K20*(F20-L20) -> 501853.27
B21: =B20 -> 44896 | C21: Petrobras | D21: 5350-4 | E21: 161172 | F21: 541821.27 | G21: =F21-SUM(L21:N21) -> 432698.47 | H21: =+IF(G21=0,0,G21/E21) -> 2.6847 | I21: 0.12 | J21: 0.0165 | K21: 0.076 | L21: =+I21*F21 -> 65018.552 | M21: =J21*(F21-L21) -> 7867.2448 | N21: =K21*(F21-L21) -> 36237.007
A22: PGU1 | B22: =B21 -> 44896 | C22: Petrobras | D22: 431308-2 | E22: 27075 | F22: 122842.02 | G22: =F22-SUM(L22:N22) -> 103675.59 | H22: =+IF(G22=0,0,G22/E22) -> 3.8292001 | I22: 0.07 | J22: 0.0165 | K22: 0.076 | L22: =+I22*F22 -> 8598.9414 | M22: =J22*(F22-L22) -> 1885.0108 | N22: =K22*(F22-L22) -> 8682.474
A23: PGU1 | B23: =B22 -> 44896 | C23: Petrobras | D23: 5351-4 | E23: 9324 | F23: 44707.56 | G23: =F23-SUM(L23:N23) -> 35703.457 | H23: =+IF(G23=0,0,G23/E23) -> 3.8291996 | I23: 0.12 | J23: 0.0165 | K23: 0.076 | L23: =+I23*F23 -> 5364.9072 | M23: =J23*(F23-L23) -> 649.15377 | N23: =K23*(F23-L23) -> 2990.0416
A24: PGU1 | B24: =B23 -> 44896 | C24: Petrobras | D24: 3684-12 | E24: 84725 | F24: 406247.15 | G24: =F24-SUM(L24:N24) -> 324428.97 | H24: =+IF(G24=0,0,G24/E24) -> 3.8292 | I24: 0.12 | J24: 0.0165 | K24: 0.076 | L24: =+I24*F24 -> 48749.658 | M24: =J24*(F24-L24) -> 5898.7086 | N24: =K24*(F24-L24) -> 27169.809
A25: PGU1 | B25: =B24 -> 44896 | C25: Petrobras | D25: 5239-24 | E25: 5327 | F25: 25542.39 | G25: =F25-SUM(L25:N25) -> 20398.153 | H25: =+IF(G25=0,0,G25/E25) -> 3.8292008 | I25: 0.12 | J25: 0.0165 | K25: 0.076 | L25: =+I25*F25 -> 3065.0868 | M25: =J25*(F25-L25) -> 370.8755 | N25: =K25*(F25-L25) -> 1708.275
A26: PGU2 | B26: =B25 -> 44896 | C26: Petrobras | D26: 3689-12 | E26: 212362 | F26: 1322595.6 | G26: =F26-SUM(L26:N26) -> 1056224.9 | H26: =+IF(G26=0,0,G26/E26) -> 4.9737 | I26: 0.12 | J26: 0.0165 | K26: 0.076 | L26: =+I26*F26 -> 158711.48 | M26: =J26*(F26-L26) -> 19204.089 | N26: =K26*(F26-L26) -> 88455.196
A27: PGU2 | B27: =B26 -> 44896 | C27: Petrobras | D27: 5352-4 | E27: 27316 | F27: 170124.71 | G27: =F27-SUM(L27:N27) -> 135861.59 | H27: =+IF(G27=0,0,G27/E27) -> 4.9737002 | I27: 0.12 | J27: 0.0165 | K27: 0.076 | L27: =+I27*F27 -> 20414.965 | M27: =J27*(F27-L27) -> 2470.2108 | N27: =K27*(F27-L27) -> 11377.941
A28: PGU2 | B28: =B27 -> 44896 | C28: Petrobras | D28: 5240-24 | E28: 12741 | F28: 79351.25 | G28: =F28-SUM(L28:N28) -> 63369.908 | H28: =+IF(G28=0,0,G28/E28) -> 4.9736997 | I28: 0.12 | J28: 0.0165 | K28: 0.076 | L28: =+I28*F28 -> 9522.15 | M28: =J28*(F28-L28) -> 1152.1802 | N28: =K28*(F28-L28) -> 5307.0116
A29: GNV | B29: =B28 -> 44896 | C29: Petrobras | D29: 5241-24 | E29: 388384 | F29: 1184880.1 | G29: =F29-SUM(L29:N29) -> 1042694.5 | H29: =+IF(G29=0,0,G29/E29) -> 2.6847 | I29: 0.12 | J29: 0 | K29: 0 | L29: =+I29*F29 -> 142185.62 | M29: =J29*(F29-L29) -> 0 | N29: =K29*(F29-L29) -> 0
A30: GNV | B30: =B29 -> 44896 | C30: Petrobras | D30: 431309-2 | E30: 11082911 | F30: 31993861 | G30: =F30-SUM(L30:N30) -> 29754291 | H30: =+IF(G30=0,0,G30/E30) -> 2.6847 | I30: 0.07 | J30: 0 | K30: 0 | L30: =+I30*F30 -> 2239570.3 | M30: =J30*(F30-L30) -> 0 | N30: =K30*(F30-L30) -> 0
A31: GNV | B31: =B30 -> 44896 | C31: Petrobras | D31: 5353-4 | E31: 336309 | F31: 1026010 | G31: =F31-SUM(L31:N31) -> 902888.77 | H31: =+IF(G31=0,0,G31/E31) -> 2.6847 | I31: 0.12 | J31: 0 | K31: 0 | L31: =+I31*F31 -> 123121.2 | M31: =J31*(F31-L31) -> 0 | N31: =K31*(F31-L31) -> 0
A32: GNV | B32: =B31 -> 44896 | C32: Petrobras | D32: 3685-12 | E32: 2151902 | F32: 6565012.8 | G32: =F32-SUM(L32:N32) -> 5777211.3 | H32: =+IF(G32=0,0,G32/E32) -> 2.6847 | I32: 0.12 | J32: 0 | K32: 0 | L32: =+I32*F32 -> 787801.54 | M32: =J32*(F32-L32) -> 0 | N32: =K32*(F32-L32) -> 0
A33: GNV PGU1 | B33: =B32 -> 44896 | C33: Petrobras | D33: 3686-12 | E33: 59399 | F33: 258466.65 | G33: =F33-SUM(L33:N33) -> 227450.65 | H33: =+IF(G33=0,0,G33/E33) -> 3.8292 | I33: 0.12 | J33: 0 | K33: 0 | L33: =+I33*F33 -> 31015.998 | M33: =J33*(F33-L33) -> 0 | N33: =K33*(F33-L33) -> 0
... A39: GNV PGU2 | B39: =B38 -> 44896 | C39: Petrobras | D39: 5355-4 | E39: 19091 | F39: 107901.03 | G39: =F39-SUM(L39:N39) -> 94952.906 | H39: =+IF(G39=0,0,G39/E39) -> 4.9737 | I39: 0.12 | J39: 0 | K39: 0 | L39: =+I39*F39 -> 12948.124 | M39: =J39*(F39-L39) -> 0 | N39: =K39*(F39-L39) -> 0
B40: =B39 -> 44896 | C40: Shell | D40: 460-1 | E40: 23188293 | F40: 61467527 | G40: =F40-SUM(L40:N40) -> 51877056 | H40: =+IF(G40=0,0,G40/E40) -> 2.2372089 | I40: 0.07 | J40: 0.0165 | K40: 0.076 | L40: =+I40*F40 -> 4302726.9 | M40: =J40*(F40-L40) -> 943219.2 | N40: =K40*(F40-L40) -> 4344524.8
B41: =B40 -> 44896 | C41: Shell | G41: =F41-SUM(L41:N41) -> 0 | H41: =+IF(G41=0,0,G41/E41) -> 0 | J41: 0.0165 | K41: 0.076 | L41: =+I41*F41 -> 0 | M41: =J41*(F41-L41) -> 0 | N41: =K41*(F41-L41) -> 0
B42: =B41 -> 44896 | C42: New Fortress (Petrolina) | D42: 25-1 | E42: 819589 | F42: 4356853.2 | G42: =F42-SUM(L42:N42) -> 3242152.3 | H42: =+IF(G42=0,0,G42/E42) -> 3.955827 | I42: 0.18 | J42: 0.0165 | K42: 0.076 | L42: =+I42*F42 -> 784233.57 | M42: =J42*(F42-L42) -> 58948.223 | N42: =K42*(F42-L42) -> 271519.09
B43: =B42 -> 44896 | C43: New Fortress (Garanhuns) | D43: 28-1 | E43: 67433 | F43: 349161.33 | G43: =F43-SUM(L43:N43) -> 259828.4 | H43: =+IF(G43=0,0,G43/E43) -> 3.8531343 | I43: 0.18 | J43: 0.0165 | K43: 0.076 | L43: =+I43*F43 -> 62849.039 | M43: =J43*(F43-L43) -> 4724.1528 | N43: =K43*(F43-L43) -> 21759.734
E46: =SUM(E18:E45) -> 48255601 | G46: =SUM(G18:G45) -> 1.2154628e+08
B49: Observações Relevantes: Publicação da Lei Complementar 194/2022, no DOU de 23.06.2022, Edição Extra, prevendo, até 31.12.2022, redução a zero da alíquota de PIS/COFINS incidente sobre a receita ou o faturamento na venda de gás natural veicular classificado nos códigos 2711.11.00 ou 2711.21.00 da NCM. "Art. 9º-B Até 31 de dezembro de 2022, ficam reduzidas a 0 (zero) as alíquotas das contribuições de que tratam o caput e o § 1º do art. 9º desta Lei Complementar incidentes sobre a receita ou o faturamento na venda ou sobre a importação de gás natural veicular classificado nos códigos 2711.11.00 ou 2711.21.00 da NCM." Dessa forma, a Copergás informou a Petrobras todo o volume de GNV e GNC veicular comercializado durante o mês de julho/22, o qual foi sensibilizado nas notas do supridor e, consequentemente, foram emitidas com alíquotas zero de PIS/Cofins

Sheet Jan23
C2: RELATÓRIO MENSAL DE ACOMPANHAMENTO DO CUSTO DO GÁS
C3: 44927
C5: Petrobras | D5: =SUMIF($C$18:$G$41,$C$5:$C$7,$G$18:$G$41)/SUMIF($C$18:$G$41,$C$5:$C$7,$E$18:$E$41) -> 2.685187
C6: Shell | D6: =SUMIF($C$18:$G$41,$C$5:$C$7,$G$18:$G$41)/SUMIF($C$18:$G$41,$C$5:$C$7,$E$18:$E$41) -> 2.2613466
C7: NFE | D7: =SUM(G42:G43)/SUM(E42:E43) -> 3.948078
M8: Poderação QDC | N8: Poderação QDR
C9: Custo Médio Ponderado real | D9: =+G46/E46 -> 2.4187732 | L9: =+C5 -> Petrobras | M9: =790000/1580000 -> 0.5 | N9: =+SUM(E18:E36)/E46 -> 0.29274688
L10: =+C6 -> Shell | M10: 0.47468354 | N10: =+SUM(E39:E41)/E46 -> 0.68748197
C11: Custo Médio Ponderado tarifa | D11: 2.4673 | L11: =+C7 -> NFE | M11: 0.025316456 | N11: =+SUM(E42:E43)/E46 -> 0.019771145
L12: Total | M12: =SUM(M9:M11) -> 1 | N12: =SUM(N9:N11) -> 1
L16: CONFORME XML DA NOTA
B17: Mês | C17: Supridor | D17: Nota Fiscal | E17: Vol m³ | F17: Compra R$ c/tributos | G17: Compra R$ s/tributos | H17: Custo | I17: ICMS | J17: PIS | K17: COFINS | L17: ICMS | M17: PIS | N17: COFINS
B18: =C3 -> 44927 | C18: Petrobras | D18: 5280-24 | E18: 1214 | F18: 4081.18 | G18: =F18-SUM(L18:N18) -> 3259.2303 | H18: =+IF(G18=0,0,G18/E18) -> 2.6847037 | I18: 0.12 | J18: 0.0165 | K18: 0.076 | L18: =+I18*F18 -> 489.7416 | M18: =J18*(F18-L18) -> 59.258734 | N18: =K18*(F18-L18) -> 272.94932
B19: =B18 -> 44927 | C19: Petrobras | D19: 431394-2 | E19: 29449 | F19: 93677.81 | G19: =F19-SUM(L19:N19) -> 79061.73 | H19: =+IF(G19=0,0,G19/E19) -> 2.6847 | I19: 0.07 | J19: 0.0165 | K19: 0.076 | L19: =+I19*F19 -> 6557.4467 | M19: =J19*(F19-L19) -> 1437.486 | N19: =K19*(F19-L19) -> 6621.1476
B20: =B19 -> 44927 | C20: Petrobras | D20: 11364-6 | E20: 90 | F20: 302.55 | G20: =F20-SUM(L20:N20) -> 241.61643 | H20: =+IF(G20=0,0,G20/E20) -> 2.684627 | I20: 0.12 | J20: 0.0165 | K20: 0.076 | L20: =+I20*F20 -> 36.306 | M20: =J20*(F20-L20) -> 4.393026 | N20: =K20*(F20-L20) -> 20.234544
B21: =B20 -> 44927 | C21: Petrobras | G21: =F21-SUM(L21:N21) -> 0 | H21: =+IF(G21=0,0,G21/E21) -> 0 | J21: 0.0165 | K21: 0.076 | L21: =+I21*F21 -> 0 | M21: =J21*(F21-L21) -> 0 | N21: =K21*(F21-L21) -> 0
A22: PGU1 | B22: =B21 -> 44927 | C22: Petrobras | D22: 431395-2 | E22: 14 | F22: 63.52 | G22: =F22-SUM(L22:N22) -> 53.609292 | H22: =+IF(G22=0,0,G22/E22) -> 3.8292351 | I22: 0.07 | J22: 0.0165 | K22: 0.076 | L22: =+I22*F22 -> 4.4464 | M22: =J22*(F22-L22) -> 0.9747144 | N22: =K22*(F22-L22) -> 4.4895936
A23: PGU1 | B23: =B22 -> 44927 | C23: Petrobras | G23: =F23-SUM(L23:N23) -> 0 | H23: =+IF(G23=0,0,G23/E23) -> 0 | J23: 0.0165 | K23: 0.076 | L23: =+I23*F23 -> 0 | M23: =J23*(F23-L23) -> 0 | N23: =K23*(F23-L23) -> 0
A24: PGU1 | B24: =B23 -> 44927 | C24: Petrobras | G24: =F24-SUM(L24:N24) -> 0 | H24: =+IF(G24=0,0,G24/E24) -> 0 | J24: 0.0165 | K24: 0.076 | L24: =+I24*F24 -> 0 | M24: =J24*(F24-L24) -> 0 | N24: =K24*(F24-L24) -> 0
A25: PGU1 | B25: =B24 -> 44927 | C25: Petrobras | G25: =F25-SUM(L25:N25) -> 0 | H25: =+IF(G25=0,0,G25/E25) -> 0 | J25: 0.0165 | K25: 0.076 | L25: =+I25*F25 -> 0 | M25: =J25*(F25-L25) -> 0 | N25: =K25*(F25-L25) -> 0
A26: PGU2 | B26: =B25 -> 44927 | C26: Petrobras | G26: =F26-SUM(L26:N26) -> 0 | H26: =+IF(G26=0,0,G26/E26) -> 0 | J26: 0.0165 | K26: 0.076 | L26: =+I26*F26 -> 0 | M26: =J26*(F26-L26) -> 0 | N26: =K26*(F26-L26) -> 0
A27: PGU2 | B27: =B26 -> 44927 | C27: Petrobras | G27: =F27-SUM(L27:N27) -> 0 | H27: =+IF(G27=0,0,G27/E27) -> 0 | J27: 0.0165 | K27: 0.076 | L27: =+I27*F27 -> 0 | M27: =J27*(F27-L27) -> 0 | N27: =K27*(F27-L27) -> 0
A28: PGU2 | B28: =B27 -> 44927 | C28: Petrobras | G28: =F28-SUM(L28:N28) -> 0 | H28: =+IF(G28=0,0,G28/E28) -> 0 | J28: 0.0165 | K28: 0.076 | L28: =+I28*F28 -> 0 | M28: =J28*(F28-L28) -> 0 | N28: =K28*(F28-L28) -> 0
A29: GNV | B29: =B28 -> 44927 | C29: Petrobras | D29: 11362-6 | E29: 73662 | F29: 224727.69 | G29: =F29-SUM(L29:N29) -> 197760.37 | H29: =+IF(G29=0,0,G29/E29) -> 2.6846999 | I29: 0.12 | J29: 0 | K29: 0 | L29: =+I29*F29 -> 26967.323 | M29: =J29*(F29-L29) -> 0 | N29: =K29*(F29-L29) -> 0
A30: GNV | B30: =B29 -> 44927 | C30: Petrobras | D30: 3460-28 | E30: 48206 | F30: 147066.65 | G30: =F30-SUM(L30:N30) -> 129418.65 | H30: =+IF(G30=0,0,G30/E30) -> 2.6847001 | I30: 0.12 | J30: 0 | K30: 0 | L30: =+I30*F30 -> 17647.998 | M30: =J30*(F30-L30) -> 0 | N30: =K30*(F30-L30) -> 0
A31: GNV | B31: =B30 -> 44927 | C31: Petrobras | D31: 5279-24 | E31: 206831 | F31: 630999.08 | G31: =F31-SUM(L31:N31) -> 555279.19 | H31: =+IF(G31=0,0,G31/E31) -> 2.6847 | I31: 0.12 | J31: 0 | K31: 0 | L31: =+I31*F31 -> 75719.89 | M31: =J31*(F31-L31) -> 0 | N31: =K31*(F31-L31) -> 0
A32: GNV | B32: =B31 -> 44927 | C32: Petrobras | D32: 431392-2 | E32: 12518840 | F32: 36139064 | G32: =F32-SUM(L32:N32) -> 33609330 | H32: =+IF(G32=0,0,G32/E32) -> 2.6847 | I32: 0.07 | J32: 0 | K32: 0 | L32: =+I32*F32 -> 2529734.5 | M32: =J32*(F32-L32) -> 0 | N32: =K32*(F32-L32) -> 0
A33: GNV PGU1 | B33: =B32 -> 44927 | C33: Petrobras | D33: 3461-28 | E33: 38 | F33: 165.35 | G33: =F33-SUM(L33:N33) -> 145.508 | H33: =+IF(G33=0,0,G33/E33) -> 3.8291579 | I33: 0.12 | J33: 0 | K33: 0 | L33: =+I33*F33 -> 19.842 | M33: =J33*(F33-L33) -> 0 | N33: =K33*(F33-L33) -> 0
A34: GNV PGU1 | B34: =B33 -> 44927 | C34: Petrobras | D34: 11363-6 | E34: 58 | F34: 252.38 | G34: =F34-SUM(L34:N34) -> 222.0944 | H34: =+IF(G34=0,0,G34/E34) -> 3.8292138 | I34: 0.12 | J34: 0 | K34: 0 | L34: =+I34*F34 -> 30.2856 | M34: =J34*(F34-L34) -> 0 | N34: =K34*(F34-L34) -> 0
A35: GNV PGU1 | B35: =B34 -> 44927 | C35: Petrobras | D35: 431393-2 | E35: 5372 | F35: 22118.77 | G35: =F35-SUM(L35:N35) -> 20570.456 | H35: =+IF(G35=0,0,G35/E35) -> 3.8291988 | I35: 0.07 | J35: 0 | K35: 0 | L35: =+I35*F35 -> 1548.3139 | M35: =J35*(F35-L35) -> 0 | N35: =K35*(F35-L35) -> 0
A36: GNV PGU1 | B36: =B35 -> 44927 | C36: Petrobras | G36: =F36-SUM(L36:N36) -> 0 | H36: =+IF(G36=0,0,G36/E36) -> 0 | J36: 0 | K36: 0 | L36: =+I36*F36 -> 0 | M36: =J36*(F36-L36) -> 0 | N36: =K36*(F36-L36) -> 0
A37: GNV PGU2 | B37: =B36 -> 44927 | C37: Petrobras | G37: =F37-SUM(L37:N37) -> 0 | H37: =+IF(G37=0,0,G37/E37) -> 0 | J37: 0 | K37: 0 | L37: =+I37*F37 -> 0 | M37: =J37*(F37-L37) -> 0 | N37: =K37*(F37-L37) -> 0
A38: GNV PGU2 | B38: =B37 -> 44927 | C38: Petrobras | G38: =F38-SUM(L38:N38) -> 0 | H38: =+IF(G38=0,0,G38/E38) -> 0 | J38: 0 | K38: 0 | L38: =+I38*F38 -> 0 | M38: =J38*(F38-L38) -> 0 | N38: =K38*(F38-L38) -> 0
A39: GNV PGU2 | B39: =B38 -> 44927 | C39: Petrobras | G39: =F39-SUM(L39:N39) -> 0 | H39: =+IF(G39=0,0,G39/E39) -> 0 | J39: 0 | K39: 0 | L39: =+I39*F39 -> 0 | M39: =J39*(F39-L39) -> 0 | N39: =K39*(F39-L39) -> 0
B40: =B39 -> 44927 | C40: Shell | D40: 966-1 | E40: 30256043 | F40: 77748046 | G40: =F40-SUM(L40:N40) -> 65617407 | H40: =+IF(G40=0,0,G40/E40) -> 2.1687372 | I40: 0.07 | J40: 0.0165 | K40: 0.076 | L40: =+I40*F40 -> 5442363.2 | M40: =J40*(F40-L40) -> 1193043.8 | N40: =K40*(F40-L40) -> 5495231.9
B41: =B40 -> 44927 | C41: Shell | D41: 998-1 | E41: 0 | F41: 3319995.6 | G41: =F41-SUM(L41:N41) -> 2801993.3 | H41: =+IF(G41=0,0,G41/E41) -> #DIV/0! | I41: 0.07 | J41: 0.0165 | K41: 0.076 | L41: =+I41*F41 -> 232399.69 | M41: =J41*(F41-L41) -> 50945.332 | N41: =K41*(F41-L41) -> 234657.29
B42: =B41 -> 44927 | C42: New Fortress (Petrolina) | D42: 27-1 | E42: 804469 | F42: 4276476.8 | G42: =F42-SUM(L42:N42) -> 3182340.2 | H42: =+IF(G42=0,0,G42/E42) -> 3.955827 | I42: 0.18 | J42: 0.0165 | K42: 0.076 | L42: =+I42*F42 -> 769765.82 | M42: =J42*(F42-L42) -> 57860.731 | N42: =K42*(F42-L42) -> 266510.03
B43: =B42 -> 44927 | C43: New Fortress (Garanhuns) | D43: 30-1 | E43: 65658 | F43: 339970.56 | G43: =F43-SUM(L43:N43) -> 252989.09 | H43: =+IF(G43=0,0,G43/E43) -> 3.8531343 | I43: 0.18 | J43: 0.0165 | K43: 0.076 | L43: =+I43*F43 -> 61194.701 | M43: =J43*(F43-L43) -> 4599.8017 | N43: =K43*(F43-L43) -> 21186.965
E46: =SUM(E18:E45) -> 44009944 | G46: =SUM(G18:G45) -> 1.0645007e+08
C47: Shell | D47: 966-1 e 998-1 | E47: =E40+E41 -> 30256043 | F47: =F40+F41 -> 81068042 | G47: =F47-SUM(L47:N47) -> 68419400 | H47: =+IF(G47=0,0,G47/E47) -> 2.2613466 | I47: 0.07 | J47: 0.0165 | K47: 0.076 | L47: =+I47*F47 -> 5674762.9 | M47: =J47*(F47-L47) -> 1243989.1 | N47: =K47*(F47-L47) -> 5729889.2
B49: Observações Relevantes: Publicação da Lei Complementar 194/2022, no DOU de 23.06.2022, Edição Extra, prevendo, até 31.12.2022, redução a zero da alíquota de PIS/COFINS incidente sobre a receita ou o faturamento na venda de gás natural veicular classificado nos códigos 2711.11.00 ou 2711.21.00 da NCM. "Art. 9º-B Até 31 de dezembro de 2022, ficam reduzidas a 0 (zero) as alíquotas das contribuições de que tratam o caput e o § 1º do art. 9º desta Lei Complementar incidentes sobre a receita ou o faturamento na venda ou sobre a importação de gás natural veicular classificado nos códigos 2711.11.00 ou 2711.21.00 da NCM." Dessa forma, a Copergás informou a Petrobras todo o volume de GNV e GNC veicular comercializado durante o mês de janeiro/23, o qual foi sensibilizado nas notas do supridor e, consequentemente, foram emitidas com alíquotas zero de PIS/Cofins. O Supridor Shell emitiu Nota de Complemento de preço (com volume zero) para ajustar a tarifa na NFe 966-1.

Sheet Fev23
C2: RELATÓRIO MENSAL DE ACOMPANHAMENTO DO CUSTO DO GÁS
C3: 44958
C5: Petrobras | D5: =SUMIF($C$18:$G$30,$C$5:$C$7,$G$18:$G$30)/SUMIF($C$18:$G$30,$C$5:$C$7,$E$18:$E$30) -> 2.4378002
C6: Shell | D6: =SUMIF($C$18:$G$30,$C$5:$C$7,$G$18:$G$30)/SUMIF($C$18:$G$30,$C$5:$C$7,$E$18:$E$30) -> 1.8185551
C7: NFE | D7: =SUM(G31:G32)/SUM(E31:E32) -> 3.6624321
M8: Poderação QDC | N8: Poderação QDR
C9: Custo Médio Ponderado real | D9: =+G35/E35 -> 2.0534504 | L9: =+C5 -> Petrobras | M9: =790000/1580000 -> 0.5 | N9: =+SUM(E18:E29)/E35 -> 0.33191736
L10: =+C6 -> Shell | M10: 0.47468354 | N10: =+SUM(E30:E30)/E35 -> 0.65216124
C11: Custo Médio Ponderado tarifa | D11: 2.0702 | L11: =+C7 -> NFE | M11: 0.025316456 | N11: =+SUM(E31:E32)/E35 -> 0.0159214
L12: Total | M12: =SUM(M9:M11) -> 1 | N12: =SUM(N9:N11) -> 1
L16: CONFORME XML DA NOTA
B17: Mês | C17: Supridor | D17: Nota Fiscal | E17: Vol m³ | F17: Compra R$ c/tributos | G17: Compra R$ s/tributos | H17: Custo | I17: ICMS | J17: PIS | K17: COFINS | L17: ICMS | M17: PIS | N17: COFINS
B18: =C3 -> 44958 | C18: Petrobras | D18: 431499-2 | E18: 2693463 | F18: 7712659.8 | G18: =F18-SUM(L18:N18) -> 6509292 | H18: =+IF(G18=0,0,G18/E18) -> 2.4167 | I18: 0.07 | J18: 0.0165 | K18: 0.076 | L18: =+I18*F18 -> 539886.18 | M18: =J18*(F18-L18) -> 118350.76 | N18: =K18*(F18-L18) -> 545130.79
B19: =B18 -> 44958 | C19: Petrobras | D19: 5318-24 | E19: 42008 | F19: 127123.38 | G19: =F19-SUM(L19:N19) -> 101520.73 | H19: =+IF(G19=0,0,G19/E19) -> 2.4166999 | I19: 0.12 | J19: 0.0165 | K19: 0.076 | L19: =+I19*F19 -> 15254.806 | M19: =J19*(F19-L19) -> 1845.8315 | N19: =K19*(F19-L19) -> 8502.0117
A20: PGU1 | B20: =B19 -> 44958 | C20: Petrobras | D20: 431500-2 | E20: 64822 | F20: 263228.13 | G20: =F20-SUM(L20:N20) -> 222157.96 | H20: =+IF(G20=0,0,G20/E20) -> 3.4272 | I20: 0.07 | J20: 0.0165 | K20: 0.076 | L20: =+I20*F20 -> 18425.969 | M20: =J20*(F20-L20) -> 4039.2357 | N20: =K20*(F20-L20) -> 18604.964
A21: PGU1 | B21: =B20 -> 44958 | C21: Petrobras | D21: 5319-24 | E21: 289 | F21: 1240.25 | G21: =F21-SUM(L21:N21) -> 990.46365 | H21: =+IF(G21=0,0,G21/E21) -> 3.4272099 | I21: 0.12 | J21: 0.0165 | K21: 0.076 | L21: =+I21*F21 -> 148.83 | M21: =J21*(F21-L21) -> 18.00843 | N21: =K21*(F21-L21) -> 82.94792
A22: PGU2 | B22: =B21 -> 44958 | C22: Petrobras | D22: 431501-2 | E22: 1727 | F22: 9080.73 | G22: =F22-SUM(L22:N22) -> 7663.9091 | H22: =+IF(G22=0,0,G22/E22) -> 4.4377007 | I22: 0.07 | J22: 0.0165 | K22: 0.076 | L22: =+I22*F22 -> 635.6511 | M22: =J22*(F22-L22) -> 139.3438 | N22: =K22*(F22-L22) -> 641.826
A23: GNV | B23: =B22 -> 44958 | C23: Petrobras | D23: 431505-2 | E23: 939887.75 | F23: 2442394.3 | G23: =F23-SUM(L23:N23) -> 2271426.7 | H23: =+IF(G23=0,0,G23/E23) -> 2.4167 | I23: 0.07 | J23: 0 | K23: 0 | L23: =+I23*F23 -> 170967.6 | M23: =J23*(F23-L23) -> 0 | N23: =K23*(F23-L23) -> 0
A24: GNV | B24: =B23 -> 44958 | C24: Petrobras | D24: 431506-2 | E24: 9730559.3 | F24: 25285852 | G24: =F24-SUM(L24:N24) -> 23515843 | H24: =+IF(G24=0,0,G24/E24) -> 2.4167 | I24: 0.07 | J24: 0 | K24: 0 | L24: =+I24*F24 -> 1770009.7 | M24: =J24*(F24-L24) -> 0 | N24: =K24*(F24-L24) -> 0
A25: GNV | B25: =B24 -> 44958 | C25: Petrobras | D25: 3474-28 | E25: 41385 | F25: 113653.56 | G25: =F25-SUM(L25:N25) -> 100015.13 | H25: =+IF(G25=0,0,G25/E25) -> 2.4167001 | I25: 0.12 | J25: 0 | K25: 0 | L25: =+I25*F25 -> 13638.427 | M25: =J25*(F25-L25) -> 0 | N25: =K25*(F25-L25) -> 0
A26: GNV | B26: =B25 -> 44958 | C26: Petrobras | D26: 5316-24 | E26: 1068231 | F26: 2933629.4 | G26: =F26-SUM(L26:N26) -> 2581593.9 | H26: =+IF(G26=0,0,G26/E26) -> 2.4167 | I26: 0.12 | J26: 0 | K26: 0 | L26: =+I26*F26 -> 352035.53 | M26: =J26*(F26-L26) -> 0 | N26: =K26*(F26-L26) -> 0
A27: PGU1 GNV | B27: =B26 -> 44958 | C27: Petrobras | D27: 431497-2 | E27: 222239 | F27: 818986.56 | G27: =F27-SUM(L27:N27) -> 761657.5 | H27: =+IF(G27=0,0,G27/E27) -> 3.4272 | I27: 0.07 | J27: 0 | K27: 0 | L27: =+I27*F27 -> 57329.059 | M27: =J27*(F27-L27) -> 0 | N27: =K27*(F27-L27) -> 0
A28: PGU1 GNV | B28: =B27 -> 44958 | C28: Petrobras | D28: 5317-24 | E28: 6794 | F28: 26459.55 | G28: =F28-SUM(L28:N28) -> 23284.404 | H28: =+IF(G28=0,0,G28/E28) -> 3.4272011 | I28: 0.12 | J28: 0 | K28: 0 | L28: =+I28*F28 -> 3175.146 | M28: =J28*(F28-L28) -> 0 | N28: =K28*(F28-L28) -> 0
A29: PGU2 GNV | B29: =B28 -> 44958 | C29: Petrobras | D29: 431498-2 | E29: 5901 | F29: 28157.92 | G29: =F29-SUM(L29:N29) -> 26186.866 | H29: =+IF(G29=0,0,G29/E29) -> 4.4376996 | I29: 0.07 | J29: 0 | K29: 0 | L29: =+I29*F29 -> 1971.0544 | M29: =J29*(F29-L29) -> 0 | N29: =K29*(F29-L29) -> 0
B30: =B29 -> 44958 | C30: Shell | D30: 1366-1 | E30: 29113490 | F30: 62732293 | G30: =F30-SUM(L30:N30) -> 52944487 | H30: =+IF(G30=0,0,G30/E30) -> 1.8185551 | I30: 0.07 | J30: 0.0165 | K30: 0.076 | L30: =+I30*F30 -> 4391260.5 | M30: =J30*(F30-L30) -> 962627.03 | N30: =K30*(F30-L30) -> 4433918.4
B31: =B30 -> 44958 | C31: New Fortress (Petrolina) | D31: 28-1 | E31: 644993 | F31: 3182653.5 | G31: =F31-SUM(L31:N31) -> 2368371.6 | H31: =+IF(G31=0,0,G31/E31) -> 3.6719338 | I31: 0.18 | J31: 0.0165 | K31: 0.076 | L31: =+I31*F31 -> 572877.62 | M31: =J31*(F31-L31) -> 43061.301 | N31: =K31*(F31-L31) -> 198342.96
B32: =B31 -> 44958 | C32: New Fortress (Garanhuns) | D32: 32-1 | E32: 65763 | F32: 315425.65 | G32: =F32-SUM(L32:N32) -> 234724 | H32: =+IF(G32=0,0,G32/E32) -> 3.569241 | I32: 0.18 | J32: 0.0165 | K32: 0.076 | L32: =+I32*F32 -> 56776.617 | M32: =J32*(F32-L32) -> 4267.709 | N32: =K32*(F32-L32) -> 19657.327
E35: =SUM(E18:E34) -> 44641552 | G35: =SUM(G18:G34) -> 91669214
B38: Observações Relevantes: Publicação da Lei Complementar 194/2022, no DOU de 23.06.2022, Edição Extra, prevendo, até 31.12.2022, redução a zero da alíquota de PIS/COFINS incidente sobre a receita ou o faturamento na venda de gás natural veicular classificado nos códigos 2711.11.00 ou 2711.21.00 da NCM. "Art. 9º-B Até 31 de dezembro de 2022, ficam reduzidas a 0 (zero) as alíquotas das contribuições de que tratam o caput e o § 1º do art. 9º desta Lei Complementar incidentes sobre a receita ou o faturamento na venda ou sobre a importação de gás natural veicular classificado nos códigos 2711.11.00 ou 2711.21.00 da NCM." Dessa forma, a Copergás informou a Petrobras todo o volume de GNV e GNC veicular comercializado durante o mês de fevereiro/23, o qual foi sensibilizado nas notas do supridor e, consequentemente, foram emitidas com alíquotas zero de PIS/Cofins.

Sheet Mar23
C2: RELATÓRIO MENSAL DE ACOMPANHAMENTO DO CUSTO DO GÁS
C3: 44986
C5: Petrobras | D5: =SUMIF($C$18:$G$36,$C$5:$C$7,$G$18:$G$36)/SUMIF($C$18:$G$36,$C$5:$C$7,$E$18:$E$36) -> 2.4188656
C6: Shell | D6: =SUMIF($C$18:$G$36,$C$5:$C$7,$G$18:$G$36)/SUMIF($C$18:$G$36,$C$5:$C$7,$E$18:$E$36) -> 43410.082
C7: NFE | D7: =SUM(G38:G39)/SUM(E38:E39) -> 3.6629206
M8: Poderação QDC | N8: Poderação QDR
C9: Custo Médio Ponderado real | D9: =+G42/E42 -> 2.0418108 | L9: =+C5 -> Petrobras | M9: =790000/1580000 -> 0.5 | N9: =+SUM(E18:E35)/E42 -> 0.3152981
L10: =+C6 -> Shell | M10: 0.47468354 | N10: =+SUM(E36:E36)/E42 -> 2.0275674e-08
C11: Custo Médio Ponderado tarifa | D11: 2.0702 | L11: =+C7 -> NFE | M11: 0.025316456 | N11: =+SUM(E38:E39)/E42 -> 0.017845188
L12: Total | M12: =SUM(M9:M11) -> 1 | N12: =SUM(N9:N11) -> 0.33314331
L16: CONFORME XML DA NOTA
B17: Mês | C17: Supridor | D17: Nota Fiscal | E17: Vol m³ | F17: Compra R$ c/tributos | G17: Compra R$ s/tributos | H17: Custo | I17: ICMS | J17: PIS | K17: COFINS | L17: ICMS | M17: PIS | N17: COFINS
B18: =C3 -> 44986 | C18: Petrobras | D18: 3483-28 | E18: 8050 | F18: 24360.68 | G18: =F18-SUM(L18:N18) -> 19454.439 | H18: =+IF(G18=0,0,G18/E18) -> 2.4167005 | I18: 0.12 | J18: 0.0165 | K18: 0.076 | L18: =+I18*F18 -> 2923.2816 | M18: =J18*(F18-L18) -> 353.71707 | N18: =K18*(F18-L18) -> 1629.2423
B19: =B18 -> 44986 | C19: Petrobras | D19: 431578-2 | E19: 1849870 | F19: 5297053.6 | G19: =F19-SUM(L19:N19) -> 4470580.8 | H19: =+IF(G19=0,0,G19/E19) -> 2.4167 | I19: 0.07 | J19: 0.0165 | K19: 0.076 | L19: =+I19*F19 -> 370793.75 | M19: =J19*(F19-L19) -> 81283.288 | N19: =K19*(F19-L19) -> 374395.75
B20: =B19 -> 44986 | C20: Petrobras | D20: 11474-6 | E20: 55901 | F20: 169165.98 | G20: =F20-SUM(L20:N20) -> 135095.95 | H20: =+IF(G20=0,0,G20/E20) -> 2.4167001 | I20: 0.12 | J20: 0.0165 | K20: 0.076 | L20: =+I20*F20 -> 20299.918 | M20: =J20*(F20-L20) -> 2456.29 | N20: =K20*(F20-L20) -> 11313.821
B21: =B20 -> 44986 | C21: Petrobras | D21: 5340-24 | E21: 304186 | F21: 920518.8 | G21: =F21-SUM(L21:N21) -> 735126.31 | H21: =+IF(G21=0,0,G21/E21) -> 2.4167 | I21: 0.12 | J21: 0.0165 | K21: 0.076 | L21: =+I21*F21 -> 110462.26 | M21: =J21*(F21-L21) -> 13365.933 | N21: =K21*(F21-L21) -> 61564.297
A22: PGU1 | B22: =B19 -> 44986 | C22: Petrobras | D22: 11475-6 | E22: 215 | F22: 922.68 | G22: =F22-SUM(L22:N22) -> 736.85225 | H22: =+IF(G22=0,0,G22/E22) -> 3.4272198 | I22: 0.12 | J22: 0.0165 | K22: 0.076 | L22: =+I22*F22 -> 110.7216 | M22: =J22*(F22-L22) -> 13.397314 | N22: =K22*(F22-L22) -> 61.708838
A23: PGU1 | B23: =B22 -> 44986 | C23: Petrobras | D23: 5341-24 | E23: 1098 | F23: 4712.08 | G23: =F23-SUM(L23:N23) -> 3763.0671 | H23: =+IF(G23=0,0,G23/E23) -> 3.4272014 | I23: 0.12 | J23: 0.0165 | K23: 0.076 | L23: =+I23*F23 -> 565.4496 | M23: =J23*(F23-L23) -> 68.419402 | N23: =K23*(F23-L23) -> 315.14391
A24: PGU1 | B24: =B23 -> 44986 | C24: Petrobras | D24: 3484-28 | E24: 63 | F24: 270.36 | G24: =F24-SUM(L24:N24) -> 215.9095 | H24: =+IF(G24=0,0,G24/E24) -> 3.4271349 | I24: 0.12 | J24: 0.0165 | K24: 0.076 | L24: =+I24*F24 -> 32.4432 | M24: =J24*(F24-L24) -> 3.9256272 | N24: =K24*(F24-L24) -> 18.081677
A25: PGU1 | B25: =B24 -> 44986 | C25: Petrobras | D25: 431579-2 | E25: 3427 | F25: 13916.3 | G25: =F25-SUM(L25:N25) -> 11745.009 | H25: =+IF(G25=0,0,G25/E25) -> 3.4271985 | I25: 0.07 | J25: 0.0165 | K25: 0.076 | L25: =+I25*F25 -> 974.141 | M25: =J25*(F25-L25) -> 213.54562 | N25: =K25*(F25-L25) -> 983.60408
A26: PGU2 | B26: =B23 -> 44986 | C26: Petrobras | G26: =F26-SUM(L26:N26) -> 0 | H26: =+IF(G26=0,0,G26/E26) -> 0 | J26: 0.0165 | K26: 0.076 | L26: =+I26*F26 -> 0 | M26: =J26*(F26-L26) -> 0 | N26: =K26*(F26-L26) -> 0
A27: GNV | B27: =B26 -> 44986 | C27: Petrobras | D27: 5342-24 | E27: 1438588 | F27: 3950722.3 | G27: =F27-SUM(L27:N27) -> 3476635.6 | H27: =+IF(G27=0,0,G27/E27) -> 2.4167 | I27: 0.12 | J27: 0 | K27: 0 | L27: =+I27*F27 -> 474086.68 | M27: =J27*(F27-L27) -> 0 | N27: =K27*(F27-L27) -> 0
A28: GNV | B28: =B27 -> 44986 | C28: Petrobras | D28: 431580-2 | E28: 11425119 | F28: 29689339 | G28: =F28-SUM(L28:N28) -> 27611085 | H28: =+IF(G28=0,0,G28/E28) -> 2.4167 | I28: 0.07 | J28: 0 | K28: 0 | L28: =+I28*F28 -> 2078253.7 | M28: =J28*(F28-L28) -> 0 | N28: =K28*(F28-L28) -> 0
A29: GNV | B29: =B28 -> 44986 | C29: Petrobras | D29: 3485-28 | E29: 97686 | F29: 268270.18 | G29: =F29-SUM(L29:N29) -> 236077.76 | H29: =+IF(G29=0,0,G29/E29) -> 2.4167 | I29: 0.12 | J29: 0 | K29: 0 | L29: =+I29*F29 -> 32192.422 | M29: =J29*(F29-L29) -> 0 | N29: =K29*(F29-L29) -> 0
A30: GNV | B30: =B29 -> 44986 | C30: Petrobras | D30: 11476-6 | E30: 337835 | F30: 927779.36 | G30: =F30-SUM(L30:N30) -> 816445.84 | H30: =+IF(G30=0,0,G30/E30) -> 2.4167 | I30: 0.12 | J30: 0 | K30: 0 | L30: =+I30*F30 -> 111333.52 | M30: =J30*(F30-L30) -> 0 | N30: =K30*(F30-L30) -> 0
A31: PGU1 GNV | B31: =B30 -> 44986 | C31: Petrobras | D31: 431581-2 | E31: 20685 | F31: 76227.56 | G31: =F31-SUM(L31:N31) -> 70891.631 | H31: =+IF(G31=0,0,G31/E31) -> 3.4271999 | I31: 0.07 | J31: 0 | K31: 0 | L31: =+I31*F31 -> 5335.9292 | M31: =J31*(F31-L31) -> 0 | N31: =K31*(F31-L31) -> 0
A32: PGU1 GNV | B32: =B31 -> 44986 | C32: Petrobras | D32: 5343-24 | E32: 4410 | F32: 17174.94 | G32: =F32-SUM(L32:N32) -> 15113.947 | H32: =+IF(G32=0,0,G32/E32) -> 3.4271989 | I32: 0.12 | J32: 0 | K32: 0 | L32: =+I32*F32 -> 2060.9928 | M32: =J32*(F32-L32) -> 0 | N32: =K32*(F32-L32) -> 0
A33: PGU1 GNV | B33: =B32 -> 44986 | C33: Petrobras | D33: 3486-28 | E33: 769 | F33: 2994.91 | G33: =F33-SUM(L33:N33) -> 2635.5208 | H33: =+IF(G33=0,0,G33/E33) -> 3.4272052 | I33: 0.12 | J33: 0 | K33: 0 | L33: =+I33*F33 -> 359.3892 | M33: =J33*(F33-L33) -> 0 | N33: =K33*(F33-L33) -> 0
A34: PGU1 GNV | B34: =B33 -> 44986 | C34: Petrobras | D34: 11477-6 | E34: 2659 | F34: 10355.59 | G34: =F34-SUM(L34:N34) -> 9112.9192 | H34: =+IF(G34=0,0,G34/E34) -> 3.4271979 | I34: 0.12 | J34: 0 | K34: 0 | L34: =+I34*F34 -> 1242.6708 | M34: =J34*(F34-L34) -> 0 | N34: =K34*(F34-L34) -> 0
A35: PGU2 GNV | B35: =B32 -> 44986 | C35: Petrobras | G35: =F35-SUM(L35:N35) -> 0 | H35: =+IF(G35=0,0,G35/E35) -> 0 | J35: 0 | K35: 0 | L35: =+I35*F35 -> 0 | M35: =J35*(F35-L35) -> 0 | N35: =K35*(F35-L35) -> 0
B36: =B35 -> 44986 | C36: Shell | D36: 1479-1 | E36: 1 | F36: 51435.27 | G36: =F36-SUM(L36:N36) -> 43410.082 | H36: =+IF(G36=0,0,G36/E36) -> 43410.082 | I36: 0.07 | J36: 0.0165 | K36: 0.076 | L36: =+I36*F36 -> 3600.4689 | M36: =J36*(F36-L36) -> 789.27422 | N36: =K36*(F36-L36) -> 3635.4449
B37: =B36 -> 44986 | C37: Shell | D37: 1848-1 | E37: 32889496 | F37: 70879495 | G37: =F37-SUM(L37:N37) -> 59820522 | H37: =+IF(G37=0,0,G37/E37) -> 1.8188336 | I37: 0.07 | J37: 0.0165 | K37: 0.076 | L37: =+I37*F37 -> 4961564.7 | M37: =J37*(F37-L37) -> 1087645.9 | N37: =K37*(F37-L37) -> 5009762.7
B38: =B36 -> 44986 | C38: New Fortress (Petrolina) | D38: 35-1 | E38: 802881 | F38: 3961736 | G38: =F38-SUM(L38:N38) -> 2948125.9 | H38: =+IF(G38=0,0,G38/E38) -> 3.6719338 | I38: 0.18 | J38: 0.0165 | K38: 0.076 | L38: =+I38*F38 -> 713112.48 | M38: =J38*(F38-L38) -> 53602.288 | N38: =K38*(F38-L38) -> 246895.39
B39: =B38 -> 44986 | C39: New Fortress (Garanhuns) | D39: 33-1 | E39: 77247 | F39: 370507.51 | G39: =F39-SUM(L39:N39) -> 275713.16 | H39: =+IF(G39=0,0,G39/E39) -> 3.5692411 | I39: 0.18 | J39: 0.0165 | K39: 0.076 | L39: =+I39*F39 -> 66691.352 | M39: =J39*(F39-L39) -> 5012.9666 | N39: =K39*(F39-L39) -> 23090.028
E42: =SUM(E18:E41) -> 49320186 | G42: =SUM(G18:G41) -> 1.0070249e+08
B45: Observações Relevantes: Publicação da Lei Complementar 194/2022, no DOU de 23.06.2022, Edição Extra, prevendo, até 31.12.2022, redução a zero da alíquota de PIS/COFINS incidente sobre a receita ou o faturamento na venda de gás natural veicular classificado nos códigos 2711.11.00 ou 2711.21.00 da NCM. "Art. 9º-B Até 31 de dezembro de 2022, ficam reduzidas a 0 (zero) as alíquotas das contribuições de que tratam o caput e o § 1º do art. 9º desta Lei Complementar incidentes sobre a receita ou o faturamento na venda ou sobre a importação de gás natural veicular classificado nos códigos 2711.11.00 ou 2711.21.00 da NCM." Dessa forma, a Copergás informou a Petrobras todo o volume de GNV e GNC veicular comercializado durante o mês de março/23, o qual foi sensibilizado nas notas do supridor e, consequentemente, foram emitidas com alíquotas zero de PIS/Cofins.

Sheet Abr23
C2: RELATÓRIO MENSAL DE ACOMPANHAMENTO DO CUSTO DO GÁS
C3: 45017
C5: Petrobras | D5: =SUMIF($C$18:$G$39,$C$5:$C$7,$G$18:$G$39)/SUMIF($C$18:$G$39,$C$5:$C$7,$E$18:$E$39) -> 2.4898734
C6: Shell | D6: =SUMIF($C$18:$G$39,$C$5:$C$7,$G$18:$G$39)/SUMIF($C$18:$G$39,$C$5:$C$7,$E$18:$E$39) -> 1.8182597
C7: NFE Fortress | D7: =SUM(G38:G39)/SUM(E38:E39) -> 3.6031494
M8: Poderação QDC | N8: Poderação QDR
C9: Custo Médio Ponderado real | D9: =+G42/E42 -> 2.0274108 | L9: =+C5 -> Petrobras | M9: =790000/1580000 -> 0.5 | N9: =+SUM(E18:E35)/E42 -> 0.26248225
L10: =+C6 -> Shell | M10: 0.47468354 | N10: =+SUM(E36:E36)/E42 -> 0.71910518
C11: Custo Médio Ponderado tarifa | D11: 2.0702 | L11: =+C7 -> NFE Fortress | M11: 0.025316456 | N11: =+SUM(E38:E39)/E42 -> 0.018412572
L12: Total | M12: =SUM(M9:M11) -> 1 | N12: =SUM(N9:N11) -> 1
L16: CONFORME XML DA NOTA
B17: Mês | C17: Supridor | D17: Nota Fiscal | E17: Vol m³ | F17: Compra R$ c/tributos | G17: Compra R$ s/tributos | H17: Custo | I17: ICMS | J17: PIS | K17: COFINS | L17: ICMS | M17: PIS | N17: COFINS
A18: GNV | B18: =C3 -> 45017 | C18: Petrobras | D18: 431599-2 | E18: 3759795 | F18: 9770211.4 | G18: =F18-SUM(L18:N18) -> 9086296.6 | H18: =+IF(G18=0,0,G18/E18) -> 2.4167 | I18: 0.07 | J18: 0 | K18: 0 | L18: =+I18*F18 -> 683914.8 | M18: =J18*(F18-L18) -> 0 | N18: =K18*(F18-L18) -> 0
A19: GNV | B19: =B18 -> 45017 | C19: Petrobras | D19: 5371-4 | E19: 3643953 | F19: 10007206 | G19: =F19-SUM(L19:N19) -> 8806341.2 | H19: =+IF(G19=0,0,G19/E19) -> 2.4167 | I19: 0.12 | J19: 0 | K19: 0 | L19: =+I19*F19 -> 1200864.7 | M19: =J19*(F19-L19) -> 0 | N19: =K19*(F19-L19) -> 0
A20: GNV | B20: =B19 -> 45017 | C20: Petrobras | D20: 11491-6 | E20: 2326966 | F20: 6390430.4 | G20: =F20-SUM(L20:N20) -> 5623578.7 | H20: =+IF(G20=0,0,G20/E20) -> 2.4167 | I20: 0.12 | J20: 0 | K20: 0 | L20: =+I20*F20 -> 766851.65 | M20: =J20*(F20-L20) -> 0 | N20: =K20*(F20-L20) -> 0
A21: GNV | B21: =B20 -> 45017 | C21: Petrobras | D21: 3701-12 | E21: 1656889 | F21: 4550231.4 | G21: =F21-SUM(L21:N21) -> 4004203.6 | H21: =+IF(G21=0,0,G21/E21) -> 2.4167 | I21: 0.12 | J21: 0 | K21: 0 | L21: =+I21*F21 -> 546027.77 | M21: =J21*(F21-L21) -> 0 | N21: =K21*(F21-L21) -> 0
A22: GNV | B22: =B21 -> 45017 | C22: Petrobras | D22: 5351-24 | E22: 221902 | F22: 609398.36 | G22: =F22-SUM(L22:N22) -> 536270.56 | H22: =+IF(G22=0,0,G22/E22) -> 2.4167 | I22: 0.12 | J22: 0 | K22: 0 | L22: =+I22*F22 -> 73127.803 | M22: =J22*(F22-L22) -> 0 | N22: =K22*(F22-L22) -> 0
A23: PGU1 GNV | B23: =B22 -> 45017 | C23: Petrobras | D23: 3702-12 | E23: 107153 | F23: 417312.23 | G23: =F23-SUM(L23:N23) -> 367234.76 | H23: =+IF(G23=0,0,G23/E23) -> 3.4272 | I23: 0.12 | J23: 0 | K23: 0 | L23: =+I23*F23 -> 50077.468 | M23: =J23*(F23-L23) -> 0 | N23: =K23*(F23-L23) -> 0
A24: PGU1 GNV | B24: =B23 -> 45017 | C24: Petrobras | D24: 431600-2 | E24: 73390 | F24: 270453.99 | G24: =F24-SUM(L24:N24) -> 251522.21 | H24: =+IF(G24=0,0,G24/E24) -> 3.4272 | I24: 0.07 | J24: 0 | K24: 0 | L24: =+I24*F24 -> 18931.779 | M24: =J24*(F24-L24) -> 0 | N24: =K24*(F24-L24) -> 0
A25: PGU1 GNV | B25: =B24 -> 45017 | C25: Petrobras | D25: 11492-6 | E25: 52254 | F25: 203505.58 | G25: =F25-SUM(L25:N25) -> 179084.91 | H25: =+IF(G25=0,0,G25/E25) -> 3.4272 | I25: 0.12 | J25: 0 | K25: 0 | L25: =+I25*F25 -> 24420.67 | M25: =J25*(F25-L25) -> 0 | N25: =K25*(F25-L25) -> 0
A26: PGU1 GNV | B26: =B25 -> 45017 | C26: Petrobras | D26: 5352-24 | E26: 1171 | F26: 4560.51 | G26: =F26-SUM(L26:N26) -> 4013.2488 | H26: =+IF(G26=0,0,G26/E26) -> 3.427198 | I26: 0.12 | J26: 0 | K26: 0 | L26: =+I26*F26 -> 547.2612 | M26: =J26*(F26-L26) -> 0 | N26: =K26*(F26-L26) -> 0
A27: PGU1 GNV | B27: =B26 -> 45017 | C27: Petrobras | D27: 5372-4 | E27: 846 | F27: 3294.78 | G27: =F27-SUM(L27:N27) -> 2899.4064 | H27: =+IF(G27=0,0,G27/E27) -> 3.4271943 | I27: 0.12 | J27: 0 | K27: 0 | L27: =+I27*F27 -> 395.3736 | M27: =J27*(F27-L27) -> 0 | N27: =K27*(F27-L27) -> 0
A28: PGU2 GNV | B28: =B27 -> 45017 | C28: Petrobras | D28: 3703-12 | E28: 319278 | F28: 1610068.2 | G28: =F28-SUM(L28:N28) -> 1416860 | H28: =+IF(G28=0,0,G28/E28) -> 4.4377 | I28: 0.12 | J28: 0 | K28: 0 | L28: =+I28*F28 -> 193208.18 | M28: =J28*(F28-L28) -> 0 | N28: =K28*(F28-L28) -> 0
A29: PGU2 GNV | B29: =B28 -> 45017 | C29: Petrobras | D29: 5373-4 | E29: 3856 | F29: 19445.19 | G29: =F29-SUM(L29:N29) -> 17111.767 | H29: =+IF(G29=0,0,G29/E29) -> 4.437699 | I29: 0.12 | J29: 0 | K29: 0 | L29: =+I29*F29 -> 2333.4228 | M29: =J29*(F29-L29) -> 0 | N29: =K29*(F29-L29) -> 0
B30: =B29 -> 45017 | C30: Petrobras | G30: =F30-SUM(L30:N30) -> 0 | H30: =+IF(G30=0,0,G30/E30) -> 0 | J30: 0.0165 | K30: 0.076 | L30: =+I30*F30 -> 0 | M30: =J30*(F30-L30) -> 0 | N30: =K30*(F30-L30) -> 0
B31: =B30 -> 45017 | C31: Petrobras | G31: =F31-SUM(L31:N31) -> 0 | H31: =+IF(G31=0,0,G31/E31) -> 0 | J31: 0.0165 | K31: 0.076 | L31: =+I31*F31 -> 0 | M31: =J31*(F31-L31) -> 0 | N31: =K31*(F31-L31) -> 0
B32: =B31 -> 45017 | C32: Petrobras | G32: =F32-SUM(L32:N32) -> 0 | H32: =+IF(G32=0,0,G32/E32) -> 0 | J32: 0.0165 | K32: 0.076 | L32: =+I32*F32 -> 0 | M32: =J32*(F32-L32) -> 0 | N32: =K32*(F32-L32) -> 0
B33: =B32 -> 45017 | C33: Petrobras | G33: =F33-SUM(L33:N33) -> 0 | H33: =+IF(G33=0,0,G33/E33) -> 0 | J33: 0.0165 | K33: 0.076 | L33: =+I33*F33 -> 0 | M33: =J33*(F33-L33) -> 0 | N33: =K33*(F33-L33) -> 0
B34: =B33 -> 45017 | C34: Petrobras | G34: =F34-SUM(L34:N34) -> 0 | H34: =+IF(G34=0,0,G34/E34) -> 0 | J34: 0.0165 | K34: 0.076 | L34: =+I34*F34 -> 0 | M34: =J34*(F34-L34) -> 0 | N34: =K34*(F34-L34) -> 0
B35: =B34 -> 45017 | C35: Petrobras | G35: =F35-SUM(L35:N35) -> 0 | H35: =+IF(G35=0,0,G35/E35) -> 0 | J35: 0.0165 | K35: 0.076 | L35: =+I35*F35 -> 0 | M35: =J35*(F35-L35) -> 0 | N35: =K35*(F35-L35) -> 0
B36: =B35 -> 45017 | C36: Shell | D36: 2368-1 | E36: 33334363 | F36: 71815552 | G36: =F36-SUM(L36:N36) -> 60610530 | H36: =+IF(G36=0,0,G36/E36) -> 1.8182597 | I36: 0.07 | J36: 0.0165 | K36: 0.076 | L36: =+I36*F36 -> 5027088.6 | M36: =J36*(F36-L36) -> 1102009.6 | N36: =K36*(F36-L36) -> 5075923.2
B37: =B36 -> 45017 | C37: Shell | G37: =F37-SUM(L37:N37) -> 0 | H37: =+IF(G37=0,0,G37/E37) -> 0 | J37: 0.0165 | K37: 0.076 | L37: =+I37*F37 -> 0 | M37: =J37*(F37-L37) -> 0 | N37: =K37*(F37-L37) -> 0
B38: =B37 -> 45017 | C38: New Fortress (Petrolina) | D38: 37-1 | E38: =74174+178586+531362 -> 784122 | F38: 3806815.7 | G38: =F38-SUM(L38:N38) -> 2832841.9 | H38: =+IF(G38=0,0,G38/E38) -> 3.6127566 | I38: 0.18 | J38: 0.0165 | K38: 0.076 | L38: =+I38*F38 -> 685226.83 | M38: =J38*(F38-L38) -> 51506.216 | N38: =K38*(F38-L38) -> 237240.75
B39: =B38 -> 45017 | C39: New Fortress (Garanhuns) | D39: 34-1 | E39: =8869+20159+40371 -> 69399 | F39: 325904.45 | G39: =F39-SUM(L39:N39) -> 242521.8 | H39: =+IF(G39=0,0,G39/E39) -> 3.4946007 | I39: 0.18 | J39: 0.0165 | K39: 0.076 | L39: =+I39*F39 -> 58662.801 | M39: =J39*(F39-L39) -> 4409.4872 | N39: =K39*(F39-L39) -> 20310.365
E42: =SUM(E18:E41) -> 46355337 | G42: =SUM(G18:G41) -> 93981311
B45: Observações Relevantes: Publicação da Lei Complementar 194/2022, no DOU de 23.06.2022, Edição Extra, prevendo, até 31.12.2022, redução a zero da alíquota de PIS/COFINS incidente sobre a receita ou o faturamento na venda de gás natural veicular classificado nos códigos 2711.11.00 ou 2711.21.00 da NCM. "Art. 9º-B Até 31 de dezembro de 2022, ficam reduzidas a 0 (zero) as alíquotas das contribuições de que tratam o caput e o § 1º do art. 9º desta Lei Complementar incidentes sobre a receita ou o faturamento na venda ou sobre a importação de gás natural veicular classificado nos códigos 2711.11.00 ou 2711.21.00 da NCM." Dessa forma, a Copergás informou a Petrobras todo o volume de GNV e GNC veicular comercializado durante o mês de abril/23, o qual foi sensibilizado nas notas do supridor e, consequentemente, foram emitidas com alíquotas zero de PIS/Cofins. NewFortress - GARANHUNS: Desconto de 5% do Preço do Gás, sobre o volume de 29.028 m³, pelo não cumprimento da estocagem mínima prevista em contrato (cláusula 6.2.4.). NewFortress - PETROLINA: Desconto de 5% do Preço do Gás, sobre o volume de 252.760 m³, pelo não cumprimento da estocagem mínima prevista em contrato (cláusula 6.2.4.).

Sheet Mai23
C2: RELATÓRIO MENSAL DE ACOMPANHAMENTO DO CUSTO DO GÁS
C3: 45047
C5: Petrobras | D5: =SUMIF($C$19:$G$41,$C$5:$C$8,$G$19:$G$41)/SUMIF($C$19:$G$41,$C$5:$C$8,$E$19:$E$41) -> 2.2213309
C6: Shell | D6: =SUMIF($C$19:$G$41,$C$5:$C$8,$G$19:$G$41)/SUMIF($C$19:$G$41,$C$5:$C$8,$E$19:$E$41) -> 1.4048723
C7: NFE | D7: =SUM(G39:G40)/SUM(E39:E40) -> 3.3635161
C8: Mastergás | D8: =H41 -> 2.904 | M8: Poderação QDC | N8: Poderação QDR
C9: Custo Médio Ponderado real | D9: =+G43/E43 -> 1.7097037 | L9: =+C5 -> Petrobras | M9: =790000/1580000 -> 0.5 | N9: =+SUM(E19:E36)/E43 -> 0.32480384
L10: =+C6 -> Shell | M10: 0.47468354 | N10: =+SUM(E37:E38)/E43 -> 0.66217407
L11: =+C7 -> NFE | M11: 0.025316456 | N11: =+SUM(E39:E40)/E43 -> 0.01302209
L12: Mastergás | M12: 0 | N12: 0
L13: Total | M13: =SUM(M9:M12) -> 1 | N13: =SUM(N9:N12) -> 1
L17: CONFORME XML DA NOTA
B18: Mês | C18: Supridor | D18: Nota Fiscal | E18: Vol m³ | F18: Compra R$ c/tributos | G18: Compra R$ s/tributos | H18: Custo | I18: ICMS | J18: PIS | K18: COFINS | L18: ICMS | M18: PIS | N18: COFINS
B19: =C3 -> 45047 | C19: Petrobras | D19: 5426-4 | E19: 1000789 | F19: 2783687.2 | G19: =F19-SUM(L19:N19) -> 2223052.6 | H19: =+IF(G19=0,0,G19/E19) -> 2.2213 | I19: 0.12 | J19: 0.0165 | K19: 0.076 | L19: =+I19*F19 -> 334042.47 | M19: =J19*(F19-L19) -> 40419.138 | N19: =K19*(F19-L19) -> 186173
B20: =B19 -> 45047 | C20: Petrobras | D20: 3723-12 | E20: 666640 | F20: 1854254.2 | G20: =F20-SUM(L20:N20) -> 1480807.4 | H20: =+IF(G20=0,0,G20/E20) -> 2.2213 | I20: 0.12 | J20: 0.0165 | K20: 0.076 | L20: =+I20*F20 -> 222510.51 | M20: =J20*(F20-L20) -> 26923.771 | N20: =K20*(F20-L20) -> 124012.52
B21: =B20 -> 45047 | C21: Petrobras | D21: 11566-6 | E21: 523720 | F21: 1456723.3 | G21: =F21-SUM(L21:N21) -> 1163339.2 | H21: =+IF(G21=0,0,G21/E21) -> 2.2213 | I21: 0.12 | J21: 0.0165 | K21: 0.076 | L21: =+I21*F21 -> 174806.8 | M21: =J21*(F21-L21) -> 21151.623 | N21: =K21*(F21-L21) -> 97425.656
B22: =B21 -> 45047 | C22: Petrobras | D22: 5401-24 | E22: 145950 | F22: 405958.85 | G22: =F22-SUM(L22:N22) -> 324198.74 | H22: =+IF(G22=0,0,G22/E22) -> 2.2213 | I22: 0.12 | J22: 0.0165 | K22: 0.076 | L22: =+I22*F22 -> 48715.062 | M22: =J22*(F22-L22) -> 5894.5225 | N22: =K22*(F22-L22) -> 27150.528
B23: =B22 -> 45047 | C23: Petrobras | D23: 431692-2 | E23: 118876 | F23: 312875.69 | G23: =F23-SUM(L23:N23) -> 264059.26 | H23: =+IF(G23=0,0,G23/E23) -> 2.2213 | I23: 0.07 | J23: 0.0165 | K23: 0.076 | L23: =+I23*F23 -> 21901.298 | M23: =J23*(F23-L23) -> 4801.0775 | N23: =K23*(F23-L23) -> 22114.054
A24: GNV | B24: =B23 -> 45047 | C24: Petrobras | D24: 5427-4 | E24: 5648794 | F24: 14258711 | G24: =F24-SUM(L24:N24) -> 12547666 | H24: =+IF(G24=0,0,G24/E24) -> 2.2213 | I24: 0.12 | J24: 0 | K24: 0 | L24: =+I24*F24 -> 1711045.4 | M24: =J24*(F24-L24) -> 0 | N24: =K24*(F24-L24) -> 0
A25: GNV | B25: =B24 -> 45047 | C25: Petrobras | D25: 3722-12 | E25: 3504490 | F25: 8846049.6 | G25: =F25-SUM(L25:N25) -> 7784523.6 | H25: =+IF(G25=0,0,G25/E25) -> 2.2213 | I25: 0.12 | J25: 0 | K25: 0 | L25: =+I25*F25 -> 1061526 | M25: =J25*(F25-L25) -> 0 | N25: =K25*(F25-L25) -> 0
A26: GNV | B26: =B25 -> 45047 | C26: Petrobras | D26: 11568-6 | E26: 2496975 | F26: 6302875.7 | G26: =F26-SUM(L26:N26) -> 5546530.6 | H26: =+IF(G26=0,0,G26/E26) -> 2.2213 | I26: 0.12 | J26: 0 | K26: 0 | L26: =+I26*F26 -> 756345.08 | M26: =J26*(F26-L26) -> 0 | N26: =K26*(F26-L26) -> 0
A27: GNV | B27: =B26 -> 45047 | C27: Petrobras | D27: 5403-24 | E27: 830093 | F27: 2095324.5 | G27: =F27-SUM(L27:N27) -> 1843885.6 | H27: =+IF(G27=0,0,G27/E27) -> 2.2213 | I27: 0.12 | J27: 0 | K27: 0 | L27: =+I27*F27 -> 251438.94 | M27: =J27*(F27-L27) -> 0 | N27: =K27*(F27-L27) -> 0
A28: GNV | B28: =B27 -> 45047 | C28: Petrobras | D28: 431693-2 | E28: 809381 | F28: 1933202.2 | G28: =F28-SUM(L28:N28) -> 1797878 | H28: =+IF(G28=0,0,G28/E28) -> 2.2213 | I28: 0.07 | J28: 0 | K28: 0 | L28: =+I28*F28 -> 135324.15 | M28: =J28*(F28-L28) -> 0 | N28: =K28*(F28-L28) -> 0
A29: PGU1 GNV | B29: =B28 -> 45047 | C29: Petrobras | D29: 5404-24 | E29: 217 | F29: 772.76 | G29: =F29-SUM(L29:N29) -> 680.0288 | H29: =+IF(G29=0,0,G29/E29) -> 3.1337733 | I29: 0.12 | J29: 0 | K29: 0 | L29: =+I29*F29 -> 92.7312 | M29: =J29*(F29-L29) -> 0 | N29: =K29*(F29-L29) -> 0
A30: PGU1 GNV | B30: =B29 -> 45047 | C30: Petrobras | D30: 11569-6 | E30: 243 | F30: 865.35 | G30: =F30-SUM(L30:N30) -> 761.508 | H30: =+IF(G30=0,0,G30/E30) -> 3.1337778 | I30: 0.12 | J30: 0 | K30: 0 | L30: =+I30*F30 -> 103.842 | M30: =J30*(F30-L30) -> 0 | N30: =K30*(F30-L30) -> 0
A31: PGU1 | B31: =B30 -> 45047 | C31: Petrobras | D31: 11567-6 | E31: 60 | F31: 235.45 | G31: =F31-SUM(L31:N31) -> 188.03037 | H31: =+IF(G31=0,0,G31/E31) -> 3.1338395 | I31: 0.12 | J31: 0.0165 | K31: 0.076 | L31: =+I31*F31 -> 28.254 | M31: =J31*(F31-L31) -> 3.418734 | N31: =K31*(F31-L31) -> 15.746896
A32: PGU1 | B32: =B31 -> 45047 | C32: Petrobras | D32: 5402-24 | E32: 14 | F32: 54.93 | G32: =F32-SUM(L32:N32) -> 43.867098 | H32: =+IF(G32=0,0,G32/E32) -> 3.1333641 | I32: 0.12 | J32: 0.0165 | K32: 0.076 | L32: =+I32*F32 -> 6.5916 | M32: =J32*(F32-L32) -> 0.7975836 | N32: =K32*(F32-L32) -> 3.6737184
B33: =B32 -> 45047 | G33: =F33-SUM(L33:N33) -> 0 | H33: =+IF(G33=0,0,G33/E33) -> 0 | L33: =+I33*F33 -> 0 | M33: =J33*(F33-L33) -> 0 | N33: =K33*(F33-L33) -> 0
B34: =B33 -> 45047 | G34: =F34-SUM(L34:N34) -> 0 | H34: =+IF(G34=0,0,G34/E34) -> 0 | L34: =+I34*F34 -> 0 | M34: =J34*(F34-L34) -> 0 | N34: =K34*(F34-L34) -> 0
B35: =B34 -> 45047 | G35: =F35-SUM(L35:N35) -> 0 | H35: =+IF(G35=0,0,G35/E35) -> 0 | L35: =+I35*F35 -> 0 | M35: =J35*(F35-L35) -> 0 | N35: =K35*(F35-L35) -> 0
B36: =B35 -> 45047 | G36: =F36-SUM(L36:N36) -> 0 | H36: =+IF(G36=0,0,G36/E36) -> 0 | L36: =+I36*F36 -> 0 | M36: =J36*(F36-L36) -> 0 | N36: =K36*(F36-L36) -> 0
B37: =B36 -> 45047 | C37: Shell | D37: 2821-1 | E37: 32101693 | F37: 53436158 | G37: =F37-SUM(L37:N37) -> 45098781 | H37: =+IF(G37=0,0,G37/E37) -> 1.4048723 | I37: 0.07 | J37: 0.0165 | K37: 0.076 | L37: =+I37*F37 -> 3740531 | M37: =J37*(F37-L37) -> 819977.84 | N37: =K37*(F37-L37) -> 3776867.6
B38: =B37 -> 45047 | C38: Shell | G38: =F38-SUM(L38:N38) -> 0 | H38: =+IF(G38=0,0,G38/E38) -> 0 | J38: 0.0165 | K38: 0.076 | L38: =+I38*F38 -> 0 | M38: =J38*(F38-L38) -> 0 | N38: =K38*(F38-L38) -> 0
B39: =B38 -> 45047 | C39: New Fortress (Petrolina) | D39: 39-1 | E39: =265571+292562 -> 558133 | F39: 2532398 | G39: =F39-SUM(L39:N39) -> 1884483.9 | H39: =+IF(G39=0,0,G39/E39) -> 3.3764066 | I39: 0.18 | J39: 0.0165 | K39: 0.076 | L39: =+I39*F39 -> 455831.63 | M39: =J39*(F39-L39) -> 34263.344 | N39: =K39*(F39-L39) -> 157819.04
B40: =B39 -> 45047 | C40: New Fortress (Garanhuns) | D40: 39-1 | E40: =29930+43238 -> 73168 | F40: 321046.98 | G40: =F40-SUM(L40:N40) -> 238907.11 | H40: =+IF(G40=0,0,G40/E40) -> 3.2651857 | I40: 0.18 | J40: 0.0165 | K40: 0.076 | L40: =+I40*F40 -> 57788.456 | M40: =J40*(F40-L40) -> 4343.7656 | N40: =K40*(F40-L40) -> 20007.648
B41: =B40 -> 45047 | C41: Mastergás | D41: 59 Notas | E41: 0 | F41: =12800*59 -> 755200 | G41: =F41-SUM(L41:N41) -> 685344 | H41: =G41/(59*4000) -> 2.904 | I41: 0 | J41: 0.0165 | K41: 0.076 | L41: =+I41*F41 -> 0 | M41: =J41*(F41-L41) -> 12460.8 | N41: =K41*(F41-L41) -> 57395.2
E43: =SUM(E19:E42) -> 48479236 | G43: =SUM(G19:G42) -> 82885131
B46: Observações Relevantes: As tarifas de fornecimento para o segmento de uso Veicular (GNV/GNC) incidem impostos de 12% de ICMS conforme Lei 14.956/2013 e 0% de PIS/COFINS, conforme Medida Provisória Nº 1.163, de 28 de fevereiro de 2023. Dessa forma, a Copergás informou a Petrobras todo o volume de GNV e GNC veicular comercializado durante o mês de maio/23, o qual foi sensibilizado nas notas do supridor e, consequentemente, foram emitidas com alíquotas zero de PIS/Cofins. NewFortress - GARANHUNS: Desconto de 5% do Preço do Gás, sobre o volume de 43.238 m³, pelo não cumprimento da estocagem mínima prevista em contrato (cláusula 6.2.4.). NewFortress - PETROLINA: Desconto de 5% do Preço do Gás, sobre o volume de 292.562 m³, pelo não cumprimento da estocagem mínima prevista em contrato (cláusula 6.2.4.). 59 Emissões de Conhecimento de Transporte de GNL pela Mastergás para abastecimento de parte da Rede Local.

Sheet Jun23
C2: RELATÓRIO MENSAL DE ACOMPANHAMENTO DO CUSTO DO GÁS
C3: 45078
C5: Petrobras | D5: =SUMIF($C$19:$G$41,$C$5:$C$8,$G$19:$G$41)/SUMIF($C$19:$G$41,$C$5:$C$8,$E$19:$E$41) -> 2.222788
C6: Shell | D6: =SUMIF($C$19:$G$41,$C$5:$C$8,$G$19:$G$41)/SUMIF($C$19:$G$41,$C$5:$C$8,$E$19:$E$41) -> 1.4048555
C7: NFE | D7: =SUM(G38:G39)/SUM(E38:E39) -> 3.4503069
C8: Mastergás | D8: =H41 -> 3.0291947 | M8: Poderação QDC | N8: Poderação QDR
C9: Custo Médio Ponderado real | D9: =+G43/E43 -> 1.6933325 | L9: =+C5 -> Petrobras | M9: =790000/1580000 -> 0.5 | N9: =+SUM(E19:E36)/E43 -> 0.32943636
L10: =+C6 -> Shell | M10: 0.47468354 | N10: =+SUM(E37:E37)/E43 -> 0.66396039
L11: =+C7 -> NFE | M11: 0.025316456 | N11: =+SUM(E38:E39)/E43 -> 0.0066032553
L12: REDE LOCAL | M12: 0 | N12: 0
L13: Total | M13: =SUM(M9:M12) -> 1 | N13: =SUM(N9:N12) -> 1
L17: CONFORME XML DA NOTA
B18: Mês | C18: Supridor | D18: Nota Fiscal | E18: Vol m³ | F18: Compra R$ c/tributos | G18: Compra R$ s/tributos | H18: Custo | I18: ICMS | J18: PIS | K18: COFINS | L18: ICMS | M18: PIS | N18: COFINS
B19: =C3 -> 45078 | C19: Petrobras | D19: 5456-4 | E19: 1822158 | F19: 5068319 | G19: =F19-SUM(L19:N19) -> 4047559.6 | H19: =+IF(G19=0,0,G19/E19) -> 2.2213 | I19: 0.12 | J19: 0.0165 | K19: 0.076 | L19: =+I19*F19 -> 608198.28 | M19: =J19*(F19-L19) -> 73591.992 | N19: =K19*(F19-L19) -> 338969.18
B20: =B19 -> 45078 | C20: Petrobras | D20: 3748-12 | E20: 809985 | F20: 2252967.3 | G20: =F20-SUM(L20:N20) -> 1799219.7 | H20: =+IF(G20=0,0,G20/E20) -> 2.2213 | I20: 0.12 | J20: 0.0165 | K20: 0.076 | L20: =+I20*F20 -> 270356.07 | M20: =J20*(F20-L20) -> 32713.085 | N20: =K20*(F20-L20) -> 150678.45
B21: =B20 -> 45078 | C21: Petrobras | D21: 431733-2 | E21: 287821 | F21: 757530.48 | G21: =F21-SUM(L21:N21) -> 639336.79 | H21: =+IF(G21=0,0,G21/E21) -> 2.2213 | I21: 0.07 | J21: 0.0165 | K21: 0.076 | L21: =+I21*F21 -> 53027.134 | M21: =J21*(F21-L21) -> 11624.305 | N21: =K21*(F21-L21) -> 53542.254
B22: =B21 -> 45078 | C22: Petrobras | D22: 11604-6 | E22: 212021 | F22: 589734.85 | G22: =F22-SUM(L22:N22) -> 470962.25 | H22: =+IF(G22=0,0,G22/E22) -> 2.2213 | I22: 0.12 | J22: 0.0165 | K22: 0.076 | L22: =+I22*F22 -> 70768.182 | M22: =J22*(F22-L22) -> 8562.95 | N22: =K22*(F22-L22) -> 39441.467
A23: PGU1 | B23: =B22 -> 45078 | C23: Petrobras | D23: 3749-12 | E23: 2453 | F23: 9625.86 | G23: =F23-SUM(L23:N23) -> 7687.2118 | H23: =+IF(G23=0,0,G23/E23) -> 3.1338002 | I23: 0.12 | J23: 0.0165 | K23: 0.076 | L23: =+I23*F23 -> 1155.1032 | M23: =J23*(F23-L23) -> 139.76749 | N23: =K23*(F23-L23) -> 643.77752
A24: PGU1 | B24: =B23 -> 45078 | C24: Petrobras | D24: 5457-4 | E24: 559 | F24: 2193.58 | G24: =F24-SUM(L24:N24) -> 1751.793 | H24: =+IF(G24=0,0,G24/E24) -> 3.1337978 | I24: 0.12 | J24: 0.0165 | K24: 0.076 | L24: =+I24*F24 -> 263.2296 | M24: =J24*(F24-L24) -> 31.850782 | N24: =K24*(F24-L24) -> 146.70663
A25: PGU1 | B25: =B24 -> 45078 | C25: Petrobras | D25: 11605-6 | E25: 187 | F25: 733.81 | G25: =F25-SUM(L25:N25) -> 586.02067 | H25: =+IF(G25=0,0,G25/E25) -> 3.1338004 | I25: 0.12 | J25: 0.0165 | K25: 0.076 | L25: =+I25*F25 -> 88.0572 | M25: =J25*(F25-L25) -> 10.654921 | N25: =K25*(F25-L25) -> 49.077213
A26: PGU1 GNV | B26: =B25 -> 45078 | C26: Petrobras | D26: 3747-12 | E26: 17208 | F26: 61280.03 | G26: =F26-SUM(L26:N26) -> 53926.426 | H26: =+IF(G26=0,0,G26/E26) -> 3.1337998 | I26: 0.12 | J26: 0 | K26: 0 | L26: =+I26*F26 -> 7353.6036 | M26: =J26*(F26-L26) -> 0 | N26: =K26*(F26-L26) -> 0
A27: PGU1 GNV | B27: =B26 -> 45078 | C27: Petrobras | D27: 5459-4 | E27: 3733 | F27: 13293.73 | G27: =F27-SUM(L27:N27) -> 11698.482 | H27: =+IF(G27=0,0,G27/E27) -> 3.1338019 | I27: 0.12 | J27: 0 | K27: 0 | L27: =+I27*F27 -> 1595.2476 | M27: =J27*(F27-L27) -> 0 | N27: =K27*(F27-L27) -> 0
A28: PGU1 GNV | B28: =B27 -> 45078 | C28: Petrobras | D28: 11607-6 | E28: 1000 | F28: 3561.14 | G28: =F28-SUM(L28:N28) -> 3133.8032 | H28: =+IF(G28=0,0,G28/E28) -> 3.1338032 | I28: 0.12 | J28: 0 | K28: 0 | L28: =+I28*F28 -> 427.3368 | M28: =J28*(F28-L28) -> 0 | N28: =K28*(F28-L28) -> 0
A29: GNV | B29: =B28 -> 45078 | C29: Petrobras | D29: 3746-12 | E29: 5224749 | F29: 13188335 | G29: =F29-SUM(L29:N29) -> 11605735 | H29: =+IF(G29=0,0,G29/E29) -> 2.2213 | I29: 0.12 | J29: 0 | K29: 0 | L29: =+I29*F29 -> 1582600.2 | M29: =J29*(F29-L29) -> 0 | N29: =K29*(F29-L29) -> 0
A30: GNV | B30: =B29 -> 45078 | C30: Petrobras | D30: 5458-4 | E30: 4212119 | F30: 10632250 | G30: =F30-SUM(L30:N30) -> 9356379.9 | H30: =+IF(G30=0,0,G30/E30) -> 2.2213 | I30: 0.12 | J30: 0 | K30: 0 | L30: =+I30*F30 -> 1275870 | M30: =J30*(F30-L30) -> 0 | N30: =K30*(F30-L30) -> 0
A31: GNV | B31: =B30 -> 45078 | C31: Petrobras | D31: 431734-2 | E31: 1631219 | F31: 3896157.8 | G31: =F31-SUM(L31:N31) -> 3623426.8 | H31: =+IF(G31=0,0,G31/E31) -> 2.2213 | I31: 0.07 | J31: 0 | K31: 0 | L31: =+I31*F31 -> 272731.05 | M31: =J31*(F31-L31) -> 0 | N31: =K31*(F31-L31) -> 0
A32: GNV | B32: =B31 -> 45078 | C32: Petrobras | D32: 11606-6 | E32: 1191943 | F32: 3008707.9 | G32: =F32-SUM(L32:N32) -> 2647663 | H32: =+IF(G32=0,0,G32/E32) -> 2.2213 | I32: 0.12 | J32: 0 | K32: 0 | L32: =+I32*F32 -> 361044.95 | M32: =J32*(F32-L32) -> 0 | N32: =K32*(F32-L32) -> 0
B33: =B32 -> 45078 | C33: Petrobras | G33: =F33-SUM(L33:N33) -> 0 | H33: =+IF(G33=0,0,G33/E33) -> 0 | I33: 0.12 | J33: 0.0165 | K33: 0.076 | L33: =+I33*F33 -> 0 | M33: =J33*(F33-L33) -> 0 | N33: =K33*(F33-L33) -> 0
B34: =B33 -> 45078 | C34: Petrobras | G34: =F34-SUM(L34:N34) -> 0 | H34: =+IF(G34=0,0,G34/E34) -> 0 | I34: 0.12 | J34: 0.0165 | K34: 0.076 | L34: =+I34*F34 -> 0 | M34: =J34*(F34-L34) -> 0 | N34: =K34*(F34-L34) -> 0
B35: =B34 -> 45078 | C35: Petrobras | G35: =F35-SUM(L35:N35) -> 0 | H35: =+IF(G35=0,0,G35/E35) -> 0 | I35: 0.12 | J35: 0.0165 | K35: 0.076 | L35: =+I35*F35 -> 0 | M35: =J35*(F35-L35) -> 0 | N35: =K35*(F35-L35) -> 0
B36: =B35 -> 45078 | C36: Petrobras | G36: =F36-SUM(L36:N36) -> 0 | H36: =+IF(G36=0,0,G36/E36) -> 0 | I36: 0.12 | J36: 0.0165 | K36: 0.076 | L36: =+I36*F36 -> 0 | M36: =J36*(F36-L36) -> 0 | N36: =K36*(F36-L36) -> 0
B37: =B36 -> 45078 | C37: Shell | D37: 3200 | E37: 31072406 | F37: 51722195 | G37: =F37-SUM(L37:N37) -> 43652239 | H37: =+IF(G37=0,0,G37/E37) -> 1.4048555 | I37: 0.07 | J37: 0.0165 | K37: 0.076 | L37: =+I37*F37 -> 3620553.6 | M37: =J37*(F37-L37) -> 793677.08 | N37: =K37*(F37-L37) -> 3655724.7
B38: =B37 -> 45078 | C38: New Fortress (Petrolina) | D38: 42 | E38: 257910 | F38: 1201705.9 | G38: =F38-SUM(L38:N38) -> 894249.41 | H38: =+IF(G38=0,0,G38/E38) -> 3.4672925 | I38: 0.18 | J38: 0.0165 | K38: 0.076 | L38: =+I38*F38 -> 216307.05 | M38: =J38*(F38-L38) -> 16259.08 | N38: =K38*(F38-L38) -> 74890.309
B39: =B38 -> 45078 | C39: New Fortress (Garanhuns) | D39: 40 | E39: 51113 | F39: 231102.32 | G39: =F39-SUM(L39:N39) -> 171974.79 | H39: =+IF(G39=0,0,G39/E39) -> 3.3645998 | I39: 0.18 | J39: 0.0165 | K39: 0.076 | L39: =+I39*F39 -> 41598.418 | M39: =J39*(F39-L39) -> 3126.8144 | N39: =K39*(F39-L39) -> 14402.297
B40: =B39 -> 45078 | C40: Contingência Rede Local (Vector) | D40: 4850 | E40: 0 | F40: =22000*2 -> 44000 | G40: =F40-SUM(L40:N40) -> 39930 | I40: 0 | J40: 0.0165 | K40: 0.076 | L40: =+I40*F40 -> 0 | M40: =J40*(F40-L40) -> 726 | N40: =K40*(F40-L40) -> 3344
B41: =B40 -> 45078 | C41: Contingência Rede Local (Mastergás) | D41: 18 Notas | E41: 0 | F41: =(12800*17)+(10000*1)+12732.8 -> 240332.8 | G41: =F41-SUM(L41:N41) -> 218102.02 | H41: =G41/(18*4000) -> 3.0291947 | I41: 0 | J41: 0.0165 | K41: 0.076 | L41: =+I41*F41 -> 0 | M41: =J41*(F41-L41) -> 3965.4912 | N41: =K41*(F41-L41) -> 18265.293
E43: =SUM(E19:E42) -> 46798584 | G43: =SUM(G19:G42) -> 79245562
B46: Observações Relevantes: As tarifas de fornecimento para o segmento de uso Veicular (GNV/GNC) incidem impostos de 12% de ICMS conforme Lei 14.956/2013 e 0% de PIS/COFINS, conforme Medida Provisória Nº 1.163, de 28 de fevereiro de 2023. Dessa forma, a Copergás informou a Petrobras todo o volume de GNV e GNC veicular comercializado durante o período de 01/06/2023 a 28/06/2023, o qual foi sensibilizado nas notas do supridor e, consequentemente, foram emitidas com alíquotas zero de PIS/Cofins. 18 Emissões de Conhecimento de Transporte de GNL pela Mastergás para abastecimento de parte da Rede Local.

Sheet Jul23
C2: RELATÓRIO MENSAL DE ACOMPANHAMENTO DO CUSTO DO GÁS
C3: 45108
C5: Petrobras | D5: =SUMIF($C$19:$G$41,$C$5:$C$8,$G$19:$G$41)/SUMIF($C$19:$G$41,$C$5:$C$8,$E$19:$E$41) -> 2.2213
C6: Shell | D6: =SUMIF($C$19:$G$41,$C$5:$C$8,$G$19:$G$41)/SUMIF($C$19:$G$41,$C$5:$C$8,$E$19:$E$41) -> 1.4049314
C7: NFE | D7: =SUM(G38:G39)/SUM(E38:E39) -> 3.4469122
C8: Mastergás | D8: =H41 -> 0 | M8: Poderação QDC | N8: Poderação QDR
C9: Custo Médio Ponderado real | D9: =+G43/E43 -> 1.6845292 | L9: =+C5 -> Petrobras | M9: =790000/1580000 -> 0.5 | N9: =+SUM(E19:E36)/E43 -> 0.30922543
L10: =+C6 -> Shell | M10: 0.47468354 | N10: =+SUM(E37:E37)/E43 -> 0.68238598
L11: =+C7 -> NFE | M11: 0.025316456 | N11: =+SUM(E38:E39)/E43 -> 0.0083885834
L12: REDE LOCAL | M12: 0 | N12: 0
L13: Total | M13: =SUM(M9:M12) -> 1 | N13: =SUM(N9:N12) -> 1
L17: CONFORME XML DA NOTA
B18: Mês | C18: Supridor | D18: Nota Fiscal | E18: Vol m³ | F18: Compra R$ c/tributos | G18: Compra R$ s/tributos | H18: Custo | I18: ICMS | J18: PIS | K18: COFINS | L18: ICMS | M18: PIS | N18: COFINS
B19: =C3 -> 45108 | C19: Petrobras | D19: 11652-6 | E19: 241292 | F19: 671151.92 | G19: =F19-SUM(L19:N19) -> 535981.92 | H19: =+IF(G19=0,0,G19/E19) -> 2.2213 | I19: 0.12 | J19: 0.0165 | K19: 0.076 | L19: =+I19*F19 -> 80538.23 | M19: =J19*(F19-L19) -> 9745.1259 | N19: =K19*(F19-L19) -> 44886.64
B20: =B19 -> 45108 | C20: Petrobras | D20: 5489-4 | E20: 2654793 | F20: 7384287.1 | G20: =F20-SUM(L20:N20) -> 5897091.7 | H20: =+IF(G20=0,0,G20/E20) -> 2.2213 | I20: 0.12 | J20: 0.0165 | K20: 0.076 | L20: =+I20*F20 -> 886114.45 | M20: =J20*(F20-L20) -> 107219.85 | N20: =K20*(F20-L20) -> 493861.12
B21: =B20 -> 45108 | C21: Petrobras | D21: 11651-6 | E21: 5097922 | F21: 14179832 | G21: =F21-SUM(L21:N21) -> 11324014 | H21: =+IF(G21=0,0,G21/E21) -> 2.2213 | I21: 0.12 | J21: 0.0165 | K21: 0.076 | L21: =+I21*F21 -> 1701579.9 | M21: =J21*(F21-L21) -> 205891.17 | N21: =K21*(F21-L21) -> 948347.19
B22: =B21 -> 45108 | C22: Petrobras | D22: 431830-2 | E22: 4586654 | F22: 12071844 | G22: =F22-SUM(L22:N22) -> 10188335 | H22: =+IF(G22=0,0,G22/E22) -> 2.2213 | I22: 0.07 | J22: 0.0165 | K22: 0.076 | L22: =+I22*F22 -> 845029.08 | M22: =J22*(F22-L22) -> 185242.45 | N22: =K22*(F22-L22) -> 853237.93
B23: =B22 -> 45108 | C23: Petrobras | D23: 5436-24 | E23: 1406576 | F23: 3912380.8 | G23: =F23-SUM(L23:N23) -> 3124427.3 | H23: =+IF(G23=0,0,G23/E23) -> 2.2213 | I23: 0.12 | J23: 0.0165 | K23: 0.076 | L23: =+I23*F23 -> 469485.69 | M23: =J23*(F23-L23) -> 56807.768 | N23: =K23*(F23-L23) -> 261660.02
B24: =B23 -> 45108 | C24: Petrobras | D24: 3754-12 | E24: 524041 | F24: 1457616.2 | G24: =F24-SUM(L24:N24) -> 1164052.3 | H24: =+IF(G24=0,0,G24/E24) -> 2.2213 | I24: 0.12 | J24: 0.0165 | K24: 0.076 | L24: =+I24*F24 -> 174913.94 | M24: =J24*(F24-L24) -> 21164.587 | N24: =K24*(F24-L24) -> 97485.369
B25: =B24 -> 45108 | C25: Petrobras | G25: =F25-SUM(L25:N25) -> 0 | H25: =+IF(G25=0,0,G25/E25) -> 0 | J25: 0.0165 | K25: 0.076 | L25: =+I25*F25 -> 0 | M25: =J25*(F25-L25) -> 0 | N25: =K25*(F25-L25) -> 0
B26: =B25 -> 45108 | C26: Petrobras | G26: =F26-SUM(L26:N26) -> 0 | H26: =+IF(G26=0,0,G26/E26) -> 0 | J26: 0.0165 | K26: 0.076 | L26: =+I26*F26 -> 0 | M26: =J26*(F26-L26) -> 0 | N26: =K26*(F26-L26) -> 0
B27: =B26 -> 45108 | C27: Petrobras | G27: =F27-SUM(L27:N27) -> 0 | H27: =+IF(G27=0,0,G27/E27) -> 0 | J27: 0.0165 | K27: 0.076 | L27: =+I27*F27 -> 0 | M27: =J27*(F27-L27) -> 0 | N27: =K27*(F27-L27) -> 0
B28: =B27 -> 45108 | C28: Petrobras | G28: =F28-SUM(L28:N28) -> 0 | H28: =+IF(G28=0,0,G28/E28) -> 0 | J28: 0.0165 | K28: 0.076 | L28: =+I28*F28 -> 0 | M28: =J28*(F28-L28) -> 0 | N28: =K28*(F28-L28) -> 0
B29: =B28 -> 45108 | C29: Petrobras | G29: =F29-SUM(L29:N29) -> 0 | H29: =+IF(G29=0,0,G29/E29) -> 0 | J29: 0.0165 | K29: 0.076 | L29: =+I29*F29 -> 0 | M29: =J29*(F29-L29) -> 0 | N29: =K29*(F29-L29) -> 0
B30: =B29 -> 45108 | C30: Petrobras | G30: =F30-SUM(L30:N30) -> 0 | H30: =+IF(G30=0,0,G30/E30) -> 0 | J30: 0.0165 | K30: 0.076 | L30: =+I30*F30 -> 0 | M30: =J30*(F30-L30) -> 0 | N30: =K30*(F30-L30) -> 0
B31: =B30 -> 45108 | C31: Petrobras | G31: =F31-SUM(L31:N31) -> 0 | H31: =+IF(G31=0,0,G31/E31) -> 0 | J31: 0.0165 | K31: 0.076 | L31: =+I31*F31 -> 0 | M31: =J31*(F31-L31) -> 0 | N31: =K31*(F31-L31) -> 0
B32: =B31 -> 45108 | C32: Petrobras | G32: =F32-SUM(L32:N32) -> 0 | H32: =+IF(G32=0,0,G32/E32) -> 0 | J32: 0.0165 | K32: 0.076 | L32: =+I32*F32 -> 0 | M32: =J32*(F32-L32) -> 0 | N32: =K32*(F32-L32) -> 0
B33: =B32 -> 45108 | C33: Petrobras | G33: =F33-SUM(L33:N33) -> 0 | H33: =+IF(G33=0,0,G33/E33) -> 0 | J33: 0.0165 | K33: 0.076 | L33: =+I33*F33 -> 0 | M33: =J33*(F33-L33) -> 0 | N33: =K33*(F33-L33) -> 0
B34: =B33 -> 45108 | C34: Petrobras | G34: =F34-SUM(L34:N34) -> 0 | H34: =+IF(G34=0,0,G34/E34) -> 0 | J34: 0.0165 | K34: 0.076 | L34: =+I34*F34 -> 0 | M34: =J34*(F34-L34) -> 0 | N34: =K34*(F34-L34) -> 0
B35: =B34 -> 45108 | C35: Petrobras | G35: =F35-SUM(L35:N35) -> 0 | H35: =+IF(G35=0,0,G35/E35) -> 0 | J35: 0.0165 | K35: 0.076 | L35: =+I35*F35 -> 0 | M35: =J35*(F35-L35) -> 0 | N35: =K35*(F35-L35) -> 0
B36: =B35 -> 45108 | C36: Petrobras | G36: =F36-SUM(L36:N36) -> 0 | H36: =+IF(G36=0,0,G36/E36) -> 0 | J36: 0.0165 | K36: 0.076 | L36: =+I36*F36 -> 0 | M36: =J36*(F36-L36) -> 0 | N36: =K36*(F36-L36) -> 0
B37: =B36 -> 45108 | C37: Shell | D37: 3715-1 | E37: 32022892 | F37: 53307227 | G37: =F37-SUM(L37:N37) -> 44989967 | H37: =+IF(G37=0,0,G37/E37) -> 1.4049314 | I37: 0.07 | J37: 0.0165 | K37: 0.076 | L37: =+I37*F37 -> 3731505.9 | M37: =J37*(F37-L37) -> 817999.41 | N37: =K37*(F37-L37) -> 3767754.8
B38: =B37 -> 45108 | C38: New Fortress (Petrolina) | D38: 44-1 | E38: 315533 | F38: 1470194.5 | G38: =F38-SUM(L38:N38) -> 1094045.2 | H38: =+IF(G38=0,0,G38/E38) -> 3.4672925 | I38: 0.18 | J38: 0.0165 | K38: 0.076 | L38: =+I38*F38 -> 264635 | M38: =J38*(F38-L38) -> 19891.731 | N38: =K38*(F38-L38) -> 91622.519
B39: =B38 -> 45108 | C39: New Fortress (Garanhuns) | D39: 42-1 | E39: 78125 | F39: 353234.38 | G39: =F39-SUM(L39:N39) -> 262859.36 | H39: =+IF(G39=0,0,G39/E39) -> 3.3645999 | I39: 0.18 | J39: 0.0165 | K39: 0.076 | L39: =+I39*F39 -> 63582.188 | M39: =J39*(F39-L39) -> 4779.2612 | N39: =K39*(F39-L39) -> 22013.567
B40: =B39 -> 45108 | C40: Contingência Rede Local (Vector) | D40: 5098 | E40: 0 | F40: 46866.66 | G40: =F40-SUM(L40:N40) -> 42531.494 | I40: 0 | J40: 0.0165 | K40: 0.076 | L40: =+I40*F40 -> 0 | M40: =J40*(F40-L40) -> 773.29989 | N40: =K40*(F40-L40) -> 3561.8662
B41: =B40 -> 45108 | C41: Contingência Rede Local (Mastergás) | D41: 47 Notas | E41: 0 | F41: =450000+952.5+20665.6 -> 471618.1 | G41: =F41-SUM(L41:N41) -> 427993.43 | I41: 0 | J41: 0.0165 | K41: 0.076 | L41: =+I41*F41 -> 0 | M41: =J41*(F41-L41) -> 7781.6987 | N41: =K41*(F41-L41) -> 35842.976
E43: =SUM(E19:E42) -> 46927828 | G43: =SUM(G19:G42) -> 79051299
B46: Observações Relevantes: As tarifas de fornecimento para o segmento de uso Veicular (GNV/GNC) incidem impostos de 12% de ICMS conforme Lei 14.956/2013. 47 Emissões de Conhecimento de Transporte de GNL pela Mastergás. 1 Emissão de Locação de Unidade de redutora de pressão pela ICTUS Engenharia para Rede Local.

Sheet Ago23
C2: RELATÓRIO MENSAL DE ACOMPANHAMENTO DO CUSTO DO GÁS
C3: 45139
C5: Petrobras | D5: =SUMIF($C$19:$G$41,$C$5:$C$8,$G$19:$G$41)/SUMIF($C$19:$G$41,$C$5:$C$8,$E$19:$E$41) -> 2.0676
C6: Shell | D6: =SUMIF($C$19:$G$41,$C$5:$C$8,$G$19:$G$41)/SUMIF($C$19:$G$41,$C$5:$C$8,$E$19:$E$41) -> 1.4251362
C7: NFE | D7: =SUM(G38:G39)/SUM(E38:E39) -> 2.973689
C8: Mastergás | D8: =H41 -> 0 | M8: Poderação QDC | N8: Poderação QDR
C9: Custo Médio Ponderado real | D9: =+G43/E43 -> 1.5839179 | L9: =+C5 -> Petrobras | M9: =790000/1580000 -> 0.5 | N9: =+SUM(E19:E36)/E43 -> 0.19628909
L10: =+C6 -> Shell | M10: 0.47468354 | N10: =+SUM(E37:E37)/E43 -> 0.80179333
L11: =+C7 -> NFE | M11: 0.025316456 | N11: =+SUM(E38:E39)/E43 -> 0.0019175714
L12: REDE LOCAL | M12: 0 | N12: 0
L13: Total | M13: =SUM(M9:M12) -> 1 | N13: =SUM(N9:N12) -> 1
L17: CONFORME XML DA NOTA
B18: Mês | C18: Supridor | D18: Nota Fiscal | E18: Vol m³ | F18: Compra R$ c/tributos | G18: Compra R$ s/tributos | H18: Custo | I18: ICMS | J18: PIS | K18: COFINS | L18: ICMS | M18: PIS | N18: COFINS
B19: =C3 -> 45139 | C19: Petrobras | D19: 3498-28 | E19: 53430 | F19: 138331.92 | G19: =F19-SUM(L19:N19) -> 110471.87 | H19: =+IF(G19=0,0,G19/E19) -> 2.0676001 | I19: 0.12 | J19: 0.0165 | K19: 0.076 | L19: =+I19*F19 -> 16599.83 | M19: =J19*(F19-L19) -> 2008.5795 | N19: =K19*(F19-L19) -> 9251.6388
B20: =B19 -> 45139 | C20: Petrobras | D20: 11699-6 | E20: 2684895 | F20: 6951275.9 | G20: =F20-SUM(L20:N20) -> 5551288.9 | H20: =+IF(G20=0,0,G20/E20) -> 2.0676 | I20: 0.12 | J20: 0.0165 | K20: 0.076 | L20: =+I20*F20 -> 834153.1 | M20: =J20*(F20-L20) -> 100932.53 | N20: =K20*(F20-L20) -> 464901.33
B21: =B20 -> 45139 | C21: Petrobras | D21: 5469-24 | E21: 1435818 | F21: 3717377 | G21: =F21-SUM(L21:N21) -> 2968697.3 | H21: =+IF(G21=0,0,G21/E21) -> 2.0676 | I21: 0.12 | J21: 0.0165 | K21: 0.076 | L21: =+I21*F21 -> 446085.24 | M21: =J21*(F21-L21) -> 53976.314 | N21: =K21*(F21-L21) -> 248618.18
B22: =B21 -> 45139 | C22: Petrobras | D22: 11700-6 | E22: 2051595 | F22: 5311642.7 | G22: =F22-SUM(L22:N22) -> 4241877.8 | H22: =+IF(G22=0,0,G22/E22) -> 2.0676 | I22: 0.12 | J22: 0.0165 | K22: 0.076 | L22: =+I22*F22 -> 637397.12 | M22: =J22*(F22-L22) -> 77125.051 | N22: =K22*(F22-L22) -> 355242.66
B23: =B22 -> 45139 | C23: Petrobras | D23: 5513-4 | E23: 1508526 | F23: 3905620.3 | G23: =F23-SUM(L23:N23) -> 3119028.4 | H23: =+IF(G23=0,0,G23/E23) -> 2.0676 | I23: 0.12 | J23: 0.0165 | K23: 0.076 | L23: =+I23*F23 -> 468674.43 | M23: =J23*(F23-L23) -> 56709.607 | N23: =K23*(F23-L23) -> 261207.88
B24: =B23 -> 45139 | C24: Petrobras | D24: 4117-4 | E24: 21137 | F24: 54724.34 | G24: =F24-SUM(L24:N24) -> 43702.858 | H24: =+IF(G24=0,0,G24/E24) -> 2.0675998 | I24: 0.12 | J24: 0.0165 | K24: 0.076 | L24: =+I24*F24 -> 6566.9208 | M24: =J24*(F24-L24) -> 794.59742 | N24: =K24*(F24-L24) -> 3659.9639
B25: =B24 -> 45139 | C25: Petrobras | D25: 431878-2 | E25: 1404025.8 | F25: 3439632.5 | G25: =F25-SUM(L25:N25) -> 2902963.8 | H25: =+IF(G25=0,0,G25/E25) -> 2.0676 | I25: 0.07 | J25: 0.0165 | K25: 0.076 | L25: =+I25*F25 -> 240774.27 | M25: =J25*(F25-L25) -> 52781.161 | N25: =K25*(F25-L25) -> 243113.22
B26: =B25 -> 45139 | C26: Petrobras | D26: 431877-2 | E26: 39970.158 | F26: 97920.32 | G26: =F26-SUM(L26:N26) -> 82642.302 | H26: =+IF(G26=0,0,G26/E26) -> 2.0676001 | I26: 0.07 | J26: 0.0165 | K26: 0.076 | L26: =+I26*F26 -> 6854.4224 | M26: =J26*(F26-L26) -> 1502.5873 | N26: =K26*(F26-L26) -> 6921.0082
B27: =B26 -> 45139 | C27: Petrobras | G27: =F27-SUM(L27:N27) -> 0 | H27: =+IF(G27=0,0,G27/E27) -> 0 | J27: 0.0165 | K27: 0.076 | L27: =+I27*F27 -> 0 | M27: =J27*(F27-L27) -> 0 | N27: =K27*(F27-L27) -> 0
B28: =B27 -> 45139 | C28: Petrobras | G28: =F28-SUM(L28:N28) -> 0 | H28: =+IF(G28=0,0,G28/E28) -> 0 | J28: 0.0165 | K28: 0.076 | L28: =+I28*F28 -> 0 | M28: =J28*(F28-L28) -> 0 | N28: =K28*(F28-L28) -> 0
B29: =B28 -> 45139 | C29: Petrobras | G29: =F29-SUM(L29:N29) -> 0 | H29: =+IF(G29=0,0,G29/E29) -> 0 | J29: 0.0165 | K29: 0.076 | L29: =+I29*F29 -> 0 | M29: =J29*(F29-L29) -> 0 | N29: =K29*(F29-L29) -> 0
B30: =B29 -> 45139 | C30: Petrobras | G30: =F30-SUM(L30:N30) -> 0 | H30: =+IF(G30=0,0,G30/E30) -> 0 | J30: 0.0165 | K30: 0.076 | L30: =+I30*F30 -> 0 | M30: =J30*(F30-L30) -> 0 | N30: =K30*(F30-L30) -> 0
B31: =B30 -> 45139 | C31: Petrobras | G31: =F31-SUM(L31:N31) -> 0 | H31: =+IF(G31=0,0,G31/E31) -> 0 | J31: 0.0165 | K31: 0.076 | L31: =+I31*F31 -> 0 | M31: =J31*(F31-L31) -> 0 | N31: =K31*(F31-L31) -> 0
B32: =B31 -> 45139 | C32: Petrobras | G32: =F32-SUM(L32:N32) -> 0 | H32: =+IF(G32=0,0,G32/E32) -> 0 | J32: 0.0165 | K32: 0.076 | L32: =+I32*F32 -> 0 | M32: =J32*(F32-L32) -> 0 | N32: =K32*(F32-L32) -> 0
B33: =B32 -> 45139 | C33: Petrobras | G33: =F33-SUM(L33:N33) -> 0 | H33: =+IF(G33=0,0,G33/E33) -> 0 | J33: 0.0165 | K33: 0.076 | L33: =+I33*F33 -> 0 | M33: =J33*(F33-L33) -> 0 | N33: =K33*(F33-L33) -> 0
B34: =B33 -> 45139 | C34: Petrobras | G34: =F34-SUM(L34:N34) -> 0 | H34: =+IF(G34=0,0,G34/E34) -> 0 | J34: 0.0165 | K34: 0.076 | L34: =+I34*F34 -> 0 | M34: =J34*(F34-L34) -> 0 | N34: =K34*(F34-L34) -> 0
B35: =B34 -> 45139 | C35: Petrobras | G35: =F35-SUM(L35:N35) -> 0 | H35: =+IF(G35=0,0,G35/E35) -> 0 | J35: 0.0165 | K35: 0.076 | L35: =+I35*F35 -> 0 | M35: =J35*(F35-L35) -> 0 | N35: =K35*(F35-L35) -> 0
B36: =B35 -> 45139 | C36: Petrobras | G36: =F36-SUM(L36:N36) -> 0 | H36: =+IF(G36=0,0,G36/E36) -> 0 | J36: 0.0165 | K36: 0.076 | L36: =+I36*F36 -> 0 | M36: =J36*(F36-L36) -> 0 | N36: =K36*(F36-L36) -> 0
B37: =B36 -> 45139 | C37: Shell | D37: 4071-1 | E37: 37577305 | F37: 63453037 | G37: =F37-SUM(L37:N37) -> 53552777 | H37: =+IF(G37=0,0,G37/E37) -> 1.4251362 | I37: 0.07 | J37: 0.0165 | K37: 0.076 | L37: =+I37*F37 -> 4441712.6 | M37: =J37*(F37-L37) -> 973686.86 | N37: =K37*(F37-L37) -> 4484860.7
B38: =B37 -> 45139 | C38: New Fortress (Petrolina) | D38: 46-1 | E38: 56218 | F38: 227559.22 | G38: =F38-SUM(L38:N38) -> 169338.19 | H38: =+IF(G38=0,0,G38/E38) -> 3.0121704 | I38: 0.18 | J38: 0.0165 | K38: 0.076 | L38: =+I38*F38 -> 40960.66 | M38: =J38*(F38-L38) -> 3078.8762 | N38: =K38*(F38-L38) -> 14181.491
B39: =B38 -> 45139 | C39: New Fortress (Garanhuns) | D39: 43-1 | E39: 33652 | F39: 131569.22 | G39: =F39-SUM(L39:N39) -> 97907.235 | H39: =+IF(G39=0,0,G39/E39) -> 2.9094032 | I39: 0.18 | J39: 0.0165 | K39: 0.076 | L39: =+I39*F39 -> 23682.46 | M39: =J39*(F39-L39) -> 1780.1315 | N39: =K39*(F39-L39) -> 8199.3938
B40: =B39 -> 45139 | C40: Contingência Rede Local (Vector) | D40: 5225 | E40: 0 | F40: 74000 | G40: =F40-SUM(L40:N40) -> 67155 | I40: 0 | J40: 0.0165 | K40: 0.076 | L40: =+I40*F40 -> 0 | M40: =J40*(F40-L40) -> 1221 | N40: =K40*(F40-L40) -> 5624
B41: =B40 -> 45139 | C41: Contingência Rede Local (Mastergás) | D41: 132 Notas | E41: 0 | F41: 1460000 | G41: =F41-SUM(L41:N41) -> 1324950 | I41: 0 | J41: 0.0165 | K41: 0.076 | L41: =+I41*F41 -> 0 | M41: =J41*(F41-L41) -> 24090 | N41: =K41*(F41-L41) -> 110960
E43: =SUM(E19:E42) -> 46866572 | G43: =SUM(G19:G42) -> 74232801
B46: Observações Relevantes: As tarifas de fornecimento para o segmento de uso Veicular (GNV/GNC) incidem impostos de 12% de ICMS conforme Lei 14.956/2013. 132 Emissões de Conhecimento de Transporte de GNL pela Mastergás. 1 Emissão de Locação de Unidade de redutora de pressão pela ICTUS Engenharia para Rede Local.

Sheet Set23
C2: RELATÓRIO MENSAL DE ACOMPANHAMENTO DO CUSTO DO GÁS
C3: 45170
C5: Petrobras | D5: =SUMIF($C$19:$G$41,$C$5:$C$8,$G$19:$G$41)/SUMIF($C$19:$G$41,$C$5:$C$8,$E$19:$E$41) -> 2.0676
C6: Shell | D6: =SUMIF($C$19:$G$41,$C$5:$C$8,$G$19:$G$41)/SUMIF($C$19:$G$41,$C$5:$C$8,$E$19:$E$41) -> 1.4250855
C7: NFE | D7: =IFERROR(SUM(G38:G39)/SUM(E38:E39),"")
C8: Mastergás/Vector | D8: =H41+H40 -> 0 | M8: Poderação QDC | N8: Poderação QDR
C9: Custo Médio Ponderado real | D9: =+G43/E43 -> 1.6574474 | L9: =+C5 -> Petrobras | M9: =790000/1580000 -> 0.5 | N9: =+SUM(E19:E36)/E43 -> 0.32077762
L10: =+C6 -> Shell | M10: 0.47468354 | N10: =+SUM(E37:E37)/E43 -> 0.67922238
L11: =+C7 -> NFE | M11: 0.025316456 | N11: =+SUM(E38:E39)/E43 -> 0
L12: REDE LOCAL | M12: 0 | N12: 0
L13: Total | M13: =SUM(M9:M12) -> 1 | N13: =SUM(N9:N12) -> 1
L17: CONFORME XML DA NOTA
B18: Mês | C18: Supridor | D18: Nota Fiscal | E18: Vol m³ | F18: Compra R$ c/tributos | G18: Compra R$ s/tributos | H18: Custo | I18: ICMS | J18: PIS | K18: COFINS | L18: ICMS | M18: PIS | N18: COFINS
B19: =C3 -> 45170 | C19: Petrobras | D19: 5527-4 | E19: 545002 | F19: 1411027 | G19: =F19-SUM(L19:N19) -> 1126846.1 | H19: =+IF(G19=0,0,G19/E19) -> 2.0676 | I19: 0.12 | J19: 0.0165 | K19: 0.076 | L19: =+I19*F19 -> 169323.24 | M19: =J19*(F19-L19) -> 20488.112 | N19: =K19*(F19-L19) -> 94369.484
B20: =B19 -> 45170 | C20: Petrobras | D20: 11739-6 | E20: 1360111 | F20: 3521369.3 | G20: =F20-SUM(L20:N20) -> 2812165.5 | H20: =+IF(G20=0,0,G20/E20) -> 2.0676 | I20: 0.12 | J20: 0.0165 | K20: 0.076 | L20: =+I20*F20 -> 422564.31 | M20: =J20*(F20-L20) -> 51130.282 | N20: =K20*(F20-L20) -> 235509.18
B21: =B20 -> 45170 | C21: Petrobras | D21: 3521-28 | E21: 1827681 | F21: 4731922.4 | G21: =F21-SUM(L21:N21) -> 3778913.2 | H21: =+IF(G21=0,0,G21/E21) -> 2.0676 | I21: 0.12 | J21: 0.0165 | K21: 0.076 | L21: =+I21*F21 -> 567830.69 | M21: =J21*(F21-L21) -> 68707.513 | N21: =K21*(F21-L21) -> 316470.97
B22: =B21 -> 45170 | C22: Petrobras | D22: 5518-24 | E22: 7031955 | F22: 18205948 | G22: =F22-SUM(L22:N22) -> 14539270 | H22: =+IF(G22=0,0,G22/E22) -> 2.0676 | I22: 0.12 | J22: 0.0165 | K22: 0.076 | L22: =+I22*F22 -> 2184713.8 | M22: =J22*(F22-L22) -> 264350.37 | N22: =K22*(F22-L22) -> 1217613.8
B23: =B22 -> 45170 | C23: Petrobras | D23: 3762-12 | E23: 83674 | F23: 216634.56 | G23: =F23-SUM(L23:N23) -> 173004.36 | H23: =+IF(G23=0,0,G23/E23) -> 2.0676 | I23: 0.12 | J23: 0.0165 | K23: 0.076 | L23: =+I23*F23 -> 25996.147 | M23: =J23*(F23-L23) -> 3145.5338 | N23: =K23*(F23-L23) -> 14488.519
B24: =B23 -> 45170 | C24: Petrobras | D24: 431950-2 | E24: 3522837 | F24: 8630371.5 | G24: =F24-SUM(L24:N24) -> 7283817.8 | H24: =+IF(G24=0,0,G24/E24) -> 2.0676 | I24: 0.07 | J24: 0.0165 | K24: 0.076 | L24: =+I24*F24 -> 604126 | M24: =J24*(F24-L24) -> 132433.05 | N24: =K24*(F24-L24) -> 609994.66
B25: =B24 -> 45170 | C25: Petrobras | D25: 11740-6 | E25: 918219 | F25: 2377297.3 | G25: =F25-SUM(L25:N25) -> 1898509.6 | H25: =+IF(G25=0,0,G25/E25) -> 2.0676 | I25: 0.12 | J25: 0.0165 | K25: 0.076 | L25: =+I25*F25 -> 285275.67 | M25: =J25*(F25-L25) -> 34518.356 | N25: =K25*(F25-L25) -> 158993.64
B26: =B25 -> 45170 | C26: Petrobras | G26: =F26-SUM(L26:N26) -> 0 | H26: =+IF(G26=0,0,G26/E26) -> 0 | J26: 0.0165 | K26: 0.076 | L26: =+I26*F26 -> 0 | M26: =J26*(F26-L26) -> 0 | N26: =K26*(F26-L26) -> 0
B27: =B26 -> 45170 | C27: Petrobras | G27: =F27-SUM(L27:N27) -> 0 | H27: =+IF(G27=0,0,G27/E27) -> 0 | J27: 0.0165 | K27: 0.076 | L27: =+I27*F27 -> 0 | M27: =J27*(F27-L27) -> 0 | N27: =K27*(F27-L27) -> 0
B28: =B27 -> 45170 | C28: Petrobras | G28: =F28-SUM(L28:N28) -> 0 | H28: =+IF(G28=0,0,G28/E28) -> 0 | J28: 0.0165 | K28: 0.076 | L28: =+I28*F28 -> 0 | M28: =J28*(F28-L28) -> 0 | N28: =K28*(F28-L28) -> 0
B29: =B28 -> 45170 | C29: Petrobras | G29: =F29-SUM(L29:N29) -> 0 | H29: =+IF(G29=0,0,G29/E29) -> 0 | J29: 0.0165 | K29: 0.076 | L29: =+I29*F29 -> 0 | M29: =J29*(F29-L29) -> 0 | N29: =K29*(F29-L29) -> 0
B30: =B29 -> 45170 | C30: Petrobras | G30: =F30-SUM(L30:N30) -> 0 | H30: =+IF(G30=0,0,G30/E30) -> 0 | J30: 0.0165 | K30: 0.076 | L30: =+I30*F30 -> 0 | M30: =J30*(F30-L30) -> 0 | N30: =K30*(F30-L30) -> 0
B31: =B30 -> 45170 | C31: Petrobras | G31: =F31-SUM(L31:N31) -> 0 | H31: =+IF(G31=0,0,G31/E31) -> 0 | J31: 0.0165 | K31: 0.076 | L31: =+I31*F31 -> 0 | M31: =J31*(F31-L31) -> 0 | N31: =K31*(F31-L31) -> 0
B32: =B31 -> 45170 | C32: Petrobras | G32: =F32-SUM(L32:N32) -> 0 | H32: =+IF(G32=0,0,G32/E32) -> 0 | J32: 0.0165 | K32: 0.076 | L32: =+I32*F32 -> 0 | M32: =J32*(F32-L32) -> 0 | N32: =K32*(F32-L32) -> 0
B33: =B32 -> 45170 | C33: Petrobras | G33: =F33-SUM(L33:N33) -> 0 | H33: =+IF(G33=0,0,G33/E33) -> 0 | J33: 0.0165 | K33: 0.076 | L33: =+I33*F33 -> 0 | M33: =J33*(F33-L33) -> 0 | N33: =K33*(F33-L33) -> 0
B34: =B33 -> 45170 | C34: Petrobras | G34: =F34-SUM(L34:N34) -> 0 | H34: =+IF(G34=0,0,G34/E34) -> 0 | J34: 0.0165 | K34: 0.076 | L34: =+I34*F34 -> 0 | M34: =J34*(F34-L34) -> 0 | N34: =K34*(F34-L34) -> 0
B35: =B34 -> 45170 | C35: Petrobras | G35: =F35-SUM(L35:N35) -> 0 | H35: =+IF(G35=0,0,G35/E35) -> 0 | J35: 0.0165 | K35: 0.076 | L35: =+I35*F35 -> 0 | M35: =J35*(F35-L35) -> 0 | N35: =K35*(F35-L35) -> 0
B36: =B35 -> 45170 | C36: Petrobras | G36: =F36-SUM(L36:N36) -> 0 | H36: =+IF(G36=0,0,G36/E36) -> 0 | J36: 0.0165 | K36: 0.076 | L36: =+I36*F36 -> 0 | M36: =J36*(F36-L36) -> 0 | N36: =K36*(F36-L36) -> 0
B37: =B36 -> 45170 | C37: Shell | D37: 4499-1 | E37: 32374317 | F37: 54665329 | G37: =F37-SUM(L37:N37) -> 46136171 | H37: =+IF(G37=0,0,G37/E37) -> 1.4250855 | I37: 0.07 | J37: 0.0165 | K37: 0.076 | L37: =+I37*F37 -> 3826573 | M37: =J37*(F37-L37) -> 838839.48 | N37: =K37*(F37-L37) -> 3863745.5
B38: =B37 -> 45170 | C38: New Fortress (Petrolina) | E38: 0 | G38: =F38-SUM(L38:N38) -> 0 | H38: =+IF(G38=0,0,G38/E38) -> 0 | J38: 0.0165 | K38: 0.076 | L38: =+I38*F38 -> 0 | M38: =J38*(F38-L38) -> 0 | N38: =K38*(F38-L38) -> 0
B39: =B38 -> 45170 | C39: New Fortress (Garanhuns) | G39: =F39-SUM(L39:N39) -> 0 | H39: =+IF(G39=0,0,G39/E39) -> 0 | J39: 0.0165 | K39: 0.076 | L39: =+I39*F39 -> 0 | M39: =J39*(F39-L39) -> 0 | N39: =K39*(F39-L39) -> 0
B40: =B39 -> 45170 | C40: Contingência Rede Local (Vector) | D40: 2 Notas | E40: 0 | F40: =74000+49333.2 -> 123333.2 | G40: =F40-SUM(L40:N40) -> 111924.88 | I40: 0 | J40: 0.0165 | K40: 0.076 | L40: =+I40*F40 -> 0 | M40: =J40*(F40-L40) -> 2034.9978 | N40: =K40*(F40-L40) -> 9373.3232
B41: =B40 -> 45170 | C41: Contingência Rede Local (Mastergás) | D41: 109 Notas | E41: 0 | F41: =1222800+32970 -> 1255770 | G41: =F41-SUM(L41:N41) -> 1139611.3 | I41: 0 | J41: 0.0165 | K41: 0.076 | L41: =+I41*F41 -> 0 | M41: =J41*(F41-L41) -> 20720.205 | N41: =K41*(F41-L41) -> 95438.52
E43: =SUM(E19:E42) -> 47663796 | G43: =SUM(G19:G42) -> 79000234
B46: Observações Relevantes: As tarifas de fornecimento para o segmento de uso Veicular (GNV/GNC) incidem impostos de 12% de ICMS conforme Lei 14.956/2013. 109 Emissões de Conhecimento de Transporte de GNL pela Mastergás. 2 Emissões de Locação de Unidade de redutora de pressão pela ICTUS Engenharia para Rede Local.

Sheet Out23
C2: RELATÓRIO MENSAL DE ACOMPANHAMENTO DO CUSTO DO GÁS
C3: 45200
C5: Petrobras | D5: =SUMIF($C$19:$G$41,$C$5:$C$8,$G$19:$G$41)/SUMIF($C$19:$G$41,$C$5:$C$8,$E$19:$E$41) -> 2.0676029
C6: Shell | D6: =SUMIF($C$19:$G$41,$C$5:$C$8,$G$19:$G$41)/SUMIF($C$19:$G$41,$C$5:$C$8,$E$19:$E$41) -> 1.4250855
C7: NFE | D7: =IFERROR(SUM(G38:G39)/SUM(E38:E39),"") -> 1.9232515
C8: Mastergás/Vector | D8: =H41+H40 -> 0
C9: Custo Médio Ponderado real | D9: =+G43/E43 -> 1.6828177
L17: CONFORME XML DA NOTA
B18: Mês | C18: Supridor | D18: Nota Fiscal | E18: Vol m³ | F18: Compra R$ c/tributos | G18: Compra R$ s/tributos | H18: Custo | I18: ICMS | J18: PIS | K18: COFINS | L18: ICMS | M18: PIS | N18: COFINS
B19: =C3 -> 45200 | C19: Petrobras | D19: 11772-6 | E19: 12594880 | F19: 32608532 | G19: =F19-SUM(L19:N19) -> 26041174 | H19: =+IF(G19=0,0,G19/E19) -> 2.0676 | I19: 0.12 | J19: 0.0165 | K19: 0.076 | L19: =+I19*F19 -> 3913023.9 | M19: =J19*(F19-L19) -> 473475.89 | N19: =K19*(F19-L19) -> 2180858.6
B20: =B19 -> 45200 | C20: Petrobras | D20: 11773-6 | E20: 3732478 | F20: 9663500.5 | G20: =F20-SUM(L20:N20) -> 7717271.5 | H20: =+IF(G20=0,0,G20/E20) -> 2.0676 | I20: 0.12 | J20: 0.0165 | K20: 0.076 | L20: =+I20*F20 -> 1159620.1 | M20: =J20*(F20-L20) -> 140314.03 | N20: =K20*(F20-L20) -> 646294.91
B21: =B20 -> 45200 | C21: Petrobras | D21: 5547-24 | E21: 438544 | F21: 1135403.9 | G21: =F21-SUM(L21:N21) -> 906733.57 | H21: =+IF(G21=0,0,G21/E21) -> 2.0676 | I21: 0.12 | J21: 0.0165 | K21: 0.076 | L21: =+I21*F21 -> 136248.47 | M21: =J21*(F21-L21) -> 16486.065 | N21: =K21*(F21-L21) -> 75935.814
B22: =B21 -> 45200 | C22: Petrobras | D22: 3775-12 | E22: 659533 | F22: 1707551.2 | G22: =F22-SUM(L22:N22) -> 1363650.4 | H22: =+IF(G22=0,0,G22/E22) -> 2.0676 | I22: 0.12 | J22: 0.0165 | K22: 0.076 | L22: =+I22*F22 -> 204906.15 | M22: =J22*(F22-L22) -> 24793.644 | N22: =K22*(F22-L22) -> 114201.03
B23: =B22 -> 45200 | C23: Petrobras | D23: 11774-6 | E23: 43 | F23: 156.32 | G23: =F23-SUM(L23:N23) -> 124.83715 | H23: =+IF(G23=0,0,G23/E23) -> 2.9031896 | I23: 0.12 | J23: 0.0165 | K23: 0.076 | L23: =+I23*F23 -> 18.7584 | M23: =J23*(F23-L23) -> 2.2697664 | N23: =K23*(F23-L23) -> 10.454682
B24: =B23 -> 45200 | C24: Petrobras | D24: 11775-6 | E24: 17 | F24: 61.81 | G24: =F24-SUM(L24:N24) -> 49.361466 | H24: =+IF(G24=0,0,G24/E24) -> 2.9036156 | I24: 0.12 | J24: 0.0165 | K24: 0.076 | L24: =+I24*F24 -> 7.4172 | M24: =J24*(F24-L24) -> 0.8974812 | N24: =K24*(F24-L24) -> 4.1338528
B25: =B24 -> 45200 | C25: Petrobras | G25: =F25-SUM(L25:N25) -> 0 | H25: =+IF(G25=0,0,G25/E25) -> 0 | J25: 0.0165 | K25: 0.076 | L25: =+I25*F25 -> 0 | M25: =J25*(F25-L25) -> 0 | N25: =K25*(F25-L25) -> 0
B26: =B25 -> 45200 | C26: Petrobras | G26: =F26-SUM(L26:N26) -> 0 | H26: =+IF(G26=0,0,G26/E26) -> 0 | J26: 0.0165 | K26: 0.076 | L26: =+I26*F26 -> 0 | M26: =J26*(F26-L26) -> 0 | N26: =K26*(F26-L26) -> 0
B27: =B26 -> 45200 | C27: Petrobras | G27: =F27-SUM(L27:N27) -> 0 | H27: =+IF(G27=0,0,G27/E27) -> 0 | J27: 0.0165 | K27: 0.076 | L27: =+I27*F27 -> 0 | M27: =J27*(F27-L27) -> 0 | N27: =K27*(F27-L27) -> 0
B28: =B27 -> 45200 | C28: Petrobras | G28: =F28-SUM(L28:N28) -> 0 | H28: =+IF(G28=0,0,G28/E28) -> 0 | J28: 0.0165 | K28: 0.076 | L28: =+I28*F28 -> 0 | M28: =J28*(F28-L28) -> 0 | N28: =K28*(F28-L28) -> 0
B29: =B28 -> 45200 | C29: Petrobras | G29: =F29-SUM(L29:N29) -> 0 | H29: =+IF(G29=0,0,G29/E29) -> 0 | J29: 0.0165 | K29: 0.076 | L29: =+I29*F29 -> 0 | M29: =J29*(F29-L29) -> 0 | N29: =K29*(F29-L29) -> 0
B30: =B29 -> 45200 | C30: Petrobras | G30: =F30-SUM(L30:N30) -> 0 | H30: =+IF(G30=0,0,G30/E30) -> 0 | J30: 0.0165 | K30: 0.076 | L30: =+I30*F30 -> 0 | M30: =J30*(F30-L30) -> 0 | N30: =K30*(F30-L30) -> 0
B31: =B30 -> 45200 | C31: Petrobras | G31: =F31-SUM(L31:N31) -> 0 | H31: =+IF(G31=0,0,G31/E31) -> 0 | J31: 0.0165 | K31: 0.076 | L31: =+I31*F31 -> 0 | M31: =J31*(F31-L31) -> 0 | N31: =K31*(F31-L31) -> 0
B32: =B31 -> 45200 | C32: Petrobras | G32: =F32-SUM(L32:N32) -> 0 | H32: =+IF(G32=0,0,G32/E32) -> 0 | J32: 0.0165 | K32: 0.076 | L32: =+I32*F32 -> 0 | M32: =J32*(F32-L32) -> 0 | N32: =K32*(F32-L32) -> 0
B33: =B32 -> 45200 | C33: Petrobras | G33: =F33-SUM(L33:N33) -> 0 | H33: =+IF(G33=0,0,G33/E33) -> 0 | J33: 0.0165 | K33: 0.076 | L33: =+I33*F33 -> 0 | M33: =J33*(F33-L33) -> 0 | N33: =K33*(F33-L33) -> 0
B34: =B33 -> 45200 | C34: Petrobras | G34: =F34-SUM(L34:N34) -> 0 | H34: =+IF(G34=0,0,G34/E34) -> 0 | J34: 0.0165 | K34: 0.076 | L34: =+I34*F34 -> 0 | M34: =J34*(F34-L34) -> 0 | N34: =K34*(F34-L34) -> 0
B35: =B34 -> 45200 | C35: Petrobras | G35: =F35-SUM(L35:N35) -> 0 | H35: =+IF(G35=0,0,G35/E35) -> 0 | J35: 0.0165 | K35: 0.076 | L35: =+I35*F35 -> 0 | M35: =J35*(F35-L35) -> 0 | N35: =K35*(F35-L35) -> 0
B36: =B35 -> 45200 | C36: Petrobras | G36: =F36-SUM(L36:N36) -> 0 | H36: =+IF(G36=0,0,G36/E36) -> 0 | J36: 0.0165 | K36: 0.076 | L36: =+I36*F36 -> 0 | M36: =J36*(F36-L36) -> 0 | N36: =K36*(F36-L36) -> 0
B37: =B36 -> 45200 | C37: Shell | D37: 4953 | E37: 32633569 | F37: 55103087 | G37: =F37-SUM(L37:N37) -> 46505628 | H37: =+IF(G37=0,0,G37/E37) -> 1.4250855 | I37: 0.07 | J37: 0.0165 | K37: 0.076 | L37: =+I37*F37 -> 3857216.1 | M37: =J37*(F37-L37) -> 845556.86 | N37: =K37*(F37-L37) -> 3894686.2
B38: =B37 -> 45200 | C38: Galp | D38: 119 | E38: 413000 | F38: 1165320.8 | G38: =F38-SUM(L38:N38) -> 983501.62 | H38: =+IF(G38=0,0,G38/E38) -> 2.3813599 | I38: 0.07 | J38: 0.0165 | K38: 0.076 | L38: =+I38*F38 -> 81572.456 | M38: =J38*(F38-L38) -> 17881.848 | N38: =K38*(F38-L38) -> 82364.874
B39: =B38 -> 45200 | C39: Petrorecôncavo | D39: 6155 | E39: 537000 | F39: 1056332.7 | G39: =F39-SUM(L39:N39) -> 843587.29 | H39: =+IF(G39=0,0,G39/E39) -> 1.5709261 | I39: 0.12 | J39: 0.0165 | K39: 0.076 | L39: =+I39*F39 -> 126759.92 | M39: =J39*(F39-L39) -> 15337.951 | N39: =K39*(F39-L39) -> 70647.531
B40: =B39 -> 45200 | C40: Contingência Rede Local (Vector) | D40: 2 Notas Vector | E40: 0 | F40: =74000+37000 -> 111000 | G40: =F40-SUM(L40:N40) -> 100732.5 | I40: 0 | J40: 0.0165 | K40: 0.076 | L40: =+I40*F40 -> 0 | M40: =J40*(F40-L40) -> 1831.5 | N40: =K40*(F40-L40) -> 8436
B41: =B40 -> 45200 | C41: Contingência Rede Local (Mastergás) | D41: 2 Notas Mastergás | E41: 0 | F41: =1302048+214760 -> 1516808 | G41: =F41-SUM(L41:N41) -> 1376503.3 | I41: 0 | J41: 0.0165 | K41: 0.076 | L41: =+I41*F41 -> 0 | M41: =J41*(F41-L41) -> 25027.332 | N41: =K41*(F41-L41) -> 115277.41
E43: =SUM(E19:E42) -> 51009064 | G43: =SUM(G19:G42) -> 85838956
B46: Observações Relevantes: As tarifas de fornecimento para o segmento de uso Veicular (GNV/GNC) incidem impostos de 12% de ICMS conforme Lei 14.956/2013. 2 Emissões de Conhecimento de Transporte de GNL pela Mastergás. 2 Emissões de Locação de Unidade de redutora de pressão pela ICTUS Engenharia para Rede Local. Início do fornecimento GALP e PetroRecôncavo

Sheet Nov23
C2: RELATÓRIO MENSAL DE ACOMPANHAMENTO DO CUSTO DO GÁS
C3: 45231
C5: Petrobras | D5: =SUMIF($C$19:$G$41,$C$5:$C$8,$G$19:$G$41)/SUMIF($C$19:$G$41,$C$5:$C$8,$E$19:$E$41) -> 2.2281
C6: Shell | D6: =SUMIF($C$19:$G$41,$C$5:$C$8,$G$19:$G$41)/SUMIF($C$19:$G$41,$C$5:$C$8,$E$19:$E$41) -> 1.5834406
C7: NFE | D7: =IFERROR(SUM(G38:G39)/SUM(E38:E39),"") -> 2.3290334
C8: Mastergás/Vector | D8: =H41+H40 -> 0 | M8: Poderação QDC | N8: Poderação QDR
C9: Custo Médio Ponderado real | D9: =+G43/E43 -> 1.8278356 | L9: =+C5 -> Petrobras | M9: =790000/1580000 -> 0.5 | N9: =+SUM(E19:E36)/E43 -> 0.31956619
L10: =+C6 -> Shell | M10: 0.47468354 | N10: =+SUM(E37:E37)/E43 -> 0.67377602
L11: =+C7 -> NFE | M11: 0.025316456 | N11: =+SUM(E38:E39)/E43 -> 0.006657789
L12: REDE LOCAL | M12: 0 | N12: 0
L13: Total | M13: =SUM(M9:M12) -> 1 | N13: =SUM(N9:N12) -> 1
L17: CONFORME XML DA NOTA
B18: Mês | C18: Supridor | D18: Nota Fiscal | E18: Vol m³ | F18: Compra R$ c/tributos | G18: Compra R$ s/tributos | H18: Custo | I18: ICMS | J18: PIS | K18: COFINS | L18: ICMS | M18: PIS | N18: COFINS
B19: =C3 -> 45231 | C19: Petrobras | D19: 5549-4 | E19: 978807 | F19: 2730878.9 | G19: =F19-SUM(L19:N19) -> 2180879.9 | H19: =+IF(G19=0,0,G19/E19) -> 2.2281 | I19: 0.12 | J19: 0.0165 | K19: 0.076 | L19: =+I19*F19 -> 327705.47 | M19: =J19*(F19-L19) -> 39652.361 | N19: =K19*(F19-L19) -> 182641.18
B20: =B19 -> 45231 | C20: Petrobras | D20: 3536-28 | E20: 121463 | F20: 338882.68 | G20: =F20-SUM(L20:N20) -> 270631.71 | H20: =+IF(G20=0,0,G20/E20) -> 2.2281 | I20: 0.12 | J20: 0.0165 | K20: 0.076 | L20: =+I20*F20 -> 40665.922 | M20: =J20*(F20-L20) -> 4920.5765 | N20: =K20*(F20-L20) -> 22664.474
B21: =B20 -> 45231 | C21: Petrobras | D21: 432036-2 | E21: 1352361 | F21: 3570242.6 | G21: =F21-SUM(L21:N21) -> 3013195.5 | H21: =+IF(G21=0,0,G21/E21) -> 2.2281 | I21: 0.07 | J21: 0.0165 | K21: 0.076 | L21: =+I21*F21 -> 249916.99 | M21: =J21*(F21-L21) -> 54785.373 | N21: =K21*(F21-L21) -> 252344.75
B22: =B21 -> 45231 | C22: Petrobras | D22: 5573-24 | E22: 1528028 | F22: 4263209.6 | G22: =F22-SUM(L22:N22) -> 3404599.2 | H22: =+IF(G22=0,0,G22/E22) -> 2.2281 | I22: 0.12 | J22: 0.0165 | K22: 0.076 | L22: =+I22*F22 -> 511585.15 | M22: =J22*(F22-L22) -> 61901.803 | N22: =K22*(F22-L22) -> 285123.46
B23: =B22 -> 45231 | C23: Petrobras | D23: 11816-6 | E23: 3085433 | F23: 8608381.2 | G23: =F23-SUM(L23:N23) -> 6874653.3 | H23: =+IF(G23=0,0,G23/E23) -> 2.2281 | I23: 0.12 | J23: 0.0165 | K23: 0.076 | L23: =+I23*F23 -> 1033005.8 | M23: =J23*(F23-L23) -> 124993.7 | N23: =K23*(F23-L23) -> 575728.54
B24: =B23 -> 45231 | C24: Petrobras | D24: 11815-6 | E24: 7333586 | F24: 20460760 | G24: =F24-SUM(L24:N24) -> 16339963 | H24: =+IF(G24=0,0,G24/E24) -> 2.2281 | I24: 0.12 | J24: 0.0165 | K24: 0.076 | L24: =+I24*F24 -> 2455291.2 | M24: =J24*(F24-L24) -> 297090.24 | N24: =K24*(F24-L24) -> 1368415.6
B25: =B24 -> 45231 | C25: Petrobras | G25: =F25-SUM(L25:N25) -> 0 | H25: =+IF(G25=0,0,G25/E25) -> 0 | J25: 0.0165 | K25: 0.076 | L25: =+I25*F25 -> 0 | M25: =J25*(F25-L25) -> 0 | N25: =K25*(F25-L25) -> 0
B26: =B25 -> 45231 | C26: Petrobras | G26: =F26-SUM(L26:N26) -> 0 | H26: =+IF(G26=0,0,G26/E26) -> 0 | J26: 0.0165 | K26: 0.076 | L26: =+I26*F26 -> 0 | M26: =J26*(F26-L26) -> 0 | N26: =K26*(F26-L26) -> 0
B27: =B26 -> 45231 | C27: Petrobras | G27: =F27-SUM(L27:N27) -> 0 | H27: =+IF(G27=0,0,G27/E27) -> 0 | J27: 0.0165 | K27: 0.076 | L27: =+I27*F27 -> 0 | M27: =J27*(F27-L27) -> 0 | N27: =K27*(F27-L27) -> 0
B28: =B27 -> 45231 | C28: Petrobras | G28: =F28-SUM(L28:N28) -> 0 | H28: =+IF(G28=0,0,G28/E28) -> 0 | J28: 0.0165 | K28: 0.076 | L28: =+I28*F28 -> 0 | M28: =J28*(F28-L28) -> 0 | N28: =K28*(F28-L28) -> 0
B29: =B28 -> 45231 | C29: Petrobras | G29: =F29-SUM(L29:N29) -> 0 | H29: =+IF(G29=0,0,G29/E29) -> 0 | J29: 0.0165 | K29: 0.076 | L29: =+I29*F29 -> 0 | M29: =J29*(F29-L29) -> 0 | N29: =K29*(F29-L29) -> 0
B30: =B29 -> 45231 | C30: Petrobras | G30: =F30-SUM(L30:N30) -> 0 | H30: =+IF(G30=0,0,G30/E30) -> 0 | J30: 0.0165 | K30: 0.076 | L30: =+I30*F30 -> 0 | M30: =J30*(F30-L30) -> 0 | N30: =K30*(F30-L30) -> 0
B31: =B30 -> 45231 | C31: Petrobras | G31: =F31-SUM(L31:N31) -> 0 | H31: =+IF(G31=0,0,G31/E31) -> 0 | J31: 0.0165 | K31: 0.076 | L31: =+I31*F31 -> 0 | M31: =J31*(F31-L31) -> 0 | N31: =K31*(F31-L31) -> 0
B32: =B31 -> 45231 | C32: Petrobras | G32: =F32-SUM(L32:N32) -> 0 | H32: =+IF(G32=0,0,G32/E32) -> 0 | J32: 0.0165 | K32: 0.076 | L32: =+I32*F32 -> 0 | M32: =J32*(F32-L32) -> 0 | N32: =K32*(F32-L32) -> 0
B33: =B32 -> 45231 | C33: Petrobras | G33: =F33-SUM(L33:N33) -> 0 | H33: =+IF(G33=0,0,G33/E33) -> 0 | J33: 0.0165 | K33: 0.076 | L33: =+I33*F33 -> 0 | M33: =J33*(F33-L33) -> 0 | N33: =K33*(F33-L33) -> 0
B34: =B33 -> 45231 | C34: Petrobras | G34: =F34-SUM(L34:N34) -> 0 | H34: =+IF(G34=0,0,G34/E34) -> 0 | J34: 0.0165 | K34: 0.076 | L34: =+I34*F34 -> 0 | M34: =J34*(F34-L34) -> 0 | N34: =K34*(F34-L34) -> 0
B35: =B34 -> 45231 | C35: Petrobras | G35: =F35-SUM(L35:N35) -> 0 | H35: =+IF(G35=0,0,G35/E35) -> 0 | J35: 0.0165 | K35: 0.076 | L35: =+I35*F35 -> 0 | M35: =J35*(F35-L35) -> 0 | N35: =K35*(F35-L35) -> 0
B36: =B35 -> 45231 | C36: Petrobras | G36: =F36-SUM(L36:N36) -> 0 | H36: =+IF(G36=0,0,G36/E36) -> 0 | J36: 0.0165 | K36: 0.076 | L36: =+I36*F36 -> 0 | M36: =J36*(F36-L36) -> 0 | N36: =K36*(F36-L36) -> 0
B37: =B36 -> 45231 | C37: Shell | D37: 5417-1 | E37: 30360401 | F37: 56961274 | G37: =F37-SUM(L37:N37) -> 48073891 | H37: =+IF(G37=0,0,G37/E37) -> 1.5834406 | I37: 0.07 | J37: 0.0165 | K37: 0.076 | L37: =+I37*F37 -> 3987289.1 | M37: =J37*(F37-L37) -> 874070.74 | N37: =K37*(F37-L37) -> 4026022.8
B38: =B37 -> 45231 | C38: Galp | D38: 129-2 | E38: 300000.5 | F38: 827881.38 | G38: =F38-SUM(L38:N38) -> 698711.19 | H38: =+IF(G38=0,0,G38/E38) -> 2.3290334 | I38: 0.07 | J38: 0.0165 | K38: 0.076 | L38: =+I38*F38 -> 57951.697 | M38: =J38*(F38-L38) -> 12703.84 | N38: =K38*(F38-L38) -> 58514.656
B39: =B38 -> 45231 | C39: Petrorecôncavo | G39: =F39-SUM(L39:N39) -> 0 | H39: =+IF(G39=0,0,G39/E39) -> 0 | J39: 0.0165 | K39: 0.076 | L39: =+I39*F39 -> 0 | M39: =J39*(F39-L39) -> 0 | N39: =K39*(F39-L39) -> 0
B40: =B39 -> 45231 | C40: Contingência Rede Local (Vector) | D40: 5612 | E40: 0 | F40: =37000+37000 -> 74000 | G40: =F40-SUM(L40:N40) -> 67155 | I40: 0 | J40: 0.0165 | K40: 0.076 | L40: =+I40*F40 -> 0 | M40: =J40*(F40-L40) -> 1221 | N40: =K40*(F40-L40) -> 5624
B41: =B40 -> 45231 | C41: Contingência Rede Local (Mastergás) | D41: 2 Notas Mastergás | E41: 0 | F41: =1403017.6+182367.5 -> 1585385.1 | G41: =F41-SUM(L41:N41) -> 1438737 | I41: 0 | J41: 0.0165 | K41: 0.076 | L41: =+I41*F41 -> 0 | M41: =J41*(F41-L41) -> 26158.854 | N41: =K41*(F41-L41) -> 120489.27
E43: =SUM(E19:E42) -> 45060080 | G43: =SUM(G19:G42) -> 82362417
B46: Observações Relevantes: As tarifas de fornecimento para o segmento de uso Veicular (GNV/GNC) incidem impostos de 12% de ICMS conforme Lei 14.956/2013. 2 Emissões de Conhecimento de Transporte de GNL pela Mastergás. 1 Emissão de Locação de Unidade de redutora de pressão pela ICTUS Engenharia para Rede Local.

Sheet Dez23
C2: RELATÓRIO MENSAL DE ACOMPANHAMENTO DO CUSTO DO GÁS
C3: 45261
C5: Petrobras | D5: =SUMIF($C$19:$G$41,$C$5:$C$8,$G$19:$G$41)/SUMIF($C$19:$G$41,$C$5:$C$8,$E$19:$E$41) -> 2.228982
C6: Shell | D6: =SUMIF($C$19:$G$41,$C$5:$C$8,$G$19:$G$41)/SUMIF($C$19:$G$41,$C$5:$C$8,$E$19:$E$41) -> 1.5834997
C7: NFE | D7: =IFERROR(SUM(G38:G39)/SUM(E38:E39),"")
C8: Mastergás/Vector | D8: =H41+H40 -> 0 | M8: Poderação QDC | N8: Poderação QDR
C9: Custo Médio Ponderado real | D9: =+G43/E43 -> 1.796856 | L9: =+C5 -> Petrobras | M9: =790000/1580000 -> 0.5 | N9: =+SUM(E19:E36)/E43 -> 0.31519658
L10: =+C6 -> Shell | M10: 0.47468354 | N10: =+SUM(E37:E37)/E43 -> 0.68480342
L11: =+C7 -> NFE | M11: 0.025316456 | N11: =+SUM(E38:E39)/E43 -> 0
L12: REDE LOCAL | M12: 0 | N12: 0
L13: Total | M13: =SUM(M9:M12) -> 1 | N13: =SUM(N9:N12) -> 1
L17: CONFORME XML DA NOTA
B18: Mês | C18: Supridor | D18: Nota Fiscal | E18: Vol m³ | F18: Compra R$ c/tributos | G18: Compra R$ s/tributos | H18: Custo | I18: ICMS | J18: PIS | K18: COFINS | L18: ICMS | M18: PIS | N18: COFINS
B19: =C3 -> 45261 | C19: Petrobras | D19: 5627-24 | E19: 743897 | F19: 2075478.2 | G19: =F19-SUM(L19:N19) -> 1657476.9 | H19: =+IF(G19=0,0,G19/E19) -> 2.2281 | I19: 0.12 | J19: 0.0165 | K19: 0.076 | L19: =+I19*F19 -> 249057.39 | M19: =J19*(F19-L19) -> 30135.944 | N19: =K19*(F19-L19) -> 138807.98
B20: =B19 -> 45261 | C20: Petrobras | D20: 11858-6 | E20: 1274954 | F20: 3557131.2 | G20: =F20-SUM(L20:N20) -> 2840725 | H20: =+IF(G20=0,0,G20/E20) -> 2.2281 | I20: 0.12 | J20: 0.0165 | K20: 0.076 | L20: =+I20*F20 -> 426855.75 | M20: =J20*(F20-L20) -> 51649.546 | N20: =K20*(F20-L20) -> 237900.94
B21: =B20 -> 45261 | C21: Petrobras | D21: 432107-2 | E21: 636300 | F21: 1679836.5 | G21: =F21-SUM(L21:N21) -> 1417740 | H21: =+IF(G21=0,0,G21/E21) -> 2.2281 | I21: 0.07 | J21: 0.0165 | K21: 0.076 | L21: =+I21*F21 -> 117588.56 | M21: =J21*(F21-L21) -> 25777.091 | N21: =K21*(F21-L21) -> 118730.85
B22: =B21 -> 45261 | C22: Petrobras | D22: 11859-6 | E22: 5986025 | F22: 16701055 | G22: =F22-SUM(L22:N22) -> 13337462 | H22: =+IF(G22=0,0,G22/E22) -> 2.2281 | I22: 0.12 | J22: 0.0165 | K22: 0.076 | L22: =+I22*F22 -> 2004126.6 | M22: =J22*(F22-L22) -> 242499.31 | N22: =K22*(F22-L22) -> 1116966.5
B23: =B22 -> 45261 | C23: Petrobras | D23: 3548-28 | E23: 151935 | F23: 423899.79 | G23: =F23-SUM(L23:N23) -> 338526.37 | H23: =+IF(G23=0,0,G23/E23) -> 2.2281 | I23: 0.12 | J23: 0.0165 | K23: 0.076 | L23: =+I23*F23 -> 50867.975 | M23: =J23*(F23-L23) -> 6155.025 | N23: =K23*(F23-L23) -> 28350.418
B24: =B23 -> 45261 | C24: Petrobras | D24: 5563-4 | E24: 4217569 | F24: 11767049 | G24: =F24-SUM(L24:N24) -> 9397165.5 | H24: =+IF(G24=0,0,G24/E24) -> 2.2281 | I24: 0.12 | J24: 0.0165 | K24: 0.076 | L24: =+I24*F24 -> 1412045.9 | M24: =J24*(F24-L24) -> 170857.55 | N24: =K24*(F24-L24) -> 786980.25
B25: =B24 -> 45261 | C25: Petrobras | D25: 3808-12 | E25: 1306727 | F25: 3645778.1 | G25: =F25-SUM(L25:N25) -> 2911518.4 | H25: =+IF(G25=0,0,G25/E25) -> 2.2281 | I25: 0.12 | J25: 0.0165 | K25: 0.076 | L25: =+I25*F25 -> 437493.38 | M25: =J25*(F25-L25) -> 52936.699 | N25: =K25*(F25-L25) -> 243829.64
B26: =B25 -> 45261 | C26: Petrobras | D26: 11860-6 | E26: 13801 | F26: 54333.01 | G26: =F26-SUM(L26:N26) -> 43390.342 | H26: =+IF(G26=0,0,G26/E26) -> 3.1439998 | I26: 0.12 | J26: 0.0165 | K26: 0.076 | L26: =+I26*F26 -> 6519.9612 | M26: =J26*(F26-L26) -> 788.91531 | N26: =K26*(F26-L26) -> 3633.7917
B27: =B26 -> 45261 | C27: Petrobras | G27: =F27-SUM(L27:N27) -> 0 | H27: =+IF(G27=0,0,G27/E27) -> 0 | J27: 0.0165 | K27: 0.076 | L27: =+I27*F27 -> 0 | M27: =J27*(F27-L27) -> 0 | N27: =K27*(F27-L27) -> 0
B28: =B27 -> 45261 | C28: Petrobras | G28: =F28-SUM(L28:N28) -> 0 | H28: =+IF(G28=0,0,G28/E28) -> 0 | J28: 0.0165 | K28: 0.076 | L28: =+I28*F28 -> 0 | M28: =J28*(F28-L28) -> 0 | N28: =K28*(F28-L28) -> 0
B29: =B28 -> 45261 | C29: Petrobras | G29: =F29-SUM(L29:N29) -> 0 | H29: =+IF(G29=0,0,G29/E29) -> 0 | J29: 0.0165 | K29: 0.076 | L29: =+I29*F29 -> 0 | M29: =J29*(F29-L29) -> 0 | N29: =K29*(F29-L29) -> 0
B30: =B29 -> 45261 | C30: Petrobras | G30: =F30-SUM(L30:N30) -> 0 | H30: =+IF(G30=0,0,G30/E30) -> 0 | J30: 0.0165 | K30: 0.076 | L30: =+I30*F30 -> 0 | M30: =J30*(F30-L30) -> 0 | N30: =K30*(F30-L30) -> 0
B31: =B30 -> 45261 | C31: Petrobras | G31: =F31-SUM(L31:N31) -> 0 | H31: =+IF(G31=0,0,G31/E31) -> 0 | J31: 0.0165 | K31: 0.076 | L31: =+I31*F31 -> 0 | M31: =J31*(F31-L31) -> 0 | N31: =K31*(F31-L31) -> 0
B32: =B31 -> 45261 | C32: Petrobras | G32: =F32-SUM(L32:N32) -> 0 | H32: =+IF(G32=0,0,G32/E32) -> 0 | J32: 0.0165 | K32: 0.076 | L32: =+I32*F32 -> 0 | M32: =J32*(F32-L32) -> 0 | N32: =K32*(F32-L32) -> 0
B33: =B32 -> 45261 | C33: Petrobras | G33: =F33-SUM(L33:N33) -> 0 | H33: =+IF(G33=0,0,G33/E33) -> 0 | J33: 0.0165 | K33: 0.076 | L33: =+I33*F33 -> 0 | M33: =J33*(F33-L33) -> 0 | N33: =K33*(F33-L33) -> 0
B34: =B33 -> 45261 | C34: Petrobras | G34: =F34-SUM(L34:N34) -> 0 | H34: =+IF(G34=0,0,G34/E34) -> 0 | J34: 0.0165 | K34: 0.076 | L34: =+I34*F34 -> 0 | M34: =J34*(F34-L34) -> 0 | N34: =K34*(F34-L34) -> 0
B35: =B34 -> 45261 | C35: Petrobras | G35: =F35-SUM(L35:N35) -> 0 | H35: =+IF(G35=0,0,G35/E35) -> 0 | J35: 0.0165 | K35: 0.076 | L35: =+I35*F35 -> 0 | M35: =J35*(F35-L35) -> 0 | N35: =K35*(F35-L35) -> 0
B36: =B35 -> 45261 | C36: Galp | D36: 154-1 | E36: 310451 | F36: 857527.75 | G36: =F36-SUM(L36:N36) -> 723731.98 | H36: =+IF(G36=0,0,G36/E36) -> 2.3312277 | I36: 0.07 | J36: 0.0165 | K36: 0.076 | L36: =+I36*F36 -> 60026.943 | M36: =J36*(F36-L36) -> 13158.763 | N36: =K36*(F36-L36) -> 60610.061
B37: =B36 -> 45261 | C37: Shell | D37: 5846-1 | E37: 31810809 | F37: 59684712 | G37: =F37-SUM(L37:N37) -> 50372405 | H37: =+IF(G37=0,0,G37/E37) -> 1.5834997 | I37: 0.07 | J37: 0.0165 | K37: 0.076 | L37: =+I37*F37 -> 4177929.9 | M37: =J37*(F37-L37) -> 915861.91 | N37: =K37*(F37-L37) -> 4218515.5
B38: =B37 -> 45261 | C38: New Fortress (Petrolina) | E38: 0 | G38: =F38-SUM(L38:N38) -> 0 | H38: =+IF(G38=0,0,G38/E38) -> 0 | J38: 0.0165 | K38: 0.076 | L38: =+I38*F38 -> 0 | M38: =J38*(F38-L38) -> 0 | N38: =K38*(F38-L38) -> 0
B39: =B38 -> 45261 | C39: New Fortress (Garanhuns) | G39: =F39-SUM(L39:N39) -> 0 | H39: =+IF(G39=0,0,G39/E39) -> 0 | J39: 0.0165 | K39: 0.076 | L39: =+I39*F39 -> 0 | M39: =J39*(F39-L39) -> 0 | N39: =K39*(F39-L39) -> 0
B40: =B39 -> 45261 | C40: Contingência Rede Local (Vector) | D40: 2 Notas | E40: 0 | F40: =37000+37000+9866.67+9866.67 -> 93733.34 | G40: =F40-SUM(L40:N40) -> 85063.006 | I40: 0 | J40: 0.0165 | K40: 0.076 | L40: =+I40*F40 -> 0 | M40: =J40*(F40-L40) -> 1546.6001 | N40: =K40*(F40-L40) -> 7123.7338
B41: =B40 -> 45261 | C41: Contingência Rede Local (Mastergás) | D41: 2 Notas Mastergás | E41: 0 | F41: =330316.8+47857.5 -> 378174.3 | G41: =F41-SUM(L41:N41) -> 343193.18 | I41: 0 | J41: 0.0165 | K41: 0.076 | L41: =+I41*F41 -> 0 | M41: =J41*(F41-L41) -> 6239.8759 | N41: =K41*(F41-L41) -> 28741.247
E43: =SUM(E19:E42) -> 46452468 | G43: =SUM(G19:G42) -> 83468398
B46: Observações Relevantes: As tarifas de fornecimento para o segmento de uso Veicular (GNV/GNC) incidem impostos de 12% de ICMS conforme Lei 14.956/2013. 2 Emissões de Conhecimento de Transporte de GNL pela Mastergás. 2 Emissões de Locação de Unidade de redutora de pressão pela ICTUS Engenharia para Rede Local.

Sheet Jan24
C2: RELATÓRIO MENSAL DE ACOMPANHAMENTO DO CUSTO DO GÁS
C3: 45292
C5: Petrobras | D5: =SUMIF($C$19:$G$40,$C$5:$C$8,$G$19:$G$40)/SUMIF($C$19:$G$40,$C$5:$C$8,$E$19:$E$40) -> 2.349
C6: Shell | D6: =SUMIF($C$19:$G$40,$C$5:$C$8,$G$19:$G$40)/SUMIF($C$19:$G$40,$C$5:$C$8,$E$19:$E$40) -> #DIV/0!
C7: NFE | D7: =IFERROR(SUM(G37:G38)/SUM(E37:E38),"") -> 6.5887563
C8: Mastergás/Vector | D8: =H40+H39 -> 0 | M8: Poderação QDC | N8: Poderação QDR
C9: Custo Médio Ponderado real | D9: =+G42/E42 -> 2.3933782 | L9: =+C5 -> Petrobras | M9: =790000/1580000 -> 0.5 | N9: =+SUM(E19:E34)/E42 -> 0.87440793
L10: Galp | N10: =+SUM(E35)/E42 -> 0.0071935087
L11: Petrorecôncavo | M11: 0.47468354 | N11: =+SUM(E36:E36)/E42 -> 0.10790263
L12: =+C7 -> NFE | M12: 0.025316456 | N12: =+SUM(E37:E38)/E42 -> 0.010495933
L13: REDE LOCAL | M13: 0 | N13: 0
L14: Total | M14: =SUM(M9:M13) -> 1 | N14: =SUM(N9:N13) -> 1
L17: CONFORME XML DA NOTA
B18: Mês | C18: Supridor | D18: Nota Fiscal | E18: Vol m³ | F18: Compra R$ c/tributos | G18: Compra R$ s/tributos | H18: Custo | I18: ICMS | J18: PIS | K18: COFINS | L18: ICMS | M18: PIS | N18: COFINS
B19: =C3 -> 45292 | C19: Petrobras | D19: 3564-28 | E19: 143365 | F19: 421693.45 | G19: =F19-SUM(L19:N19) -> 336764.39 | H19: =+IF(G19=0,0,G19/E19) -> 2.349 | I19: 0.12 | J19: 0.0165 | K19: 0.076 | L19: =+I19*F19 -> 50603.214 | M19: =J19*(F19-L19) -> 6122.9889 | N19: =K19*(F19-L19) -> 28202.858
B20: =B19 -> 45292 | C20: Petrobras | D20: 4175-4 | E20: 513155 | F20: 1509392.8 | G20: =F20-SUM(L20:N20) -> 1205401.1 | H20: =+IF(G20=0,0,G20/E20) -> 2.349 | I20: 0.12 | J20: 0.0165 | K20: 0.076 | L20: =+I20*F20 -> 181127.14 | M20: =J20*(F20-L20) -> 21916.384 | N20: =K20*(F20-L20) -> 100948.19
B21: =B20 -> 45292 | C21: Petrobras | D21: 5618-4 | E21: 19210731 | F21: 56506395 | G21: =F21-SUM(L21:N21) -> 45126007 | H21: =+IF(G21=0,0,G21/E21) -> 2.349 | I21: 0.12 | J21: 0.0165 | K21: 0.076 | L21: =+I21*F21 -> 6780767.4 | M21: =J21*(F21-L21) -> 820472.86 | N21: =K21*(F21-L21) -> 3779147.7
B22: =B21 -> 45292 | C22: Petrobras | D22: 5690-24 | E22: 2760112 | F22: 8118586.4 | G22: =F22-SUM(L22:N22) -> 6483503.1 | H22: =+IF(G22=0,0,G22/E22) -> 2.349 | I22: 0.12 | J22: 0.0165 | K22: 0.076 | L22: =+I22*F22 -> 974230.37 | M22: =J22*(F22-L22) -> 117881.87 | N22: =K22*(F22-L22) -> 542971.06
B23: =B22 -> 45292 | C23: Petrobras | D23: 11919-6 | E23: 1250975 | F23: 3679614.7 | G23: =F23-SUM(L23:N23) -> 2938540.3 | H23: =+IF(G23=0,0,G23/E23) -> 2.349 | I23: 0.12 | J23: 0.0165 | K23: 0.076 | L23: =+I23*F23 -> 441553.76 | M23: =J23*(F23-L23) -> 53428.005 | N23: =K23*(F23-L23) -> 246092.63
B24: =B23 -> 45292 | C24: Petrobras | D24: 11920-6 | E24: 3669849.3 | F24: 10794485 | G24: =F24-SUM(L24:N24) -> 8620475.9 | H24: =+IF(G24=0,0,G24/E24) -> 2.349 | I24: 0.12 | J24: 0.0165 | K24: 0.076 | L24: =+I24*F24 -> 1295338.2 | M24: =J24*(F24-L24) -> 156735.93 | N24: =K24*(F24-L24) -> 721935.17
B25: =B24 -> 45292 | C25: Petrobras | D25: 11921-6 | E25: 6858601.7 | F25: 20173874 | G25: =F25-SUM(L25:N25) -> 16110855 | H25: =+IF(G25=0,0,G25/E25) -> 2.349 | I25: 0.12 | J25: 0.0165 | K25: 0.076 | L25: =+I25*F25 -> 2420864.8 | M25: =J25*(F25-L25) -> 292924.65 | N25: =K25*(F25-L25) -> 1349228.7
B26: =B25 -> 45292 | C26: Petrobras | D26: 432214-2 | E26: 3275303 | F26: 9116012.6 | G26: =F26-SUM(L26:N26) -> 7693686.8 | H26: =+IF(G26=0,0,G26/E26) -> 2.349 | I26: 0.07 | J26: 0.0165 | K26: 0.076 | L26: =+I26*F26 -> 638120.88 | M26: =J26*(F26-L26) -> 139885.21 | N26: =K26*(F26-L26) -> 644319.77
B27: =B26 -> 45292 | C27: Petrobras | G27: =F27-SUM(L27:N27) -> 0 | H27: =+IF(G27=0,0,G27/E27) -> 0 | J27: 0.0165 | K27: 0.076 | L27: =+I27*F27 -> 0 | M27: =J27*(F27-L27) -> 0 | N27: =K27*(F27-L27) -> 0
B28: =B27 -> 45292 | C28: Petrobras | G28: =F28-SUM(L28:N28) -> 0 | H28: =+IF(G28=0,0,G28/E28) -> 0 | J28: 0.0165 | K28: 0.076 | L28: =+I28*F28 -> 0 | M28: =J28*(F28-L28) -> 0 | N28: =K28*(F28-L28) -> 0
B29: =B28 -> 45292 | C29: Petrobras | G29: =F29-SUM(L29:N29) -> 0 | H29: =+IF(G29=0,0,G29/E29) -> 0 | J29: 0.0165 | K29: 0.076 | L29: =+I29*F29 -> 0 | M29: =J29*(F29-L29) -> 0 | N29: =K29*(F29-L29) -> 0
B30: =B29 -> 45292 | C30: Petrobras | G30: =F30-SUM(L30:N30) -> 0 | H30: =+IF(G30=0,0,G30/E30) -> 0 | J30: 0.0165 | K30: 0.076 | L30: =+I30*F30 -> 0 | M30: =J30*(F30-L30) -> 0 | N30: =K30*(F30-L30) -> 0
B31: =B30 -> 45292 | C31: Petrobras | G31: =F31-SUM(L31:N31) -> 0 | H31: =+IF(G31=0,0,G31/E31) -> 0 | J31: 0.0165 | K31: 0.076 | L31: =+I31*F31 -> 0 | M31: =J31*(F31-L31) -> 0 | N31: =K31*(F31-L31) -> 0
B32: =B31 -> 45292 | C32: Petrobras | G32: =F32-SUM(L32:N32) -> 0 | H32: =+IF(G32=0,0,G32/E32) -> 0 | J32: 0.0165 | K32: 0.076 | L32: =+I32*F32 -> 0 | M32: =J32*(F32-L32) -> 0 | N32: =K32*(F32-L32) -> 0
B33: =B32 -> 45292 | C33: Petrobras | G33: =F33-SUM(L33:N33) -> 0 | H33: =+IF(G33=0,0,G33/E33) -> 0 | J33: 0.0165 | K33: 0.076 | L33: =+I33*F33 -> 0 | M33: =J33*(F33-L33) -> 0 | N33: =K33*(F33-L33) -> 0
B34: =B33 -> 45292 | C34: Petrobras | G34: =F34-SUM(L34:N34) -> 0 | H34: =+IF(G34=0,0,G34/E34) -> 0 | J34: 0.0165 | K34: 0.076 | L34: =+I34*F34 -> 0 | M34: =J34*(F34-L34) -> 0 | N34: =K34*(F34-L34) -> 0
B35: =B34 -> 45292 | C35: Galp | D35: 147-2 | E35: 310000 | F35: 837868 | G35: =F35-SUM(L35:N35) -> 707139.65 | H35: =+IF(G35=0,0,G35/E35) -> 2.2810956 | I35: 0.07 | J35: 0.0165 | K35: 0.076 | L35: =+I35*F35 -> 58650.76 | M35: =J35*(F35-L35) -> 12857.084 | N35: =K35*(F35-L35) -> 59220.51
B36: =B35 -> 45292 | C36: Petrorecôncavo | D36: 777-1 | E36: 4650000 | F36: 12121620 | G36: =F36-SUM(L36:N36) -> 9680325.7 | H36: =+IF(G36=0,0,G36/E36) -> 2.0817905 | I36: 0.12 | J36: 0.0165 | K36: 0.076 | L36: =+I36*F36 -> 1454594.4 | M36: =J36*(F36-L36) -> 176005.92 | N36: =K36*(F36-L36) -> 810693.95
B37: =B36 -> 45292 | C37: New Fortress (Petrolina) | D37: NF-e 49 | E37: 343991 | F37: 3141497.8 | G37: =F37-SUM(L37:N37) -> 2266472.9 | H37: =+IF(G37=0,0,G37/E37) -> 6.5887563 | I37: 0.205 | J37: 0.0165 | K37: 0.076 | L37: =+I37*F37 -> 644007.05 | M37: =J37*(F37-L37) -> 41208.598 | N37: =K37*(F37-L37) -> 189809.3
B38: =B37 -> 45292 | C38: New Fortress (Garanhuns) | D38: NF-e 44 e 45 | E38: =104395+3930 -> 108325 | F38: =953387.34+35890.73 -> 989278.07 | G38: =F38-SUM(L38:N38) -> 713727.03 | H38: =+IF(G38=0,0,G38/E38) -> 6.5887563 | I38: 0.205 | J38: 0.0165 | K38: 0.076 | L38: =+I38*F38 -> 202802 | M38: =J38*(F38-L38) -> 12976.855 | N38: =K38*(F38-L38) -> 59772.181
B39: =B38 -> 45292 | C39: Contingência Rede Local (Vector) | D39: 3 Notas Fiscais | E39: 0 | F39: =56733.34+23433.33+24666.67 -> 104833.34 | G39: =F39-SUM(L39:N39) -> 95136.256 | I39: 0 | J39: 0.0165 | K39: 0.076 | L39: =+I39*F39 -> 0 | M39: =J39*(F39-L39) -> 1729.7501 | N39: =K39*(F39-L39) -> 7967.3338
B40: =B39 -> 45292 | C40: Contingência Rede Local (Mastergás) | D40: 3 Notas Fiscais | E40: 0 | F40: =97914.44+758068.85+425759.95 -> 1281743.2 | G40: =F40-SUM(L40:N40) -> 1163182 | I40: 0 | J40: 0.0165 | K40: 0.076 | L40: =+I40*F40 -> 0 | M40: =J40*(F40-L40) -> 21148.763 | N40: =K40*(F40-L40) -> 97412.486
E42: =SUM(E19:E41) -> 43094408 | G42: =SUM(G19:G41) -> 1.0314122e+08
B45: Observações Relevantes: As tarifas de fornecimento para o segmento de uso Veicular (GNV/GNC) incidem impostos de 12% de ICMS conforme Lei 14.956/2013. 3 Emissões de Conhecimento de Transporte de GNL pela Mastergás. 3 Emissões de Locação de Unidade de redutora de pressão pela ICTUS Engenharia para Rede Local.

Sheet Fev24
C2: RELATÓRIO MENSAL DE ACOMPANHAMENTO DO CUSTO DO GÁS
C3: 45323
C5: Petrobras | D5: =SUMIF($C$19:$G$75,$C$5:$C$11,$G$19:$G$75)/SUMIF($C$19:$G$75,$C$5:$C$11,$E$19:$E$75) -> 2.3079
C6: Galp | D6: =SUMIF($C$19:$G$75,$C$5:$C$11,$G$19:$G$75)/SUMIF($C$19:$G$75,$C$5:$C$11,$E$19:$E$75) -> 1.6981832
C7: Petrorecôncavo | D7: =SUMIF($C$19:$G$75,$C$5:$C$11,$G$19:$G$75)/SUMIF($C$19:$G$75,$C$5:$C$11,$E$19:$E$75) -> 2.0341141
C8: New Fortress (Petrolina) | D8: =SUMIF($C$19:$G$75,$C$5:$C$11,$G$19:$G$75)/SUMIF($C$19:$G$75,$C$5:$C$11,$E$19:$E$75) -> 6.0364483 | N8: Poderação QDC | O8: Poderação QDR
C9: New Fortress (Garanhuns) | D9: =SUMIF($C$19:$G$75,$C$5:$C$11,$G$19:$G$75)/SUMIF($C$19:$G$75,$C$5:$C$11,$E$19:$E$75) -> 6.5887563 | M9: Petrobras | N9: =1415000/1620000 -> 0.87345679 | O9: =+SUM(E19:E32)/E77 -> 0.86968091
C10: GasLocal | D10: =SUMIF($C$19:$G$75,$C$5:$C$11,$G$19:$G$75)/SUMIF($C$19:$G$75,$C$5:$C$11,$E$19:$E$75) -> #DIV/0! | M10: Galp | N10: =10000/1620000 -> 0.0061728395 | O10: =+SUM(E33)/E77 -> 0.02614238
C11: TAG | D11: =SUMIF($C$19:$G$75,$C$5:$C$11,$G$19:$G$75)/SUMIF($C$19:$G$75,$C$5:$C$11,$E$19:$E$75) -> #DIV/0! | M11: Petrorecôncavo | N11: =150000/1620000 -> 0.092592593 | O11: =+SUM(E34)/E77 -> 0.078427141
C12: Custo Médio Ponderado real | D12: =+G77/E77 -> 2.4274376 | M12: GasLocal e NewFortress | N12: =45000/1620000 -> 0.027777778 | O12: =+SUM(E37:E49)/E77 -> 0.024617852
M13: Total | N13: =SUM(N9:N12) -> 1 | O13: =SUM(O9:O12) -> 0.99886829
M17: CONFORME XML DA NOTA
B18: Mês | C18: Supridor | D18: Nota Fiscal | E18: Vol m³ | F18: Compra R$ c/tributos | G18: Compra R$ s/tributos | H18: Custo | I18: ICMS | J18: PIS | K18: COFINS | L18: CSLL | M18: ICMS | N18: PIS | O18: COFINS | P18: CSLL
B19: =C3 -> 45323 | C19: Petrobras | D19: 4185-4 | E19: 290618 | F19: 839866.37 | G19: =F19-SUM(M19:P19) -> 670717.28 | H19: =+IF(G19=0,0,G19/E19) -> 2.3079 | I19: 0.12 | J19: 0.0165 | K19: 0.076 | L19: 0 | M19: =+I19*F19 -> 100783.96 | N19: =J19*(F19-M19) -> 12194.86 | O19: =K19*(F19-M19) -> 56170.263 | P19: =L19*(F19) -> 0
B20: =B19 -> 45323 | C20: Petrobras | D20: 5632-4 | E20: 9466352 | F20: 27357117 | G20: =F20-SUM(M20:P20) -> 21847394 | H20: =+IF(G20=0,0,G20/E20) -> 2.3079 | I20: 0.12 | J20: 0.0165 | K20: 0.076 | L20: 0 | M20: =+I20*F20 -> 3282854.1 | N20: =J20*(F20-M20) -> 397225.34 | O20: =K20*(F20-M20) -> 1829644 | P20: =L20*(F20) -> 0
B21: =B20 -> 45323 | C21: Petrobras | D21: 11935-6 | E21: 3484591 | F21: 10070232 | G21: =F21-SUM(M21:P21) -> 8042087.6 | H21: =+IF(G21=0,0,G21/E21) -> 2.3079 | I21: 0.12 | J21: 0.0165 | K21: 0.076 | L21: 0 | M21: =+I21*F21 -> 1208427.9 | N21: =J21*(F21-M21) -> 146219.77 | O21: =K21*(F21-M21) -> 673497.14 | P21: =L21*(F21) -> 0
B22: =B21 -> 45323 | C22: Petrobras | D22: 11936-6 | E22: 23444877 | F22: 67754110 | G22: =F22-SUM(M22:P22) -> 54108432 | H22: =+IF(G22=0,0,G22/E22) -> 2.3079 | I22: 0.12 | J22: 0.0165 | K22: 0.076 | L22: 0 | M22: =+I22*F22 -> 8130493.2 | N22: =J22*(F22-M22) -> 983789.68 | O22: =K22*(F22-M22) -> 4531394.9 | P22: =L22*(F22) -> 0
B23: =B22 -> 45323 | C23: Petrobras | D23: 11937-6 | E23: 1903385.7 | F23: 5500656 | G23: =F23-SUM(M23:P23) -> 4392823.9 | H23: =+IF(G23=0,0,G23/E23) -> 2.3079 | I23: 0.12 | J23: 0.0165 | K23: 0.076 | L23: 0 | M23: =+I23*F23 -> 660078.72 | N23: =J23*(F23-M23) -> 79869.526 | O23: =K23*(F23-M23) -> 367883.88 | P23: =L23*(F23) -> 0
B24: =B23 -> 45323 | C24: Petrobras | G24: =F24-SUM(M24:P24) -> 0 | H24: =+IF(G24=0,0,G24/E24) -> 0 | J24: 0.0165 | K24: 0.076 | L24: 0 | M24: =+I24*F24 -> 0 | N24: =J24*(F24-M24) -> 0 | O24: =K24*(F24-M24) -> 0 | P24: =L24*(F24) -> 0
B25: =B24 -> 45323 | C25: Petrobras | G25: =F25-SUM(M25:P25) -> 0 | H25: =+IF(G25=0,0,G25/E25) -> 0 | J25: 0.0165 | K25: 0.076 | L25: 0 | M25: =+I25*F25 -> 0 | N25: =J25*(F25-M25) -> 0 | O25: =K25*(F25-M25) -> 0 | P25: =L25*(F25) -> 0
B26: =B25 -> 45323 | C26: Petrobras | G26: =F26-SUM(M26:P26) -> 0 | H26: =+IF(G26=0,0,G26/E26) -> 0 | J26: 0.0165 | K26: 0.076 | L26: 0 | M26: =+I26*F26 -> 0 | N26: =J26*(F26-M26) -> 0 | O26: =K26*(F26-M26) -> 0 | P26: =L26*(F26) -> 0
B27: =B26 -> 45323 | C27: Petrobras | G27: =F27-SUM(M27:P27) -> 0 | H27: =+IF(G27=0,0,G27/E27) -> 0 | J27: 0.0165 | K27: 0.076 | L27: 0 | M27: =+I27*F27 -> 0 | N27: =J27*(F27-M27) -> 0 | O27: =K27*(F27-M27) -> 0 | P27: =L27*(F27) -> 0
B28: =B27 -> 45323 | C28: Petrobras | G28: =F28-SUM(M28:P28) -> 0 | H28: =+IF(G28=0,0,G28/E28) -> 0 | J28: 0.0165 | K28: 0.076 | L28: 0 | M28: =+I28*F28 -> 0 | N28: =J28*(F28-M28) -> 0 | O28: =K28*(F28-M28) -> 0 | P28: =L28*(F28) -> 0
B29: =B28 -> 45323 | C29: Petrobras | G29: =F29-SUM(M29:P29) -> 0 | H29: =+IF(G29=0,0,G29/E29) -> 0 | J29: 0.0165 | K29: 0.076 | L29: 0 | M29: =+I29*F29 -> 0 | N29: =J29*(F29-M29) -> 0 | O29: =K29*(F29-M29) -> 0 | P29: =L29*(F29) -> 0
B30: =B29 -> 45323 | C30: Petrobras | G30: =F30-SUM(M30:P30) -> 0 | H30: =+IF(G30=0,0,G30/E30) -> 0 | J30: 0.0165 | K30: 0.076 | L30: 0 | M30: =+I30*F30 -> 0 | N30: =J30*(F30-M30) -> 0 | O30: =K30*(F30-M30) -> 0 | P30: =L30*(F30) -> 0
B31: =B30 -> 45323 | C31: Petrobras | G31: =F31-SUM(M31:P31) -> 0 | H31: =+IF(G31=0,0,G31/E31) -> 0 | J31: 0.0165 | K31: 0.076 | L31: 0 | M31: =+I31*F31 -> 0 | N31: =J31*(F31-M31) -> 0 | O31: =K31*(F31-M31) -> 0 | P31: =L31*(F31) -> 0
B32: =B31 -> 45323 | C32: Petrobras | G32: =F32-SUM(M32:P32) -> 0 | H32: =+IF(G32=0,0,G32/E32) -> 0 | J32: 0.0165 | K32: 0.076 | L32: 0 | M32: =+I32*F32 -> 0 | N32: =J32*(F32-M32) -> 0 | O32: =K32*(F32-M32) -> 0 | P32: =L32*(F32) -> 0
B33: =B32 -> 45323 | C33: Galp | D33: 195 | E33: =290000+870000 -> 1160000 | F33: 2334065 | G33: =F33-SUM(M33:P33) -> 1969892.5 | H33: =+IF(G33=0,0,G33/E33) -> 1.6981832 | I33: 0.07 | J33: 0.0165 | K33: 0.076 | L33: 0 | M33: =+I33*F33 -> 163384.55 | N33: =J33*(F33-M33) -> 35816.227 | O33: =K33*(F33-M33) -> 164971.71 | P33: =L33*(F33) -> 0
B34: =B33 -> 45323 | C34: Petrorecôncavo | D34: 1034 | E34: 3480000 | F34: 8863908 | G34: =F34-SUM(M34:P34) -> 7078716.9 | H34: =+IF(G34=0,0,G34/E34) -> 2.0341141 | I34: 0.12 | J34: 0.0165 | K34: 0.076 | L34: 0 | M34: =+I34*F34 -> 1063669 | N34: =J34*(F34-M34) -> 128703.94 | O34: =K34*(F34-M34) -> 592818.17 | P34: =L34*(F34) -> 0
B35: =B32 -> 45323 | C35: New Fortress (Petrolina) | D35: 3350-1 | E35: 25298.16 | F35: 193794.02 | G35: =F35-SUM(M35:P35) -> 163557.31 | H35: =+IF(G35=0,0,G35/E35) -> 6.4651859 | I35: 0.07 | J35: 0.0165 | K35: 0.076 | L35: 0 | M35: =+I35*F35 -> 13565.581 | N35: =J35*(F35-M35) -> 2973.7692 | O35: =K35*(F35-M35) -> 13697.361 | P35: =L35*(F35) -> 0
B36: =B33 -> 45323 | C36: New Fortress (Petrolina) | D36: 3351-1 | E36: 24918.63 | F36: 190886.67 | G36: =F36-SUM(M36:P36) -> 161103.58 | H36: =+IF(G36=0,0,G36/E36) -> 6.465186 | I36: 0.07 | J36: 0.0165 | K36: 0.076 | L36: 0 | M36: =+I36*F36 -> 13362.067 | N36: =J36*(F36-M36) -> 2929.156 | O36: =K36*(F36-M36) -> 13491.87 | P36: =L36*(F36) -> 0
B37: =B34 -> 45323 | C37: New Fortress (Petrolina) | D37: 3339-1 | E37: 25015.46 | F37: 126943.45 | G37: =F37-SUM(M37:P37) -> 107137.1 | H37: =+IF(G37=0,0,G37/E37) -> 4.2828354 | I37: 0.07 | J37: 0.0165 | K37: 0.076 | L37: 0 | M37: =+I37*F37 -> 8886.0415 | N37: =J37*(F37-M37) -> 1947.9472 | O37: =K37*(F37-M37) -> 8972.363 | P37: =L37*(F37) -> 0
B38: =B37 -> 45323 | C38: New Fortress (Petrolina) | D38: 3340-1 | E38: 25068.08 | F38: 127210.48 | G38: =F38-SUM(M38:P38) -> 107362.46 | H38: =+IF(G38=0,0,G38/E38) -> 4.2828356 | I38: 0.07 | J38: 0.0165 | K38: 0.076 | L38: 0 | M38: =+I38*F38 -> 8904.7336 | N38: =J38*(F38-M38) -> 1952.0448 | O38: =K38*(F38-M38) -> 8991.2367 | P38: =L38*(F38) -> 0
B39: =B38 -> 45323 | C39: New Fortress (Petrolina) | D39: 3341-1 | E39: 24629.77 | F39: 124986.23 | G39: =F39-SUM(M39:P39) -> 105485.25 | H39: =+IF(G39=0,0,G39/E39) -> 4.2828355 | I39: 0.07 | J39: 0.0165 | K39: 0.076 | L39: 0 | M39: =+I39*F39 -> 8749.0361 | N39: =J39*(F39-M39) -> 1917.9137 | O39: =K39*(F39-M39) -> 8834.0267 | P39: =L39*(F39) -> 0
B40: =B39 -> 45323 | C40: New Fortress (Petrolina) | D40: 3342-1 | E40: 25105.67 | F40: 127401.23 | G40: =F40-SUM(M40:P40) -> 107523.45 | H40: =+IF(G40=0,0,G40/E40) -> 4.2828354 | I40: 0.07 | J40: 0.0165 | K40: 0.076 | L40: 0 | M40: =+I40*F40 -> 8918.0861 | N40: =J40*(F40-M40) -> 1954.9719 | O40: =K40*(F40-M40) -> 9004.7189 | P40: =L40*(F40) -> 0
B41: =B40 -> 45323 | C41: New Fortress (Petrolina) | D41: 3343-1 | E41: 24318.85 | F41: 123408.44 | G41: =F41-SUM(M41:P41) -> 104153.64 | H41: =+IF(G41=0,0,G41/E41) -> 4.2828357 | I41: 0.07 | J41: 0.0165 | K41: 0.076 | L41: 0 | M41: =+I41*F41 -> 8638.5908 | N41: =J41*(F41-M41) -> 1893.7025 | O41: =K41*(F41-M41) -> 8722.5085 | P41: =L41*(F41) -> 0
B42: =B41 -> 45323 | C42: New Fortress (Petrolina) | D42: 3344-1 | E42: 23533.03 | F42: 119420.71 | G42: =F42-SUM(M42:P42) -> 100788.09 | H42: =+IF(G42=0,0,G42/E42) -> 4.2828354 | I42: 0.07 | J42: 0.0165 | K42: 0.076 | L42: 0 | M42: =+I42*F42 -> 8359.4497 | N42: =J42*(F42-M42) -> 1832.5108 | O42: =K42*(F42-M42) -> 8440.6558 | P42: =L42*(F42) -> 0
B43: =B42 -> 45323 | C43: New Fortress (Petrolina) | D43: 3345-1 | E43: 25115.78 | F43: 127452.54 | G43: =F43-SUM(M43:P43) -> 107566.76 | H43: =+IF(G43=0,0,G43/E43) -> 4.2828356 | I43: 0.07 | J43: 0.0165 | K43: 0.076 | L43: 0 | M43: =+I43*F43 -> 8921.6778 | N43: =J43*(F43-M43) -> 1955.7592 | O43: =K43*(F43-M43) -> 9008.3455 | P43: =L43*(F43) -> 0
B44: =B43 -> 45323 | C44: New Fortress (Petrolina) | D44: 3346-1 | E44: 23780.64 | F44: 120677.24 | G44: =F44-SUM(M44:P44) -> 101848.57 | H44: =+IF(G44=0,0,G44/E44) -> 4.2828357 | I44: 0.07 | J44: 0.0165 | K44: 0.076 | L44: 0 | M44: =+I44*F44 -> 8447.4068 | N44: =J44*(F44-M44) -> 1851.7922 | O44: =K44*(F44-M44) -> 8529.4673 | P44: =L44*(F44) -> 0
B45: =B44 -> 45323 | C45: New Fortress (Petrolina) | D45: 3347-1 | E45: 24456.29 | F45: 124105.89 | G45: =F45-SUM(M45:P45) -> 104742.27 | H45: =+IF(G45=0,0,G45/E45) -> 4.2828356 | I45: 0.07 | J45: 0.0165 | K45: 0.076 | L45: 0 | M45: =+I45*F45 -> 8687.4123 | N45: =J45*(F45-M45) -> 1904.4049 | O45: =K45*(F45-M45) -> 8771.8043 | P45: =L45*(F45) -> 0
B46: =B45 -> 45323 | C46: New Fortress (Petrolina) | D46: 3348-1 | E46: 24907.44 | F46: 126395.3 | G46: =F46-SUM(M46:P46) -> 106674.47 | H46: =+IF(G46=0,0,G46/E46) -> 4.2828357 | I46: 0.07 | J46: 0.0165 | K46: 0.076 | L46: 0 | M46: =+I46*F46 -> 8847.671 | N46: =J46*(F46-M46) -> 1939.5359 | O46: =K46*(F46-M46) -> 8933.6198 | P46: =L46*(F46) -> 0
B47: =B46 -> 45323 | C47: New Fortress (Petrolina) | D47: 57-1 | E47: 741865 | F47: 6775082.1 | G47: =F47-SUM(M47:P47) -> 4887967.7 | H47: =+IF(G47=0,0,G47/E47) -> 6.5887563 | I47: 0.205 | J47: 0.0165 | K47: 0.076 | L47: 0 | M47: =+I47*F47 -> 1388891.8 | N47: =J47*(F47-M47) -> 88872.14 | O47: =K47*(F47-M47) -> 409350.46 | P47: =L47*(F47) -> 0
B48: =B37 -> 45323 | C48: New Fortress (Garanhuns) | D48: 47-1 | E48: 104557 | F48: 954866.8 | G48: =F48-SUM(M48:P48) -> 688900.59 | H48: =+IF(G48=0,0,G48/E48) -> 6.5887563 | I48: 0.205 | J48: 0.0165 | K48: 0.076 | L48: 0 | M48: =+I48*F48 -> 195747.69 | N48: =J48*(F48-M48) -> 12525.465 | O48: =K48*(F48-M48) -> 57693.052 | P48: =L48*(F48) -> 0
B49: =B48 -> 45323 | C49: GasLocal | D49: 165 | F49: 970981.12 | G49: =F49-SUM(M49:P49) -> 925830.5 | I49: 0 | J49: 0.0065 | K49: 0.03 | L49: 0.01 | M49: =+I49*F49 -> 0 | N49: =J49*(F49-M49) -> 6311.3773 | O49: =K49*(F49-M49) -> 29129.434 | P49: =L49*(F49) -> 9709.8112 | Q49: ok
B50: =B48 -> 45323 | C50: TAG | D50: 13864 | F50: 4052.23 | G50: =F50-SUM(M50:P50) -> 3419.9808 | I50: 0.07 | J50: 0.0165 | K50: 0.076 | L50: 0 | M50: =+I50*F50 -> 283.6561 | N50: =J50*(F50-M50) -> 62.181469 | O50: =K50*(F50-M50) -> 286.41162 | P50: =L50*(F50) -> 0
B51: =B50 -> 45323 | C51: TAG | D51: 13863 | F51: 2776.5 | G51: =F51-SUM(M51:P51) -> 2343.2966 | I51: 0.07 | J51: 0.0165 | K51: 0.076 | L51: 0 | M51: =+I51*F51 -> 194.355 | N51: =J51*(F51-M51) -> 42.605393 | O51: =K51*(F51-M51) -> 196.24302 | P51: =L51*(F51) -> 0
B52: =B51 -> 45323 | C52: TAG | D52: 13906 | F52: 4618.64 | G52: =F52-SUM(M52:P52) -> 3898.0167 | I52: 0.07 | J52: 0.0165 | K52: 0.076 | L52: 0 | M52: =+I52*F52 -> 323.3048 | N52: =J52*(F52-M52) -> 70.873031 | O52: =K52*(F52-M52) -> 326.44548 | P52: =L52*(F52) -> 0
B53: =B52 -> 45323 | C53: TAG | D53: 13907 | F53: 8965.58 | G53: =F53-SUM(M53:P53) -> 7566.7254 | I53: 0.07 | J53: 0.0165 | K53: 0.076 | L53: 0 | M53: =+I53*F53 -> 627.5906 | N53: =J53*(F53-M53) -> 137.57683 | O53: =K53*(F53-M53) -> 633.68719 | P53: =L53*(F53) -> 0
B54: =B53 -> 45323 | C54: TAG | D54: 3781 | F54: 255999.54 | G54: =F54-SUM(M54:P54) -> 204441.23 | I54: 0.12 | J54: 0.0165 | K54: 0.076 | L54: 0 | M54: =+I54*F54 -> 30719.945 | N54: =J54*(F54-M54) -> 3717.1133 | O54: =K54*(F54-M54) -> 17121.249 | P54: =L54*(F54) -> 0
B55: =B54 -> 45323 | C55: TAG | D55: 13865 | F55: 11599.54 | G55: =F55-SUM(M55:P55) -> 9789.7218 | I55: 0.07 | J55: 0.0165 | K55: 0.076 | L55: 0 | M55: =+I55*F55 -> 811.9678 | N55: =J55*(F55-M55) -> 177.99494 | O55: =K55*(F55-M55) -> 819.85549 | P55: =L55*(F55) -> 0
B56: =B55 -> 45323 | C56: TAG | D56: 13875 | F56: 16409.14 | G56: =F56-SUM(M56:P56) -> 13848.904 | I56: 0.07 | J56: 0.0165 | K56: 0.076 | L56: 0 | M56: =+I56*F56 -> 1148.6398 | N56: =J56*(F56-M56) -> 251.79825 | O56: =K56*(F56-M56) -> 1159.798 | P56: =L56*(F56) -> 0
B57: =B56 -> 45323 | C57: TAG | D57: 13876 | F57: 7800.55 | G57: =F57-SUM(M57:P57) -> 6583.4692 | I57: 0.07 | J57: 0.0165 | K57: 0.076 | L57: 0 | M57: =+I57*F57 -> 546.0385 | N57: =J57*(F57-M57) -> 119.69944 | O57: =K57*(F57-M57) -> 551.34287 | P57: =L57*(F57) -> 0
B58: =B57 -> 45323 | C58: TAG | D58: 13877 | F58: 2604.74 | G58: =F58-SUM(M58:P58) -> 2198.3354 | I58: 0.07 | J58: 0.0165 | K58: 0.076 | L58: 0 | M58: =+I58*F58 -> 182.3318 | N58: =J58*(F58-M58) -> 39.969735 | O58: =K58*(F58-M58) -> 184.10302 | P58: =L58*(F58) -> 0
B59: =B58 -> 45323 | C59: TAG | D59: 13878 | F59: 5023.81 | G59: =F59-SUM(M59:P59) -> 4239.97 | I59: 0.07 | J59: 0.0165 | K59: 0.076 | L59: 0 | M59: =+I59*F59 -> 351.6667 | N59: =J59*(F59-M59) -> 77.090364 | O59: =K59*(F59-M59) -> 355.08289 | P59: =L59*(F59) -> 0
B60: =B59 -> 45323 | C60: TAG | D60: 13908 | F60: 3564.24 | G60: =F60-SUM(M60:P60) -> 3008.1295 | I60: 0.07 | J60: 0.0165 | K60: 0.076 | L60: 0 | M60: =+I60*F60 -> 249.4968 | N60: =J60*(F60-M60) -> 54.693263 | O60: =K60*(F60-M60) -> 251.92048 | P60: =L60*(F60) -> 0
B61: =B60 -> 45323 | C61: TAG | D61: 13879 | F61: 17283.28 | G61: =F61-SUM(M61:P61) -> 14586.656 | I61: 0.07 | J61: 0.0165 | K61: 0.076 | L61: 0 | M61: =+I61*F61 -> 1209.8296 | N61: =J61*(F61-M61) -> 265.21193 | O61: =K61*(F61-M61) -> 1221.5822 | P61: =L61*(F61) -> 0
B62: =B61 -> 45323 | C62: TAG | D62: 13917 | F62: 5721.54 | G62: =F62-SUM(M62:P62) -> 4828.8367 | I62: 0.07 | J62: 0.0165 | K62: 0.076 | L62: 0 | M62: =+I62*F62 -> 400.5078 | N62: =J62*(F62-M62) -> 87.797031 | O62: =K62*(F62-M62) -> 404.39845 | P62: =L62*(F62) -> 0
... B72: =B71 -> 45323 | C72: TAG | D72: 3787 | F72: 170911.39 | G72: =F72-SUM(M72:P72) -> 136489.84 | I72: 0.12 | J72: 0.0165 | K72: 0.076 | L72: 0 | M72: =+I72*F72 -> 20509.367 | N72: =J72*(F72-M72) -> 2481.6334 | O72: =K72*(F72-M72) -> 11430.554 | P72: =L72*(F72) -> 0
B73: =B50 -> 45323 | C73: TAG | D73: 3780 | F73: 177750.95 | G73: =F73-SUM(M73:P73) -> 141951.91 | I73: 0.12 | J73: 0.0165 | K73: 0.076 | L73: 0 | M73: =+I73*F73 -> 21330.114 | N73: =J73*(F73-M73) -> 2580.9438 | O73: =K73*(F73-M73) -> 11887.984 | P73: =L73*(F73) -> 0
B74: =B73 -> 45323 | C74: Contingência Rede Local (Vector) | D74: 1 Nota Fiscal | F74: 37000 | G74: =F74-SUM(M74:P74) -> 33577.5 | I74: 0 | J74: 0.0165 | K74: 0.076 | L74: 0 | M74: =+I74*F74 -> 0 | N74: =J74*(F74-M74) -> 610.5 | O74: =K74*(F74-M74) -> 2812 | P74: =L74*(F74) -> 0
B75: =B74 -> 45323 | C75: Contingência Rede Local (Mastergás) | D75: 3 Notas Fiscais | F75: =71625.34+264044.55+521497.9 -> 857167.79 | G75: =F75-SUM(M75:P75) -> 777879.77 | I75: 0 | J75: 0.0165 | K75: 0.076 | L75: 0 | M75: =+I75*F75 -> 0 | N75: =J75*(F75-M75) -> 14143.269 | O75: =K75*(F75-M75) -> 65144.752 | P75: =L75*(F75) -> 0
